Workbook

Sheet Test Plan
A1: iSpace.az — Test Planı
A4: 1. ÜMUMİ MƏLUMAT
A5: Test obyekti | B5: iSpace.az — Apple Premium Partner e-commerce saytı (https://ispace.az). ASBIS platforması üzərində qurulub; AZ / EN / RU dillərində işləyir.
A6: Mühit | B6: Production (public). Ayrıca test mühiti yoxdur — bütün testlər canlı sistemə qarşı, etik qaydalara əməl edilməklə aparılır.
A7: Platforma / brauzer | B7: Desktop, Google Chrome (son stabil versiya). Ekran: 1920×1080.
A8: Məqsəd | B8: Saytın gəlir gətirən əsas axınını — Kataloq → Məhsul → Səbət — həm Web, həm API səviyyəsində yoxlamaq; manual və avtomat testləri əsaslandırılmış şəkildə ayırmaq; regression dəstini stabil avtomatlaşdırmaq.
A9: 2. SCOPE — TEST EDİLƏNLƏR
A10: Axtarış | B10: Məhsul axtarışı: ad, model, məhsul kodu, qismən söz, Azərbaycan hərfləri və.s
A11: Kateqoriya / listing | B11: Filtrlər (stok, qiymət aralığı, seriya, ekran, yaddaş, kamera, SIM, rəng, əlavə xüsusiyyətlər) və onların kombinasiyası, filtr sayğacları, sıralama (Məşhur / Aşağı qiymət / Yüksək qiymət), pagination.
A12: Məhsul səhifəsi (PDP) | B12: Qiymət və aylıq ödəniş göstərişi, variant seçimi (yaddaş / rəng), məhsul kodu, stok vəziyyəti, ön sifariş, əlavə proqram seçimi, miqdar, çatdırılma növü seçimi (submit-siz). 'Bütün proqramlara baxın' — taksit pəncərəsi: müddətlər, tərəfdaşlar, aylıq və ümumi məbləğ.
A13: Səbət | B13: Məhsul əlavə etmə (listing və PDP), miqdar dəyişmə, silmə, cəm hesablanması, qoruma proqramı sətri, endirim göstərişi, mini-səbət, səbətdən taksit pəncərəsi, səhifə yenilənəndə və sessiyada vəziyyətin qorunması.
A14: Lokalizasiya və xidmət səhifələri | B14: AZ / EN / RU keçidi scope-dakı səhifələrdə; tərcümə olunmamış və ya səhv mətnlər. Trade In və 'Çatdırılma və ödəniş' məlumat səhifələrinin açılması və şərtlərin səhifə daxilində ardıcıllığı (müraciət göndərilmir).
A15: 3. OUT OF SCOPE — VƏ SƏBƏBİ
A16: Checkout / sifariş / '1 kliklə al' | B16: Prodda real sifariş yaradır, operator müştəri ilə əlaqə saxlayır — geri qaytarıla bilməyən biznes əməliyyatı. Checkout-da yalnız göndərmədən yoxlanıla bilənlər test edildi: telefon və e-poçt validasiyası, çatdırılma haqqının xülasədə göstərilməsi, boş məcburi sahələr, mağazadan götürmə və rayon çatdırılma şərtləri. Sifariş heç vaxt göndərilmir; tapıntılar BUG-025, BUG-028, BUG-030.
A17: Ödəniş | B17: Real maliyyə əməliyyatı; test kartı imkanı yoxdur.
A18: Kredit və Trade-in müraciəti | B18: Real maliyyə/biznes müraciəti yaradır; bank və qiymətləndirmə prosesləri xarici sistemlərdir.
A19: Qeydiyyat / login | B19: Prodda hesab yaradılmır; login axını test edilmir.
A20: Əks əlaqə və abunə formu (submit) | B20: Real əməkdaşlara müraciət / spam yaradır. Yalnız client-side validasiya yoxlanıla bilər.
A21: Performance / load testing | B21: Prod sistemə yük vermək etik deyil və icazəsizdir.
A22: Security testing | B22: Injection, brute force kimi hücumlar prodda icazəsizdir. Yalnız passiv müşahidələr qeyd olunur.
A23: Cross-browser, mobil, responsive, əlçatanlıq | B23: Risk əsaslı olaraq desktop Chrome seçilib. Əlçatanlıq (klaviatura ilə naviqasiya, fokus, şəkillərin alt mətni) ayrıca alət və metodika (WCAG) tələb edir — növbəti mərhələyə saxlanılır.
A24: Mağaza xəritəsi, sosial şəbəkə linkləri | B24: Üçüncü tərəf servislərdir; yalnız linkin düzgün ünvana aparması yoxlanıla bilər.
A25: 4. RİSKLƏR VƏ AZALDILMASI
A26: R1 — Bot qoruması (Cloudflare) | B26: Avtomat sorğular bloklana bilər → testlər flaky olar. Azaldılma: 1-ci gün 30 ardıcıl sorğu + headless/headed Chrome sınağı; problem olarsa müəllimə dərhal məlumat.
A27: R2 — Dinamik katalog | B27: Qiymət, stok, məhsul adları gündəlik dəyişir. Azaldılma: test datası koda yazılmır, icra zamanı API-dən götürülür; assertion-lar konkret dəyərə yox, uyğunluq qaydalarına (oracle) əsaslanır.
A28: R3 — Tələb sənədinin olmaması | B28: Rəsmi spesifikasiya yoxdur. Azaldılma: tələblər müşahidəyə əsaslanan biznes qaydaları (BR-01…) kimi yazılıb və RTM-də izlənir; təsdiqlənməmiş fərziyyələr avtomat assertion-a çevrilmir.
A29: R4 — Prodda yan təsir | B29: Testlər real data yarada bilər. Azaldılma: yalnız geri qaytarıla bilən əməliyyatlar (axtarış, filtr, səbət); səbət test sonunda təmizlənir.
A30: R5 — Asinxron UI | B30: Loader ('Mağazanın yüklənməsi'), lazy-load, banner karuseli. Azaldılma: yalnız explicit wait, Thread.sleep qadağandır.
A31: R6 — Paylaşılan vəziyyət | B31: Başqa istifadəçilərin hərəkəti stoku dəyişə bilər. Azaldılma: qlobal say və sıraya ('ilk məhsul X-dir') assertion yazılmır.
A32: R7 — robots.txt məhdudiyyəti | B32: robots.txt /cart, /search, /checkout, /login və parametrli URL-ləri botlar üçün qadağan edir. Azaldılma: avtomat testlərin həcmi minimal, hər test tək brauzer sessiyası ilə; real sifariş/müraciət göndərilmir.
A33: 5. TEST SƏVİYYƏLƏRİ VƏ NÖVLƏRİ
A34: Səviyyələr | B34: API (backend məntiqi, validasiya, kontrakt) → UI / E2E (istifadəçi axınları). Test piramidası: kombinasiya və validasiyaların çoxu API-də, UI-da yalnız kritik axınlar və UI-a məxsus davranış.
A35: Növlər | B35: Functional (pozitiv / neqativ), Smoke, Regression, Localization, Exploratory (session-based), UI–API uyğunluğu.
A36: Test dizayn texnikaları | B36: Equivalence Partitioning, Boundary Value Analysis, Decision Table (filtr kombinasiyaları), State Transition (səbət vəziyyətləri), Error Guessing, Consistency Oracle (listing = PDP = səbət).
A37: 6. PRİORİTET VƏ SEVERİTY ŞKALASI
A38: Test case prioriteti | B38: Risk = biznes təsiri × baş vermə ehtimalı. Critical: gəlir axınını bloklayır (səbətə əlavə, qiymət). High: əsas funksiya səhv işləyir (filtr, sıralama, axtarış). Medium: köməkçi funksiya. Low: kosmetik.
A39: Bug severity | B39: Critical (Blocker) / High (Major) / Medium (Moderate) / Low — kurs materialındakı şkala.
A40: Bug priority | B40: P1 — dərhal · P2 — yüksək · P3 — orta · P4 — aşağı.
A41: 7. AVTOMATLAŞDIRMA YANAŞMASI
A42: Seçim meyarları | B42: 'Decision Matrix' sheet-inə əsasən: təkrarlanma tezliyi, risk, determinizm, kənar asılılıq, yoxlamanın təbiəti (kodlar A1–A3, M1–M5).
A43: Ardıcıllıq | B43: Əvvəl API testləri (sürətli, stabil, UI üçün data mənbəyi), sonra UI testləri.
A44: Assertion qaydası | B44: API: status + struktur/schema + biznes dəyərləri (+ mümkün olduqda cross-check). UI: ekranda real nəticə (mətn, dəyər, element vəziyyəti).
A45: Stabillik meyarı | B45: Suite ard-arda 10 dəfə yaşıl; testlər istənilən sırada və tək-tək keçir; retry ilə flaky gizlədilmir.
A46: Alətlər / arxitektura | B46: Müəllimin verdiyi Gauge Test Automation arxitekturası (Gauge + Selenium WebDriver + RestAssured, Maven, `mvn test`) — dəyişdirilmədən istifadə olunur.
A47: 8. ETİKA QAYDALARI (PROD)
A48: Qaydalar | B48: Yük testi yoxdur; hücum xarakterli sorğu yoxdur; real sifariş, müraciət, abunə yaradılmır; şəxsi məlumat istifadə olunmur; sorğular arasında makul interval saxlanılır.
A49: 9. GİRİŞ / ÇIXIŞ MEYARLARI
A50: Giriş meyarı | B50: Sayt əlçatandır; API siyahısı və arxitektura əldədir; scope təsdiqlənib.
A51: Çıxış meyarı | B51: Bütün Critical/High case-lər icra olunub; regression dəsti (40 case) seçilib: 38-i (95%) Gauge ilə avtomatlaşdırılıb və stabil keçir (35 Pass + 3 bilinən bug: BUG-016, BUG-017, BUG-032), 2-si prod riski səbəbindən manual regression-dur; ümumi 126 case-dən 51-i (40%) avtomatdır; tapılan bug-lar sənədləşdirilib; README hazırdır.
A52: 10. NƏTİCƏ SƏNƏDLƏRİ
A53: Deliverables | B53: Bu Excel faylı (Test Plan, Test Scenarios, Web Test Cases, RTM, Decision Matrix, Bug Reports, Test Summary Report) + avtomatlaşdırma layihəsi (GitHub repo, LAYIHE.md).
A54: 11. RESURSLAR
A55: Komanda | B55: QA mühəndisi (tələbə) — manual test dizaynı, icra, bug report, avtomatlaşdırma
A56: Alətlər | B56: Excel (test sənədləri), Google Chrome (inkognito), iSpace Test İcrası tracker-i, IntelliJ IDEA + Gauge + Selenium + RestAssured + Maven (avtomatlaşdırma), Git / GitHub
A57: Test mühiti | B57: Production — https://ispace.az (public); API — müəllimin bank sandbox-u (https://api.anarabbas.com)
A58: 12. TƏSDİQ (APPROVAL)
A59: Hazırladı | B59: Məleykə Əlili

Sheet Test Scenarios
A1: Test Ssenariləri — iSpace.az
A4: Ssenari ID | B4: Modul | C4: Test ssenarisi | D4: Prioritet | E4: Əlaqəli tələb | F4: Test case sayı | G4: Avtomat | H4: Regression
A5: SC-001 | B5: Kateqoriya (PLP) | C5: İstifadəçi iPhone kateqoriyasını açdıqda məhsul kartları ad, qiymət, aylıq ödəniş və stok vəziyyətinə uyğun düymə ilə göstərilməli, kartdakı qiymət məhsul səhifəsindəki ilə eyni olmalıdır. | D5: P1 — Critical | E5: UJ-01 · BR-01, BR-11 | F5: =COUNTIF('Web Test Cases'!$B$5:$B$130,A5) -> 4 | G5: =COUNTIFS('Web Test Cases'!$B$5:$B$130,A5,'Web Test Cases'!$M$5:$M$130,"Avtomat") -> 4 | H5: =COUNTIFS('Web Test Cases'!$B$5:$B$130,A5,'Web Test Cases'!$O$5:$O$130,"Bəli") -> 4
A6: SC-002 | B6: Kateqoriya (PLP) | C6: İstifadəçi stok, yaddaş və rəng filtrlərini tək-tək və birlikdə tətbiq etdikdə yalnız seçimə uyğun məhsullar göstərilməli, filtr sayğacları nəticə sayına bərabər olmalıdır. | D6: P2 — High | E6: UJ-03 · BR-02, BR-12 | F6: =COUNTIF('Web Test Cases'!$B$5:$B$130,A6) -> 9 | G6: =COUNTIFS('Web Test Cases'!$B$5:$B$130,A6,'Web Test Cases'!$M$5:$M$130,"Avtomat") -> 7 | H6: =COUNTIFS('Web Test Cases'!$B$5:$B$130,A6,'Web Test Cases'!$O$5:$O$130,"Bəli") -> 3
A7: SC-003 | B7: Kateqoriya (PLP) | C7: İstifadəçi qiymət aralığı daxil etdikdə yalnız bu aralıqdakı (sərhədlər daxil) məhsullar göstərilməli, keçərsiz dəyər daxil etdikdə sistem onu rədd etməlidir. | D7: P2 — High | E7: UJ-03 · BR-04 | F7: =COUNTIF('Web Test Cases'!$B$5:$B$130,A7) -> 5 | G7: =COUNTIFS('Web Test Cases'!$B$5:$B$130,A7,'Web Test Cases'!$M$5:$M$130,"Avtomat") -> 3 | H7: =COUNTIFS('Web Test Cases'!$B$5:$B$130,A7,'Web Test Cases'!$O$5:$O$130,"Bəli") -> 2
A8: SC-004 | B8: Kateqoriya (PLP) | C8: İstifadəçi qiymətə görə sıralama seçdikdə və səhifələr arasında keçdikdə məhsullar bütün səhifələr boyu artan və ya azalan sırada, hər biri yalnız bir dəfə göstərilməlidir. | D8: P2 — High | E8: UJ-03 · BR-03, BR-05, BR-14 | F8: =COUNTIF('Web Test Cases'!$B$5:$B$130,A8) -> 5 | G8: =COUNTIFS('Web Test Cases'!$B$5:$B$130,A8,'Web Test Cases'!$M$5:$M$130,"Avtomat") -> 4 | H8: =COUNTIFS('Web Test Cases'!$B$5:$B$130,A8,'Web Test Cases'!$O$5:$O$130,"Bəli") -> 2
A9: SC-005 | B9: Kateqoriya (PLP) | C9: İstifadəçi alt-kateqoriya çipini və ya Seriya filtrini seçdikdə yalnız həmin seriyanın məhsulları göstərilməli, sayğaclar ümumi məhsul sayı ilə uyğun olmalıdır. | D9: P2 — High | E9: UJ-03 · BR-12, BR-18 | F9: =COUNTIF('Web Test Cases'!$B$5:$B$130,A9) -> 3 | G9: =COUNTIFS('Web Test Cases'!$B$5:$B$130,A9,'Web Test Cases'!$M$5:$M$130,"Avtomat") -> 3 | H9: =COUNTIFS('Web Test Cases'!$B$5:$B$130,A9,'Web Test Cases'!$O$5:$O$130,"Bəli") -> 1
A10: SC-006 | B10: Kateqoriya (PLP) | C10: İstifadəçi texniki xüsusiyyət filtrlərini (ekran, kamera, video, SIM, məhsul tipi) seçdikdə nəticələr məhsulun PDP-dəki texniki göstəriciləri ilə uyğun olmalıdır. | D10: P3 — Medium | E10: UJ-03 · BR-18 | F10: =COUNTIF('Web Test Cases'!$B$5:$B$130,A10) -> 5 | G10: =COUNTIFS('Web Test Cases'!$B$5:$B$130,A10,'Web Test Cases'!$M$5:$M$130,"Avtomat") -> 3 | H10: =COUNTIFS('Web Test Cases'!$B$5:$B$130,A10,'Web Test Cases'!$O$5:$O$130,"Bəli") -> 0
A11: SC-007 | B11: Kateqoriya (PLP) | C11: İstifadəçi Rəng və 'Əlavə xüsusiyyətlər' filtrlərini seçdikdə uyğun məhsulların hamısı tapılmalı, filtr dəyərləri azərbaycanca göstərilməlidir. | D11: P2 — High | E11: UJ-03 · BR-18 | F11: =COUNTIF('Web Test Cases'!$B$5:$B$130,A11) -> 4 | G11: =COUNTIFS('Web Test Cases'!$B$5:$B$130,A11,'Web Test Cases'!$M$5:$M$130,"Avtomat") -> 1 | H11: =COUNTIFS('Web Test Cases'!$B$5:$B$130,A11,'Web Test Cases'!$O$5:$O$130,"Bəli") -> 0
A12: SC-008 | B12: Kateqoriya (PLP) | C12: İstifadəçi filtr seçib 'Tətbiq et' basdıqda nəticə və digər qrupların sayğacları yenilənməli, aktiv filtrlər görünməli və tək-tək silinə bilməlidir. | D12: P2 — High | E12: UJ-03 · BR-02, BR-12 | F12: =COUNTIF('Web Test Cases'!$B$5:$B$130,A12) -> 4 | G12: =COUNTIFS('Web Test Cases'!$B$5:$B$130,A12,'Web Test Cases'!$M$5:$M$130,"Avtomat") -> 2 | H12: =COUNTIFS('Web Test Cases'!$B$5:$B$130,A12,'Web Test Cases'!$O$5:$O$130,"Bəli") -> 0
A13: SC-009 | B13: Kateqoriya (PLP) | C13: İstifadəçi filtrləri sıralama, səhifələmə, dil dəyişmə və brauzerin 'Geri' düyməsi ilə birlikdə istifadə etdikdə filtr vəziyyəti qorunmalı və nəticə dəqiq olmalıdır. | D13: P2 — High | E13: UJ-03 · BR-18 | F13: =COUNTIF('Web Test Cases'!$B$5:$B$130,A13) -> 7 | G13: =COUNTIFS('Web Test Cases'!$B$5:$B$130,A13,'Web Test Cases'!$M$5:$M$130,"Avtomat") -> 4 | H13: =COUNTIFS('Web Test Cases'!$B$5:$B$130,A13,'Web Test Cases'!$O$5:$O$130,"Bəli") -> 2
A14: SC-010 | B14: Məhsul səhifəsi (PDP) | C14: İstifadəçi məhsul səhifəsini açdıqda ad, məhsul kodu, qiymət, aylıq ödəniş, şəkillər və texniki göstəricilər listing ilə uyğun göstərilməlidir. | D14: P1 — Critical | E14: UJ-01 · BR-01, BR-08 | F14: =COUNTIF('Web Test Cases'!$B$5:$B$130,A14) -> 3 | G14: =COUNTIFS('Web Test Cases'!$B$5:$B$130,A14,'Web Test Cases'!$M$5:$M$130,"Avtomat") -> 2 | H14: =COUNTIFS('Web Test Cases'!$B$5:$B$130,A14,'Web Test Cases'!$O$5:$O$130,"Bəli") -> 2
A15: SC-011 | B15: Məhsul səhifəsi (PDP) | C15: İstifadəçi məhsul səhifəsində variant, miqdar, qoruma proqramı və çatdırılma seçdikdə məhsul məlumatı və məbləğ seçimə uyğun yenilənməlidir. | D15: P2 — High | E15: UJ-01 · BR-06, BR-15 | F15: =COUNTIF('Web Test Cases'!$B$5:$B$130,A15) -> 7 | G15: =COUNTIFS('Web Test Cases'!$B$5:$B$130,A15,'Web Test Cases'!$M$5:$M$130,"Avtomat") -> 5 | H15: =COUNTIFS('Web Test Cases'!$B$5:$B$130,A15,'Web Test Cases'!$O$5:$O$130,"Bəli") -> 3
A16: SC-012 | B16: Məhsul səhifəsi (PDP) | C16: İstifadəçi stokda olmayan və ya mövcud olmayan məhsulu açdıqda məhsul alına bilməməli və aydın vəziyyət mesajı göstərilməlidir. | D16: P2 — High | E16: UJ-01 · BR-11 | F16: =COUNTIF('Web Test Cases'!$B$5:$B$130,A16) -> 2 | G16: =COUNTIFS('Web Test Cases'!$B$5:$B$130,A16,'Web Test Cases'!$M$5:$M$130,"Avtomat") -> 1 | H16: =COUNTIFS('Web Test Cases'!$B$5:$B$130,A16,'Web Test Cases'!$O$5:$O$130,"Bəli") -> 1
... A28: SC-024 | B28: Xidmət səhifələri | C28: İstifadəçi Trade In və 'Çatdırılma və ödəniş' məlumat səhifələrini açdıqda səhifə açılmalı, şərtlər tam və seçilmiş dildə göstərilməli, eyni şərt (müddət, qiymət) səhifənin bütün hissələrində (mətn, cədvəl, FAQ) eyni yazılmalıdır. | D28: P3 — Medium | E28: UJ-01, UJ-05 · BR-10, BR-13 | F28: =COUNTIF('Web Test Cases'!$B$5:$B$130,A28) -> 3 | G28: =COUNTIFS('Web Test Cases'!$B$5:$B$130,A28,'Web Test Cases'!$M$5:$M$130,"Avtomat") -> 0 | H28: =COUNTIFS('Web Test Cases'!$B$5:$B$130,A28,'Web Test Cases'!$O$5:$O$130,"Bəli") -> 0
C29: Cəmi | F29: =SUM(F5:F28) -> 126 | G29: =SUM(G5:G28) -> 74 | H29: =SUM(H5:H28) -> 40

Sheet Web Test Cases
A1: Test Case-lər — iSpace.az (Web)
A4: Test Case ID | B4: Ssenari ID | C4: Modul | D4: Başlıq (Title) | E4: Prioritet | F4: Test növü | G4: Ön şərtlər | H4: Test addımları | I4: Test datası | J4: Gözlənilən nəticə | K4: Faktiki nəticə | L4: Status | M4: Avtomat / Manual | N4: Səbəb (Decision Matrix) | O4: Regression | P4: Smoke | Q4: Bug ID | R4: Əlaqəli tələb (BR) | S4: Avtomatlaşdırma statusu (Gauge) | T4: Avtomatlaşdırma qeydi
A5: TC_PLP_POS_001 | B5: SC-001 | C5: Kateqoriya (PLP) | D5: iPhone kateqoriyası açıldıqda başlıq, breadcrumb, məhsul sayı və məhsul kartları göstərilir | E5: P1 — Critical | F5: Pozitiv · Funksional | G5: Ümumi ön şərt (P0): Chrome son versiya, inkognito pəncərə, 1920×1080, AZ dili, login olmadan | H5: 1. Brauzerdə https://ispace.az/category/iphone ünvanını aç 2. 'Mağazanın yüklənməsi' yazısı yox olana qədər gözlə 3. Səhifə başlığını oxu 4. Başlığın üstündəki breadcrumb-u oxu 5. Səhifənin yuxarısındakı 'N Məhsul' mətnindən nəticə sayını qeyd et 6. Səhifədə məhsul kartlarının göstərildiyinə bax | I5: URL: /category/iphone | J5: 1. Səhifə başlığı 'iPhone'. 2. Breadcrumb: 'Ana səhifə > iPhone'. 3. 'N Məhsul' mətni göstərilir, N > 0. 4. Ən azı 1 məhsul kartı var. | K5: Səhifə yükləndi; başlıq, breadcrumb, məhsul sayı və kartlar göstərildi. Bütün yoxlama nöqtələri gözlənilən nəticəyə uyğundur. | L5: Pass | M5: Avtomat | N5: A1 — əsas axının giriş nöqtəsi, hər release-də | O5: Bəli | P5: Bəli | R5: BR-01, BR-11 | S5: Avtomatlaşdırılıb — PASS, 16.10.2026 | T5: —
A6: TC_PLP_POS_002 | B6: SC-001 | C6: Kateqoriya (PLP) | D6: Hər məhsul kartında ad, qiymət, aylıq ödəniş və düymə göstərilir | E6: P1 — Critical | F6: Pozitiv · Funksional | G6: Ümumi ön şərt (P0): Chrome son versiya, inkognito pəncərə, 1920×1080, AZ dili, login olmadan | H6: 1. https://ispace.az/category/iphone ünvanını aç 2. 1-ci səhifədəki hər məhsul kartında şəkli, adı və qiyməti yoxla 3. Stokda olan kartlarda aylıq ödəniş mətnini ('Ayda X ₼-dan') yoxla 4. Hər kartın altındakı düymənin mətnini qeyd et | I6: 1-ci səhifənin bütün kartları | J6: Hər kartda: şəkil; boş olmayan ad; 'X XXX ₼' formatında qiymət (X > 0); stokda olan məhsullarda aylıq ödəniş mətni; vəziyyətə uyğun düymə: 'Səbətə', 'Ön sifariş', 'Tezliklə satışda' və ya 'Mənə xəbər ver' (BR-11). | K6: Bütün kartlarda şəkil, ad, '₼' formatında qiymət və düymə var; boş sahə yoxdur. Kartlarda 4 fərqli düymə vəziyyəti müşahidə olundu: 'Səbətə', 'Ön sifariş', 'Tezliklə satışda', 'Mənə xəbər ver' (BR-11 yeniləndi). | L6: Pass | M6: Avtomat | N6: A2 — struktur yoxlaması, kart sayı çox (A3) | O6: Bəli | P6: Xeyr | R6: BR-01, BR-11 | S6: Avtomatlaşdırılıb — PASS, 16.10.2026 | T6: Kart sayı = şəkil = ad = qiymət = düymə sayı (düymə növündən asılı olmayaraq); bütün qiymətlərdə '₼', boş ad yoxdur
A7: TC_PLP_POS_003 | B7: SC-001 | C7: Kateqoriya (PLP) | D7: Kartdakı qiymət məhsul səhifəsindəki qiymətlə eynidir | E7: P1 — Critical | F7: Pozitiv · Funksional | G7: Ümumi ön şərt (P0): Chrome son versiya, inkognito pəncərə, 1920×1080, AZ dili, login olmadan | H7: 1. https://ispace.az/category/iphone ünvanını aç 2. 'Səbətə' düyməsi olan ilk kartın adını və qiymətini qeyd et 3. Həmin kartın şəklinə klik et — məhsul səhifəsi açılır 4. Məhsul səhifəsindəki adı və qiyməti qeyd etdiyin dəyərlərlə müqayisə et | I7: Stokda olan istənilən məhsul (icra zamanı seçilir) | J7: PDP-dəki ad və qiymət kartdakı ilə hərfbəhərf eynidir. | K7: Kartdakı ad və qiymət PDP-dəki ilə hərfbəhərf eynidir. | L7: Pass | M7: Avtomat | N7: A1, A2 — qiymət səhvi birbaşa pul itkisidir; dəyişkən qiymətdə belə sınmır | O7: Bəli | P7: Xeyr | R7: BR-01 | S7: Avtomatlaşdırılıb — PASS, 16.10.2026 | T7: İlk kart icra zamanı seçilir, ad və qiymət dəyişənə saxlanır
A8: TC_PLP_POS_004 | B8: SC-001 | C8: Kateqoriya (PLP) | D8: Stokda olan məhsulun kartında 'Səbətə', olmayanda 'Ön sifariş' / 'Mənə xəbər ver' düyməsi göstərilir | E8: P2 — High | F8: Pozitiv · Funksional | G8: Ümumi ön şərt (P0): Chrome son versiya, inkognito pəncərə, 1920×1080, AZ dili, login olmadan | H8: 1. https://ispace.az/category/iphone ünvanını aç 2. Filtr panelinin 'Stokda var' qrupunda 'Mövcuddur' seç 3. Filtr panelinin altındakı 'Tətbiq et' düyməsini bas 4. 1-ci səhifədəki bütün kartların düyməsini qeyd et 5. 'Mövcuddur' seçimini götür, 'Mövcud deyil' seç 6. Filtr panelinin altındakı 'Tətbiq et' düyməsini bas 7. 1-ci səhifədəki bütün kartların düyməsini qeyd et | I8: Stok filtri: Mövcuddur / Mövcud deyil | J8: Stokda olan bütün kartlarda 'Səbətə'; stokda olmayan kartlarda 'Mənə xəbər ver' və ya 'Ön sifariş'. Stokda olmayan kartda 'Səbətə' düyməsi yoxdur. | K8: Stokda olan kartlarda 'Səbətə', stokda olmayanlarda 'Mənə xəbər ver' və ya 'Ön sifariş' göstərilir; stokda olmayan kartda 'Səbətə' yoxdur. | L8: Pass | M8: Avtomat | N8: A2 — stokda olmayan məhsulun satışı biznes riskidir | O8: Bəli | P8: Xeyr | R8: BR-11 | S8: Avtomatlaşdırılıb — PASS, 16.10.2026 | T8: 'Mövcuddur' filtrində ad sayı = 'Səbətə' sayı; 'Mövcud deyil' filtrində 'Səbətə' sayı = 0
A9: TC_PLP_POS_005 | B9: SC-002 | C9: Kateqoriya (PLP) | D9: 'Mövcuddur' filtri: nəticə sayı sayğaca bərabərdir | E9: P2 — High | F9: Pozitiv · Funksional | G9: Ümumi ön şərt (P0): Chrome son versiya, inkognito pəncərə, 1920×1080, AZ dili, login olmadan | H9: 1. https://ispace.az/category/iphone ünvanını aç 2. Filtr panelinin 'Stokda var' qrupunda 'Mövcuddur (N)' sayğacındakı N-i qeyd et 3. 'Mövcuddur' seç 4. Filtr panelinin altındakı 'Tətbiq et' düyməsini bas 5. Səhifənin yuxarısındakı 'N Məhsul' mətnindən nəticə sayını qeyd et 6. Kartların hamısında 'Səbətə' düyməsi olduğunu yoxla | I9: N — icra zamanı oxunur (04.10-da 41) | J9: 1. 'N Məhsul' mətni sayğacdakı N ilə eynidir. 2. Bütün kartlar stokdadır ('Səbətə' düyməsi). | K9: 'Mövcuddur' filtrindən sonra nəticə sayı sayğacdakı rəqəmə bərabərdir; bütün kartlar stokdadır. | L9: Pass | M9: Avtomat | N9: A2 — say qaydaya əsaslanır, konkret rəqəm koda yazılmır | O9: Bəli | P9: Xeyr | R9: BR-02 | S9: Avtomatlaşdırılıb — PASS, 16.10.2026 | T9: Sayğac ('Movcuddur (N)') icra zamanı oxunur; Java: 'N Məhsul' = N
A10: TC_PLP_POS_006 | B10: SC-002 | C10: Kateqoriya (PLP) | D10: Bir filtr qrupunda sayğacların cəmi ümumi məhsul sayına bərabərdir | E10: P3 — Medium | F10: Pozitiv · Funksional | G10: Ümumi ön şərt (P0): Chrome son versiya, inkognito pəncərə, 1920×1080, AZ dili, login olmadan | H10: 1. https://ispace.az/category/iphone ünvanını aç 2. Səhifənin yuxarısındakı 'N Məhsul' mətnindən nəticə sayını qeyd et — ümumi N 3. Filtr panelinin 'Stokda var' qrupundakı bütün sayğacları topla 4. 'Yaddaş' qrupundakı bütün sayğacları topla ('+ Daha çox göstər' varsa bas) 5. 'SIM kart növü' qrupundakı bütün sayğacları topla 6. Hər qrupun cəmini ümumi N ilə müqayisə et | I10: 04.10 müşahidəsi: 41+172 = 213; 66+66+36+32+13 = 213; 187+26 = 213 | J10: Hər bir-birini istisna edən qrupda sayğacların cəmi = N. | K10: Stok, yaddaş və SIM qruplarında sayğacların cəmi ümumi məhsul sayına bərabərdir (BR-12 təsdiqləndi). | L10: Pass | M10: Avtomat | N10: A2, A3 — ucuz, sayma bug-larını tutur | O10: Xeyr | P10: Xeyr | R10: BR-12 | S10: Avtomatlaşdırılıb — PASS, 16.10.2026 | T10: Stok və SIM qruplarında sayğacların cəmi = 'N Məhsul'
A11: TC_PLP_POS_007 | B11: SC-002 | C11: Kateqoriya (PLP) | D11: Yaddaş filtri yalnız seçilmiş yaddaşlı məhsulları göstərir | E11: P2 — High | F11: Pozitiv · Funksional | G11: Ümumi ön şərt (P0): Chrome son versiya, inkognito pəncərə, 1920×1080, AZ dili, login olmadan | H11: 1. https://ispace.az/category/iphone ünvanını aç 2. Filtr panelinin 'Yaddaş' qrupunda '256 GB (N)' sayğacındakı N-i qeyd et 3. '256 GB' seç 4. Filtr panelinin altındakı 'Tətbiq et' düyməsini bas 5. Səhifənin yuxarısındakı 'N Məhsul' mətnindən nəticə sayını qeyd et 6. 1-ci səhifədəki bütün kartların adında '256 GB' olduğunu yoxla | I11: Yaddaş = 256 GB | J11: 1. Bütün kartların adında '256 GB' var. 2. Nəticə sayı = N. | K11: '256 GB' filtri: bütün kartların adında '256 GB' var; nəticə sayı 66 = sayğac (66). | L11: Pass | M11: Avtomat | N11: A1, A2 | O11: Bəli | P11: Xeyr | R11: BR-02 | S11: Avtomatlaşdırılıb — PASS, 16.10.2026 | T11: PLP_POS_009-un sadə variantı: yalnız 256 GB filtri; bütün adlarda '256 GB'
A12: TC_PLP_POS_008 | B12: SC-002 | C12: Kateqoriya (PLP) | D12: Rəng filtri yalnız seçilmiş rəngli məhsulları göstərir | E12: P3 — Medium | F12: Pozitiv · Funksional | G12: Ümumi ön şərt (P0): Chrome son versiya, inkognito pəncərə, 1920×1080, AZ dili, login olmadan | H12: 1. https://ispace.az/category/iphone ünvanını aç 2. Filtr panelinin 'Rəng' qrupunda 'Qara (N)' sayğacındakı N-i qeyd et 3. 'Qara' seç 4. Filtr panelinin altındakı 'Tətbiq et' düyməsini bas 5. Səhifənin yuxarısındakı 'N Məhsul' mətnindən nəticə sayını qeyd et 6. 1-ci səhifədəki kartların adında və şəklində rəngi yoxla | I12: Rəng = Qara | J12: Bütün nəticələr qara rəngli modellərdir (Black, Black Titanium, Space Black və s. daxil). Say = sayğac. | K12: 'Qara' filtrinin nəticələri qara rəngli modellərdir; say sayğaca bərabərdir. | L12: Pass | M12: Manual | N12: M1 — kart adlarında rəng adları qarışıqdır (Qara / Black / Black Titanium), avtomat oracle etibarsızdır | O12: Xeyr | P12: Xeyr | R12: BR-02
A13: TC_PLP_POS_009 | B13: SC-002 | C13: Kateqoriya (PLP) | D13: '256 GB' və 'Mövcuddur' birlikdə seçildikdə yalnız hər iki şərtə uyğun məhsullar göstərilir (VƏ məntiqi) | E13: P2 — High | F13: Pozitiv · Funksional | G13: Ümumi ön şərt (P0): Chrome son versiya, inkognito pəncərə, 1920×1080, AZ dili, login olmadan | H13: 1. https://ispace.az/category/iphone ünvanını aç 2. 'Yaddaş' qrupunda '256 GB' seç 3. 'Stokda var' qrupunda 'Mövcuddur' seç 4. Filtr panelinin altındakı 'Tətbiq et' düyməsini bas 5. Səhifənin yuxarısındakı 'N Məhsul' mətnindən nəticə sayını qeyd et 6. Hər kartın adında '256 GB' və altında 'Səbətə' düyməsi olduğunu yoxla | I13: Yaddaş = 256 GB + Stok = Mövcuddur | J13: Bütün nəticələr həm 256 GB-dır, həm də stokdadır ('Səbətə'). Nəticə sayı hər iki tək filtrin sayından ≤-dir. | K13: 256 GB + Mövcuddur: nəticələr hər iki şərtə uyğundur ('VƏ' məntiqi). | L13: Pass | M13: Avtomat | N13: A2, A3 — kombinasiya məntiqi | O13: Bəli | P13: Xeyr | R13: BR-02, BR-12 | S13: Avtomatlaşdırılıb — PASS, 16.10.2026 | T13: Desktop (1920×1080) görünüşdə filtr seçiləndə dərhal tətbiq olunur — 'Tətbiq et' yalnız mobil görünüşdədir; hər kartda 'Səbətə' olduğu say ilə yoxlanır
A14: TC_PLP_POS_010 | B14: SC-002 | C14: Kateqoriya (PLP) | D14: '256 GB' və '512 GB' birlikdə seçildikdə nəticə sayı iki sayğacın cəminə bərabərdir (VƏ YA məntiqi) | E14: P3 — Medium | F14: Pozitiv · Funksional | G14: Ümumi ön şərt (P0): Chrome son versiya, inkognito pəncərə, 1920×1080, AZ dili, login olmadan | H14: 1. https://ispace.az/category/iphone ünvanını aç 2. 'Yaddaş' qrupunda '256 GB (N1)' və '512 GB (N2)' sayğaclarını qeyd et 3. '256 GB' seç 4. '512 GB' seç 5. Filtr panelinin altındakı 'Tətbiq et' düyməsini bas 6. Səhifənin yuxarısındakı 'N Məhsul' mətnindən nəticə sayını qeyd et 7. Nəticə sayını N1 + N2 ilə müqayisə et | I14: Yaddaş = 256 GB + 512 GB | J14: Bütün nəticələr 256 GB və ya 512 GB-dır. Nəticə sayı = N1 + N2. | K14: 256 GB + 512 GB: nəticələr hər iki dəyərdən birinə uyğundur, say = N1 + N2 ('VƏ YA' məntiqi). | L14: Pass | M14: Avtomat | N14: A2, A3 | O14: Xeyr | P14: Xeyr | R14: BR-12 | S14: Avtomatlaşdırılıb — PASS, 16.10.2026 | T14: 256 GB + 512 GB: 'N Məhsul' = iki sayğacın cəmi
A15: TC_PLP_POS_011 | B15: SC-002 | C15: Kateqoriya (PLP) | D15: Filtrlər təmizlənəndə ilkin siyahı bərpa olunur | E15: P3 — Medium | F15: Pozitiv · Funksional | G15: Ümumi ön şərt (P0): Chrome son versiya, inkognito pəncərə, 1920×1080, AZ dili, login olmadan | H15: 1. https://ispace.az/category/iphone ünvanını aç 2. Səhifənin yuxarısındakı 'N Məhsul' mətnindən nəticə sayını qeyd et — ümumi N 3. 'Yaddaş' qrupunda '256 GB' seç 4. 'Stokda var' qrupunda 'Mövcuddur' seç 5. Filtr panelinin altındakı 'Tətbiq et' düyməsini bas 6. Seçilmiş hər iki filtrin işarəsini götür 7. Filtr panelinin altındakı 'Tətbiq et' düyməsini bas 8. Səhifənin yuxarısındakı 'N Məhsul' mətnindən nəticə sayını qeyd et 9. Nəticə sayını N ilə müqayisə et | I15: — | J15: Məhsul sayı yenidən N-dir, filtr seçimləri boşdur. | K15: Filtrlər təmizləndikdən sonra ilkin məhsul sayı bərpa olundu. | L15: Pass | M15: Avtomat | N15: A2 | O15: Xeyr | P15: Xeyr | R15: BR-02, BR-12 | S15: Avtomatlaşdırılıb — PASS, 16.10.2026 | T15: 256 GB + 'Mövcuddur' seçilib ləğv olunur; ilkin məhsul sayı bərpa olunur
A16: TC_PLP_POS_012 | B16: SC-002 | C16: Kateqoriya (PLP) | D16: Filtrli səhifə yeniləndikdə və link yeni tabda açıldıqda filtr qorunur | E16: P3 — Medium | F16: Pozitiv · Funksional | G16: Ümumi ön şərt (P0): Chrome son versiya, inkognito pəncərə, 1920×1080, AZ dili, login olmadan | H16: 1. https://ispace.az/category/iphone ünvanını aç 2. 'Yaddaş' qrupunda '256 GB' seç 3. Filtr panelinin altındakı 'Tətbiq et' düyməsini bas 4. Səhifənin yuxarısındakı 'N Məhsul' mətnindən nəticə sayını qeyd et 5. Klaviaturada F5 bas (səhifəni yenilə) 6. Filtrin seçili qaldığını və nəticə sayını yoxla 7. Ünvan sətrindəki URL-i kopyala 8. Yeni tab aç və URL-i yapışdırıb aç 9. Filtrin seçili qaldığını və nəticə sayını yoxla | I16: — | J16: Hər iki halda filtr seçili qalır, nəticə sayı və kartlar eynidir. | K16: Filtr səhifə yeniləndikdə və link yeni tabda açıldıqda qorunur. | L16: Pass | M16: Avtomat | N16: A2 | O16: Xeyr | P16: Xeyr | R16: BR-02, BR-12 | S16: Avtomatlaşdırılıb — PASS, 16.10.2026 | T16: F5-dən sonra və eyni link yeni tabda açıldıqda say və '256 GB' filtri qorunur
A17: TC_PLP_NEG_013 | B17: SC-002 | C17: Kateqoriya (PLP) | D17: Nəticəsiz filtr kombinasiyasında boş vəziyyət mesajı göstərilir | E17: P3 — Medium | F17: Neqativ · Funksional | G17: Ümumi ön şərt (P0): Chrome son versiya, inkognito pəncərə, 1920×1080, AZ dili, login olmadan | H17: 1. https://ispace.az/category/iphone ünvanını aç 2. Filtr panelinin 'Qiymət ₼' qrupunda 'qədər' sahəsinə test datasındakı dəyəri yaz 3. Filtr panelinin altındakı 'Tətbiq et' düyməsini bas 4. Səhifədə göstərilən mesaja bax | I17: 'qədər' = 100 (bütün qiymətlərdən aşağı) | J17: 'Məhsul tapılmadı' tipli mesaj və filtrləri təmizləmək imkanı göstərilir. Səhifə xəta vermir. | K17: Nəticəsiz kombinasiyada 'Məhsul tapılmadı. Daha az filtrdən istifadə edin və ya Hamısını silin' mesajı göstərildi. | L17: Pass | M17: Manual | N17: M3 — kataloq dəyişdikcə 'nəticəsiz' kombinasiya nəticə verə bilər | O17: Xeyr | P17: Xeyr | R17: BR-02, BR-12
A18: TC_PLP_POS_014 | B18: SC-003 | C18: Kateqoriya (PLP) | D18: Qiymət aralığı daxilində olan məhsullar göstərilir | E18: P2 — High | F18: Pozitiv · Funksional | G18: Ümumi ön şərt (P0): Chrome son versiya, inkognito pəncərə, 1920×1080, AZ dili, login olmadan | H18: 1. https://ispace.az/category/iphone ünvanını aç 2. 'Qiymət ₼' qrupunda 'dən' sahəsinə 2000 yaz 3. 'qədər' sahəsinə 3000 yaz 4. Filtr panelinin altındakı 'Tətbiq et' düyməsini bas 5. Bütün səhifələrdəki kartların qiymətini yoxla | I18: min = 2000, max = 3000 (etibarlı sinif) | J18: Bütün kartların qiyməti 2000 ≤ qiymət ≤ 3000. Nəticə sayı > 0. | K18: 2000–3000 ₼ aralığında bütün nəticələrin qiyməti aralıq daxilindədir; nəticə sayı > 0. | L18: Pass | M18: Avtomat | N18: A1, A2 | O18: Bəli | P18: Xeyr | R18: BR-04 | S18: Avtomatlaşdırılıb — PASS, 16.10.2026 | T18: Desktop-da qiymət filtri Enter ilə tətbiq olunur; Java: bütün qiymətlər 2000–3000 aralığındadır
A19: TC_PLP_BVA_015 | B19: SC-003 | C19: Kateqoriya (PLP) | D19: Qiymət filtrinin sərhədləri daxildir (min = max = məhsulun qiyməti) | E19: P2 — High | F19: BVA · Funksional | G19: Ümumi ön şərt (P0): Chrome son versiya, inkognito pəncərə, 1920×1080, AZ dili, login olmadan | H19: 1. https://ispace.az/category/iphone ünvanını aç 2. 'Səbətə' düyməsi olan bir məhsulun qiymətini (Q) qeyd et 3. 'dən' sahəsinə Q yaz 4. 'qədər' sahəsinə Q yaz 5. Filtr panelinin altındakı 'Tətbiq et' düyməsini bas 6. Həmin məhsulun nəticədə olduğunu və bütün qiymətlərin Q olduğunu yoxla | I19: Q — icra zamanı seçilən məhsulun qiyməti (məs. 2409) | J19: Həmin məhsul nəticədədir; bütün nəticələrin qiyməti = Q. | K19: min = max = 2409 ₼: yalnız qiyməti 2409 ₼ olan məhsullar göstərildi — sərhəd dəyəri daxildir (BR-04 təsdiqləndi). | L19: Pass | M19: Avtomat | N19: A2 — sərhəd səhvi (< əvəzinə ≤) tipik regression-dur | O19: Bəli | P19: Xeyr | R19: BR-04 | S19: Avtomatlaşdırılıb — PASS, 16.10.2026 | T19: Qiymət filtri desktop-da Enter ilə tətbiq olunur; Q icra zamanı ilk kartdan götürülür
A20: TC_PLP_BVA_016 | B20: SC-003 | C20: Kateqoriya (PLP) | D20: Sərhəddən bir vahid kənar dəyər məhsulu xaric edir | E20: P3 — Medium | F20: BVA · Funksional | G20: Ümumi ön şərt (P0): Chrome son versiya, inkognito pəncərə, 1920×1080, AZ dili, login olmadan | H20: 1. https://ispace.az/category/iphone ünvanını aç 2. Bir məhsulun qiymətini (Q) qeyd et 3. 'dən' = Q + 1, 'qədər' = Q + 1000 yaz 4. Filtr panelinin altındakı 'Tətbiq et' düyməsini bas 5. Q qiymətli məhsulun nəticədə olmadığını yoxla 6. 'dən' = Q − 1000, 'qədər' = Q − 1 yaz 7. Filtr panelinin altındakı 'Tətbiq et' düyməsini bas 8. Q qiymətli məhsulun nəticədə olmadığını yoxla | I20: Q + 1 və Q − 1 | J20: Hər iki halda Q qiymətli məhsul nəticədə yoxdur. | K20: Q+1 və Q−1 aralıqlarında Q qiymətli məhsul nəticədə yoxdur. | L20: Pass | M20: Avtomat | N20: A2 | O20: Xeyr | P20: Xeyr | R20: BR-04 | S20: Avtomatlaşdırılıb — PASS, 16.10.2026 | T20: Q icra zamanı ilk kartdan götürülür; [Q+1, Q+500] və [Q−500, Q−1] aralıqlarında Q qiymətli kart yoxdur
A21: TC_PLP_NEG_017 | B21: SC-003 | C21: Kateqoriya (PLP) | D21: Minimum maksimumdan böyük olduqda sistem istifadəçini məlumatlandırır | E21: P3 — Medium | F21: Neqativ · Funksional | G21: Ümumi ön şərt (P0): Chrome son versiya, inkognito pəncərə, 1920×1080, AZ dili, login olmadan | H21: 1. https://ispace.az/category/iphone ünvanını aç 2. 'Qiymət ₼' qrupunda 'dən' sahəsinə 3000 yaz 3. 'qədər' sahəsinə 1000 yaz 4. Filtr panelinin altındakı 'Tətbiq et' düyməsini bas 5. Göstərilən mesaja və nəticəyə bax | I21: min = 3000, max = 1000 (etibarsız sinif) | J21: Sistem ya xəta mesajı göstərir, ya da dəyərlərin yerini dəyişir. Mesajsız boş nəticə səhifəsi qəbuledilməzdir. Səhifə xəta vermir. | K21: min = 3000, max = 1000: səhifə xəta vermədi, 'Məhsul tapılmadı. Daha az filtrdən istifadə edin və ya Hamısını silin' boş vəziyyət mesajı göstərildi. Qeyd (UX təklifi): mesaj səbəbi (min > max) izah etmir — OBS-01. | L21: Pass | M21: Manual | N21: M5 — gözlənilən davranış tələbdə yoxdur, biznes qərarı lazımdır | O21: Xeyr | P21: Xeyr | R21: BR-04
A22: TC_PLP_NEG_018 | B22: SC-003 | C22: Kateqoriya (PLP) | D22: Qiymət sahəsi qeyri-rəqəm və mənfi dəyərləri qəbul etmir | E22: P3 — Medium | F22: Neqativ · Funksional | G22: Ümumi ön şərt (P0): Chrome son versiya, inkognito pəncərə, 1920×1080, AZ dili, login olmadan | H22: 1. https://ispace.az/category/iphone ünvanını aç 2. 'dən' sahəsinə 'abc' yazmağa çalış 3. Filtr panelinin altındakı 'Tətbiq et' düyməsini bas 4. Sahənin dəyərinə və nəticəyə bax 5. Sahəni təmizlə və '-100' yaz 6. Filtr panelinin altındakı 'Tətbiq et' düyməsini bas 7. Sahənin dəyərinə və nəticəyə bax 8. Sahəni təmizlə və '1 000,50' yaz 9. Filtr panelinin altındakı 'Tətbiq et' düyməsini bas 10. Sahənin dəyərinə və nəticəyə bax | I22: abc; -100; 1 000,50 | J22: Hərflər və mənfi işarə sahəyə yazılmır və ya filtr tətbiq olunmur və bildiriş göstərilir. Səhifə xəta vermir, nəticələr pozulmur. | K22: Mənfi işarə və '1 000,50' formatı sahəyə yazılmır; səhifə xəta vermir. | L22: Pass | M22: Manual | N22: M5 — bir dəfəlik input yoxlaması, regression dəyəri aşağı | O22: Xeyr | P22: Xeyr | R22: BR-04
A23: TC_PLP_POS_019 | B23: SC-004 | C23: Kateqoriya (PLP) | D23: 'Aşağı qiymət' sıralaması qiymətləri artan sırada göstərir | E23: P2 — High | F23: Pozitiv · Funksional | G23: Ümumi ön şərt (P0): Chrome son versiya, inkognito pəncərə, 1920×1080, AZ dili, login olmadan | H23: 1. https://ispace.az/category/iphone ünvanını aç 2. Məhsul siyahısının üstündəki sıralama siyahısını aç 3. 'Aşağı qiymət' seç 4. 1-ci səhifədəki qiymətləri yuxarıdan aşağı ardıcıl oxu və müqayisə et | I23: — | J23: Hər növbəti kartın qiyməti əvvəlkindən ≥-dir. | K23: 'Aşağı qiymət': qiymətlər artan sıradadır. | L23: Pass | M23: Avtomat | N23: A1, A2 | O23: Bəli | P23: Xeyr | R23: BR-03 | S23: Avtomatlaşdırılıb — PASS, 16.10.2026 | T23: Sıralama custom dropdown-dur (əsl select gizlidir); URL sort=cheap; Java: qiymətlər artan
A24: TC_PLP_POS_020 | B24: SC-004 | C24: Kateqoriya (PLP) | D24: 'Yüksək qiymət' sıralaması azalan sıradadır və ilk məhsul ən bahalısıdır | E24: P2 — High | F24: Pozitiv · Funksional | G24: Ümumi ön şərt (P0): Chrome son versiya, inkognito pəncərə, 1920×1080, AZ dili, login olmadan | H24: 1. https://ispace.az/category/iphone ünvanını aç 2. 'Qiymət ₼' qrupundakı 'Ən yüksək qiymət' dəyərini (Qmax) qeyd et 3. Sıralama siyahısından 'Yüksək qiymət' seç 4. İlk kartın qiymətini Qmax ilə müqayisə et 5. 1-ci səhifədəki qiymətlərin azalan sırada olduğunu yoxla | I24: Qmax — icra zamanı oxunur (04.10: 7 229 ₼) | J24: 1. Qiymətlər azalan sıradadır. 2. İlk kartın qiyməti = Qmax. | K24: 'Yüksək qiymət': qiymətlər azalan sıradadır, ilk kartın qiyməti filtrdəki 'Ən yüksək qiymət' ilə eynidir. | L24: Pass | M24: Avtomat | N24: A1, A2 | O24: Bəli | P24: Xeyr | R24: BR-03, BR-05 | S24: Avtomatlaşdırılıb — PASS, 16.10.2026 | T24: URL sort=expensive; Java: qiymətlər azalan; ilk kartın qiyməti = filtrdəki 'Ən yüksək qiymət'
A25: TC_PLP_POS_021 | B25: SC-004 | C25: Kateqoriya (PLP) | D25: Sıralama növbəti səhifədə də davam edir | E25: P3 — Medium | F25: Pozitiv · Funksional | G25: Ümumi ön şərt (P0): Chrome son versiya, inkognito pəncərə, 1920×1080, AZ dili, login olmadan | H25: 1. https://ispace.az/category/iphone ünvanını aç 2. Sıralama siyahısından 'Aşağı qiymət' seç 3. 1-ci səhifədəki son kartın qiymətini (Q1) qeyd et 4. Səhifənin altındakı səhifələmədən '2' bas 5. 2-ci səhifədəki ilk kartın qiymətini (Q2) qeyd et 6. URL-də sıralama parametrinin qaldığını yoxla | I25: — | J25: Q1 ≤ Q2 və 2-ci səhifədə də sıra artandır. URL-də sıralama parametri saxlanılır. | K25: 1-ci səhifənin son qiyməti ≤ 2-ci səhifənin ilk qiyməti; sıra 2-ci səhifədə də artandır. | L25: Pass | M25: Avtomat | N25: A2, A3 | O25: Xeyr | P25: Xeyr | R25: BR-03 | S25: Avtomatlaşdırılıb — PASS, 16.10.2026 | T25: 1-ci səhifənin son qiyməti ≤ 2-ci səhifənin ilk qiyməti; hər iki səhifə artan sıradadır
A26: TC_PLP_POS_022 | B26: SC-004 | C26: Kateqoriya (PLP) | D26: Səhifə ölçüsü və səhifə sayı ümumi məhsul sayına uyğundur | E26: P3 — Medium | F26: Pozitiv · Funksional | G26: Ümumi ön şərt (P0): Chrome son versiya, inkognito pəncərə, 1920×1080, AZ dili, login olmadan | H26: 1. https://ispace.az/category/iphone ünvanını aç 2. Səhifənin yuxarısındakı 'N Məhsul' mətnindən nəticə sayını qeyd et 3. 1-ci səhifədəki kartları say 4. Səhifələmədəki son səhifə nömrəsini qeyd et 5. Son səhifəni aç və kartları say | I26: 04.10: N = 213, səhifədə 21, 11 səhifə, sonuncuda 3 | J26: 1. Tam səhifələrdə 21 kart var. 2. Səhifə sayı = ⌈N / 21⌉. 3. Son səhifədə N − 21 × (səhifə sayı − 1) kart var. | K26: Tam səhifələrdə 21 kart, səhifə sayı ⌈N/21⌉, son səhifədəki kart sayı düsturla uyğundur (BR-14 təsdiqləndi). | L26: Pass | M26: Avtomat | N26: A2 | O26: Xeyr | P26: Xeyr | R26: BR-14
A27: TC_PLP_POS_023 | B27: SC-004 | C27: Kateqoriya (PLP) | D27: Səhifələr arasında məhsul təkrarlanmır və itmir | E27: P3 — Medium | F27: Pozitiv · Funksional | G27: Ümumi ön şərt (P0): Chrome son versiya, inkognito pəncərə, 1920×1080, AZ dili, login olmadan | H27: 1. https://ispace.az/category/iphone ünvanını aç 2. Hər səhifədə bütün kartların linkini (URL) siyahıya yaz 3. Səhifələmə ilə növbəti səhifəyə keç və təkrarla — son səhifəyə qədər 4. Toplanan URL-lərin sayını N ilə müqayisə et 5. Siyahıda təkrarlanan URL olub-olmadığını yoxla | I27: — | J27: Toplanmış URL-lərin sayı = N; təkrarlanan URL yoxdur. | K27: Bütün səhifələr ardıcıl açıldı; toplanan məhsul URL-lərinin sayı ümumi saya bərabərdir, təkrarlanan və ya itən məhsul yoxdur (10.10 təkrar icra). | L27: Pass | M27: Manual | N27: M3 — default 'Məşhur' sırası və eyni qiymətli məhsullar sorğular arasında yer dəyişə bilər → avtomat test flaky olar | O27: Xeyr | P27: Xeyr | R27: BR-03, BR-05, BR-14
A28: TC_FLT_POS_001 | B28: SC-005 | C28: Kateqoriya (PLP) | D28: 'iPhone 18 Pro & Pro Max' çipi seçildikdə nəticə sayı həmin seriyaların sayğaclarının cəminə bərabərdir | E28: P3 — Medium | F28: Pozitiv · Funksional | G28: Ümumi ön şərt (P0): Chrome son versiya, inkognito pəncərə, 1920×1080, AZ dili, login olmadan; filtr seçilməyib | H28: 1. https://ispace.az/category/iphone ünvanını aç 2. Filtr panelinin 'Seriya' qrupunda 'iPhone 18 Pro (N1)' və 'iPhone 18 Pro Max (N2)' sayğaclarını qeyd et 3. Səhifənin yuxarısındakı 'iPhone 18 Pro & iPhone 18 Pro Max' çipinə klik et 4. Açılan səhifənin URL-ini və başlığını qeyd et 5. Səhifənin yuxarısındakı 'N Məhsul' mətnindən nəticə sayını qeyd et 6. Nəticə sayını N1 + N2 ilə müqayisə et | I28: 10.10: N1 = 16, N2 = 16 → gözlənilən 32 | J28: /category/iphone-series-18-pro açılır; məhsul sayı = N1 + N2 (32); bütün kartlar iPhone 18 Pro və ya 18 Pro Max-dır. | K28: Gözlənilən nəticəyə uyğundur. | L28: Pass | M28: Avtomat | N28: A2 — iki səhifə arasında uyğunluq qaydası | O28: Xeyr | P28: Xeyr | R28: BR-12
A29: TC_FLT_POS_002 | B29: SC-005 | C29: Kateqoriya (PLP) | D29: Seriya filtri yalnız dəqiq seriyanı qaytarır (alt-seriyaları qarışdırmır) | E29: P2 — High | F29: Pozitiv · Funksional | G29: Ümumi ön şərt (P0): Chrome son versiya, inkognito pəncərə, 1920×1080, AZ dili, login olmadan; filtr seçilməyib | H29: 1. https://ispace.az/category/iphone ünvanını aç 2. 'Seriya' qrupunda yalnız 'iPhone 16 (N)' seç 3. Filtr panelinin altındakı 'Tətbiq et' düyməsini bas 4. Səhifənin yuxarısındakı 'N Məhsul' mətnindən nəticə sayını qeyd et 5. Bütün kartların adının 'iPhone 16,' ilə başladığını yoxla (16 Pro / Plus / Pro Max / 16e olmamalıdır) 6. Seçimi götür, yalnız 'iPhone 15' seç 7. Filtr panelinin altındakı 'Tətbiq et' düyməsini bas 8. Adları eyni qayda ilə yoxla | I29: 10.10: iPhone 16 (17), iPhone 15 (15) | J29: Nəticə sayı = N. Bütün adlar 'iPhone 16,' ilə başlayır; 'iPhone 16 Pro', 'iPhone 16 Plus', 'iPhone 16 Pro Max', 'iPhone 16e' nəticədə YOXDUR. Mətnə əsaslanan 'contains' axtarışı səhvini tutur. | K29: Gözlənilən nəticəyə uyğundur. | L29: Pass | M29: Avtomat | N29: A1, A2 — tipik substring bug-ı, regression üçün dəyərli | O29: Bəli | P29: Xeyr | R29: BR-02 | S29: Avtomatlaşdırılıb — PASS, 16.10.2026 | T29: Desktop-da filtr dərhal tətbiq olunur; bütün adlarda 'iPhone 16,' (vergüllə) yoxlanır
A30: TC_FLT_POS_003 | B30: SC-005 | C30: Kateqoriya (PLP) | D30: Bütün Seriya sayğaclarının cəmi ümumi məhsul sayına bərabərdir ('Daha çox göstər' açıq) | E30: P3 — Medium | F30: Pozitiv · Funksional | G30: Ümumi ön şərt (P0): Chrome son versiya, inkognito pəncərə, 1920×1080, AZ dili, login olmadan; filtr seçilməyib | H30: 1. https://ispace.az/category/iphone ünvanını aç 2. 'Seriya' qrupunda '+ Daha çox göstər' bas 3. Bütün seriyaların sayğaclarını topla 4. Cəmi ümumi 'N Məhsul' ilə müqayisə et | I30: 10.10: görünən 10 seriyanın cəmi 150; gizli seriyalarla 213 olmalıdır | J30: Cəm = 213. Az olarsa — seriyası təyin edilməmiş məhsullar var (Seriya filtri ilə tapılmır); çox olarsa — bir məhsul iki seriyaya bağlanıb. | K30: Gözlənilən nəticəyə uyğundur. | L30: Pass | M30: Avtomat | N30: A2 | O30: Xeyr | P30: Xeyr | R30: BR-12
A31: TC_FLT_POS_004 | B31: SC-006 | C31: Kateqoriya (PLP) | D31: Ekran diaqonalı filtri: say və PDP göstəricisi uyğundur | E31: P3 — Medium | F31: Pozitiv · Funksional | G31: Ümumi ön şərt (P0): Chrome son versiya, inkognito pəncərə, 1920×1080, AZ dili, login olmadan; filtr seçilməyib | H31: 1. https://ispace.az/category/iphone ünvanını aç 2. 'Ekran diaqonalı' qrupunda '6.90" (N)' seç 3. Filtr panelinin altındakı 'Tətbiq et' düyməsini bas 4. Səhifənin yuxarısındakı 'N Məhsul' mətnindən nəticə sayını qeyd et 5. Təsadüfi 3 nəticənin məhsul səhifəsini aç və 'Ekran diaqonalı' göstəricisini oxu 6. Filtri '7.60"' ilə dəyiş 7. Filtr panelinin altındakı 'Tətbiq et' düyməsini bas 8. Nəticədəki modellərin adlarını qeyd et | I31: 10.10: 6.90" (40), 7.60" (8) | J31: Say = sayğac; seçilmiş PDP-lərdə 'Ekran diaqonalı 6.90"'. 7.60" nəticələri yalnız həmin ölçülü modeldir (məs. iPhone Duo) — məntiqsiz model (məs. iPhone 16e) yoxdur. | K31: Gözlənilən nəticəyə uyğundur. | L31: Pass | M31: Avtomat | N31: A2 — filtr datası ilə PDP datasının uyğunluğu | O31: Xeyr | P31: Xeyr | R31: BR-12
A32: TC_FLT_POS_005 | B32: SC-006 | C32: Kateqoriya (PLP) | D32: '48 MP' əsas kamera filtri seçildikdə yalnız tək arxa kameralı modellər göstərilir (12 məhsul) | E32: P3 — Medium | F32: Pozitiv · Funksional | G32: Ümumi ön şərt (P0): Chrome son versiya, inkognito pəncərə, 1920×1080, AZ dili, login olmadan; filtr seçilməyib | H32: 1. https://ispace.az/category/iphone ünvanını aç 2. 'Əsas kamera' qrupunda '48 Mpixel (N)' seç 3. Filtr panelinin altındakı 'Tətbiq et' düyməsini bas 4. Səhifənin yuxarısındakı 'N Məhsul' mətnindən nəticə sayını qeyd et 5. Nəticədəki model adlarını qeyd et 6. 2 nəticənin məhsul səhifəsində 'Əsas kamera' göstəricisini oxu | I32: 10.10: 48 Mpixel (12) | J32: Say = 12; nəticələr yalnız tək arxa kameralı modellərdir (məs. iPhone 16e, 17e, Air); PDP-də 'Əsas kamera 48 Mpixel'. Pro modeli bu qrupa düşmür. | K32: Gözlənilən nəticəyə uyğundur. | L32: Pass | M32: Avtomat | N32: A2 | O32: Xeyr | P32: Xeyr | R32: BR-12
A33: TC_FLT_EDGE_006 | B33: SC-006 | C33: Kateqoriya (PLP) | D33: 'Video izləmə müddəti' filtrinin bütün dəyərləri azərbaycanca və eyni vahidlə ('saat') yazılır | E33: P4 — Low | F33: Edge Case · Funksional | G33: Ümumi ön şərt (P0): Chrome son versiya, inkognito pəncərə, 1920×1080, AZ dili, login olmadan; filtr seçilməyib | H33: 1. https://ispace.az/category/iphone ünvanını aç 2. 'Video izləmə müddəti' qrupunda '+ Daha çox göstər' bas 3. Qrupdakı bütün dəyərləri siyahıya yaz 4. Hər dəyərin vahidini ('saat' və ya başqa) qeyd et | I33: 10.10: '36 Hours (16)', '45 Hours (16)' — digərləri 'saat' | J33: Bütün dəyərlər 'saat' vahidi ilə, azərbaycanca yazılır; '36 Hours', '45 Hours' kimi ingiliscə dəyər yoxdur. | K33: AZ səhifədə '36 Hours' və '45 Hours' dəyərləri ingiliscədir, digər dəyərlər 'saat' ilə yazılıb (10.10 icrası). | L33: Fail | M33: Manual | N33: M1 — data keyfiyyəti və tərcümə | O33: Xeyr | P33: Xeyr | Q33: BUG-011 | R33: BR-18
A34: TC_FLT_EDGE_007 | B34: SC-006 | C34: Kateqoriya (PLP) | D34: '36 Hours' filtri ilə tapılan modellərin məhsul səhifəsindəki video izləmə müddəti 36 saatdır | E34: P4 — Low | F34: Edge Case · Funksional | G34: Ümumi ön şərt (P0): Chrome son versiya, inkognito pəncərə, 1920×1080, AZ dili, login olmadan; filtr seçilməyib | H34: 1. https://ispace.az/category/iphone ünvanını aç 2. 'Video izləmə müddəti' qrupunda '+ Daha çox göstər' bas 3. '36 Hours' seç 4. Filtr panelinin altındakı 'Tətbiq et' düyməsini bas 5. Birinci nəticənin məhsul səhifəsini aç 6. 'Texniki göstəricilər'də video izləmə müddətini oxu 7. Digər 2 nəticə üçün 5–6-cı addımları təkrarla | I34: 'Video izləmə müddəti' = '36 Hours' (10.10: 16 nəticə) | J34: Nəticədəki hər modelin məhsul səhifəsində video izləmə müddəti 36 saatdır. | K34: '36 Hours' seçildikdə nəticədə olan 'iPhone 18 Pro, 512 GB, Burgundy' məhsul səhifəsində video izləmə müddəti 34 saata qədər göstərilir — filtr dəyəri ilə uyğun deyil (10.10 icrası). | L34: Fail | M34: Manual | N34: M1 — PDP göstəricisi ilə müqayisə | O34: Xeyr | P34: Xeyr | Q34: BUG-021 | R34: BR-18
A35: TC_FLT_POS_008 | B35: SC-006 | C35: Kateqoriya (PLP) | D35: SIM kart növü filtri bir-birini istisna edir | E35: P3 — Medium | F35: Pozitiv · Funksional | G35: Ümumi ön şərt (P0): Chrome son versiya, inkognito pəncərə, 1920×1080, AZ dili, login olmadan; filtr seçilməyib | H35: 1. https://ispace.az/category/iphone ünvanını aç 2. 'SIM kart növü' qrupunda 'eSIM (N1)' seç 3. Filtr panelinin altındakı 'Tətbiq et' düyməsini bas 4. Səhifənin yuxarısındakı 'N Məhsul' mətnindən nəticə sayını qeyd et 5. 2 nəticənin məhsul səhifəsində 'SIM kart növü'nü oxu 6. Seçimi 'Nano-SIM + eSIM (N2)' ilə dəyiş 7. Filtr panelinin altındakı 'Tətbiq et' düyməsini bas 8. Nəticədə eSIM-only modellərin olmadığını yoxla 9. N1 + N2-ni ümumi say ilə müqayisə et | I35: 10.10: eSIM (26), Nano-SIM + eSIM (187) | J35: eSIM nəticələri = 26 və PDP-də 'eSIM'; Nano-SIM + eSIM nəticələrində eSIM-only modellər yoxdur; 26 + 187 = 213. | K35: eSIM nəticələri sayğacla uyğundur və məhsul səhifələrində 'eSIM' yazılıb; 'Nano-SIM + eSIM' nəticələrində eSIM-only modellər yoxdur; 26 + 187 = 213. | L35: Pass | M35: Avtomat | N35: A2 | O35: Xeyr | P35: Xeyr | R35: BR-12
A36: TC_FLT_EDGE_009 | B36: SC-007 | C36: Kateqoriya (PLP) | D36: Hər məhsul ən azı bir Rəng dəyərinə bağlıdır (rəng sayğacları cəmi = 213) | E36: P3 — Medium | F36: Edge Case · Funksional | G36: Ümumi ön şərt (P0): Chrome son versiya, inkognito pəncərə, 1920×1080, AZ dili, login olmadan; filtr seçilməyib | H36: 1. https://ispace.az/category/iphone ünvanını aç 2. 'Rəng' qrupunda '+ Daha çox göstər' bas 3. Bütün rəng sayğaclarını topla 4. Cəmi ümumi 'N Məhsul' ilə müqayisə et | I36: 10.10: görünən 10 rəngin cəmi 204; gizlilərlə 213 olmalıdır | J36: Cəm = 213. Az olarsa — rəngi təyin edilməmiş məhsullar var (məs. Lavender, Sage, Cosmic Orange, Glacier, Burgundy) və onlar heç bir rəng filtri ilə tapılmır. | K36: 'Daha çox göstər' açıq halda rəng sayğaclarının cəmi = 213; hər məhsul bir rəngə bağlıdır. | L36: Pass | M36: Avtomat | N36: A2 | O36: Xeyr | P36: Xeyr | R36: BR-12
A37: TC_FLT_EDGE_010 | B37: SC-007 | C37: Kateqoriya (PLP) | D37: Hər modelin Apple rəng adı vizual rənginə uyğun Rəng filtri dəyərində tapılır | E37: P3 — Medium | F37: Edge Case · Funksional | G37: Ümumi ön şərt (P0): Chrome son versiya, inkognito pəncərə, 1920×1080, AZ dili, login olmadan; filtr seçilməyib | H37: 1. https://ispace.az/category/iphone ünvanını aç 2. 'Rəng' qrupunda test datasındakı birinci modelə uyğun rəngi seç 3. Filtr panelinin altındakı 'Tətbiq et' düyməsini bas 4. Modelin nəticədə olub-olmadığını qeyd et 5. Test datasındakı digər modellər üçün 2–4-cü addımları təkrarla | I37: Model → gözlənilən rəng filtri: iPhone 17 Lavender → Bənövşəyi/Cəhrayı; iPhone 17 Sage → Yaşıl; iPhone 17 Pro Cosmic Orange → Narıncı; iPhone 17 Pro Max Deep Blue → Mavi; iPhone 18 Pro Glacier → Ağ/Gümüş; iPhone 18 Pro Burgundy → Qırmızı | J37: Hər model vizual rənginə uyğun bir filtrdə tapılır. Heç bir filtrdə tapılmayan və ya açıq-aydın səhv rəngdə olan (məs. Burgundy → Mavi) model — data bug-ı. | K37: Gözlənilən nəticəyə uyğundur. | L37: Pass | M37: Manual | N37: M1 — rəng uyğunluğu insan qiymətləndirməsidir | O37: Xeyr | P37: Xeyr | R37: BR-18
A38: TC_FLT_EDGE_011 | B38: SC-007 | C38: Kateqoriya (PLP) | D38: 'Əlavə xüsusiyyətlər' filtri bütün uyğun məhsulları qaytarır (data tamlığı) | E38: P2 — High | F38: Edge Case · Funksional | G38: Ümumi ön şərt (P0): Chrome son versiya, inkognito pəncərə, 1920×1080, AZ dili, login olmadan; filtr seçilməyib | H38: 1. https://ispace.az/category/iphone ünvanını aç 2. 'Əlavə xüsusiyyətlər' qrupunda 'Dynamic Island (N)' seç 3. Filtr panelinin altındakı 'Tətbiq et' düyməsini bas 4. Səhifənin yuxarısındakı 'N Məhsul' mətnindən nəticə sayını qeyd et 5. Nəticədəki model adlarını qeyd et 6. Filtrsiz siyahıda Dynamic Island olan modellərin (iPhone 15 / 16 / 17 / 18) sayını N ilə müqayisə et | I38: 10.10: bütün xüsusiyyətlər yalnız (8). Dynamic Island iPhone 15-dən bəri bütün əsas modellərdədir — kateqoriyada 100+ belə məhsul var | J38: Filtr xüsusiyyəti olan bütün məhsulları qaytarır və ya xüsusiyyət datası tam deyilsə filtr göstərilmir. 8 nəticə — istifadəçi uyğun modellərin 90%-dən çoxunu görmür (data bug-ı). | K38: Gözlənilən nəticəyə uyğundur. | L38: Pass | M38: Manual | N38: M1 — gözlənilən say Apple spesifikasiyasına əsaslanır, insan yoxlaması lazımdır | O38: Xeyr | P38: Xeyr | R38: BR-18
A39: TC_FLT_UI_012 | B39: SC-007 | C39: Kateqoriya (PLP) | D39: 'Əlavə xüsusiyyətlər' dəyərləri azərbaycancadır | E39: P4 — Low | F39: UI | G39: Ümumi ön şərt (P0): Chrome son versiya, inkognito pəncərə, 1920×1080, AZ dili, login olmadan; filtr seçilməyib | H39: 1. https://ispace.az/category/iphone ünvanını aç 2. 'Əlavə xüsusiyyətlər' qrupunda '+ Daha çox göstər' bas 3. Qrupdakı bütün dəyərləri oxu və dilini qeyd et | I39: 10.10: 'ProMotion technology with adaptive refresh rates up to 120Hz', '1600 nits peak brightness (HDR)', '3000 nits peak brightness (outdoor)', 'Always On display' | J39: Bütün dəyərlər azərbaycancadır (brend terminləri — Dynamic Island, True Tone — istisna ola bilər). | K39: AZ səhifədə 'Əlavə xüsusiyyətlər' dəyərlərinin bir qismi azərbaycanca, bir qismi ingiliscədir (məs. 'ProMotion technology with adaptive refresh rates up to 120Hz', '… nits peak brightness'). | L39: Fail | M39: Manual | N39: M1 | O39: Xeyr | P39: Xeyr | Q39: BUG-020 | R39: BR-18
A40: TC_FLT_POS_013 | B40: SC-008 | C40: Kateqoriya (PLP) | D40: Filtr seçildikdən sonra digər qrupların sayğacları nəticəyə görə yenilənir | E40: P2 — High | F40: Pozitiv · Funksional | G40: Ümumi ön şərt (P0): Chrome son versiya, inkognito pəncərə, 1920×1080, AZ dili, login olmadan; filtr seçilməyib | H40: 1. https://ispace.az/category/iphone ünvanını aç 2. 'Yaddaş' qrupunda '2 TB (N)' seç 3. Filtr panelinin altındakı 'Tətbiq et' düyməsini bas 4. 'Rəng', 'Seriya' və 'Stokda var' qruplarının sayğaclarını oxu 5. Hər qrupun sayğac cəmini N ilə müqayisə et | I40: 10.10: 2 TB (13) | J40: Bütün qrupların sayğacları yalnız 2 TB nəticələrinə aiddir; hər bir-birini istisna edən qrupda cəm = 13; 0 nəticəli dəyərlər gizlənir və ya deaktivdir. Sayğaclar dəyişmirsə — istifadəçi '0 nəticə' verən kombinasiyalar seçir. | K40: Gözlənilən nəticəyə uyğundur. | L40: Pass | M40: Avtomat | N40: A2 | O40: Xeyr | P40: Xeyr | R40: BR-12
A41: TC_FLT_POS_014 | B41: SC-008 | C41: Kateqoriya (PLP) | D41: 'Tətbiq et' basılmadan seçim nəticəni dəyişmir və itmir | E41: P3 — Medium | F41: Pozitiv · Funksional | G41: Ümumi ön şərt (P0): Chrome son versiya, inkognito pəncərə, 1920×1080, AZ dili, login olmadan; filtr seçilməyib | H41: 1. https://ispace.az/category/iphone ünvanını aç 2. Səhifənin yuxarısındakı 'N Məhsul' mətnindən nəticə sayını qeyd et 3. 'Yaddaş' qrupunda '512 GB' seç — 'Tətbiq et' BASMA 4. Səhifənin yuxarısındakı 'N Məhsul' mətnindən nəticə sayını qeyd et — dəyişməməlidir 5. Sıralama siyahısından 'Aşağı qiymət' seç 6. Filtr panelindəki '512 GB' işarəsinə və nəticəyə bax | I41: — | J41: 'Tətbiq et'-ə qədər nəticə dəyişmir. Sıralama dəyişəndə tətbiq olunmamış seçim ya ləğv olunur, ya da açıq şəkildə tətbiq edilir — panel və nəticə arasında ziddiyyət (checkbox seçili, nəticə filtrsiz) yoxdur. | K41: Gözlənilən nəticəyə uyğundur. | L41: Pass | M41: Avtomat | N41: A2 | O41: Xeyr | P41: Xeyr | R41: BR-02, BR-12
A42: TC_FLT_POS_015 | B42: SC-008 | C42: Kateqoriya (PLP) | D42: '+ Daha çox göstər' gizli dəyəri seçdikdən sonra aktiv filtr görünür qalır | E42: P3 — Medium | F42: Pozitiv · Funksional | G42: Ümumi ön şərt (P0): Chrome son versiya, inkognito pəncərə, 1920×1080, AZ dili, login olmadan; filtr seçilməyib | H42: 1. https://ispace.az/category/iphone ünvanını aç 2. 'Rəng' qrupunda '+ Daha çox göstər' bas 3. Yalnız gizli siyahıda olan bir rəngi seç 4. Filtr panelinin altındakı 'Tətbiq et' düyməsini bas 5. Səhifə yeniləndikdən sonra 'Rəng' qrupunda seçilmiş rəngin göründüyünü yoxla | I42: — | J42: Qrup açılır/bağlanır; seçilmiş gizli dəyər tətbiqdən sonra görünür (qrup açıq qalır və ya seçilmiş dəyər yuxarıda göstərilir). İstifadəçi aktiv filtri axtarmaq məcburiyyətində qalmır. | K42: Gözlənilən nəticəyə uyğundur. | L42: Pass | M42: Manual | N42: M1 | O42: Xeyr | P42: Xeyr | R42: BR-02, BR-12
A43: TC_FLT_POS_016 | B43: SC-008 | C43: Kateqoriya (PLP) | D43: Aktiv filtrlər görünür və tək-tək silinə bilir | E43: P3 — Medium | F43: Pozitiv · Funksional | G43: Ümumi ön şərt (P0): Chrome son versiya, inkognito pəncərə, 1920×1080, AZ dili, login olmadan; filtr seçilməyib | H43: 1. https://ispace.az/category/iphone ünvanını aç 2. '256 GB', 'Qara' və 'Mövcuddur' seç 3. Filtr panelinin altındakı 'Tətbiq et' düyməsini bas 4. Aktiv filtrlərin harada göstərildiyinə bax 5. Yalnız 'Qara' seçimini götür 6. Filtr panelinin altındakı 'Tətbiq et' düyməsini bas 7. Qalan filtrlərə və nəticə sayına bax 8. Bütün filtrləri birdən silmək imkanını axtar | I43: — | J43: Aktiv filtrlər görünür; 'Qara' silindikdə digər ikisi qalır və nəticə müvafiq yenilənir; filtr panelində hamısını təmizləmək imkanı var (10.10: 'Hamısını sil' yalnız 'Məhsul tapılmadı' vəziyyətində görünür). | K43: Gözlənilən nəticəyə uyğundur. | L43: Pass | M43: Manual | N43: M5 — UX tələbi təsdiqlənməyib | O43: Xeyr | P43: Xeyr | R43: BR-02, BR-12
A44: TC_FLT_POS_017 | B44: SC-009 | C44: Kateqoriya (PLP) | D44: Üç fərqli qrupdan filtr kombinasiyası dəqiq nəticə verir | E44: P2 — High | F44: Pozitiv · Funksional | G44: Ümumi ön şərt (P0): Chrome son versiya, inkognito pəncərə, 1920×1080, AZ dili, login olmadan; filtr seçilməyib | H44: 1. https://ispace.az/category/iphone ünvanını aç 2. 'Seriya' qrupunda 'iPhone 18 Pro' seç 3. 'Yaddaş' qrupunda '1 TB' seç 4. 'Rəng' qrupunda 'Gümüş' seç 5. Filtr panelinin altındakı 'Tətbiq et' düyməsini bas 6. Bütün nəticələrin adının 'iPhone 18 Pro, 1 TB, Gümüş' olduğunu yoxla 7. Rəngi 'Qara' ilə dəyiş 8. Filtr panelinin altındakı 'Tətbiq et' düyməsini bas 9. Adları eyni qayda ilə yoxla | I44: 04.10 kataloqunda: 'iPhone 18 Pro, 1 TB, Gümüş' mövcuddur | J44: Bütün nəticələr hər üç şərtə uyğundur (ad 'iPhone 18 Pro, 1 TB, Gümüş'); Pro Max və digər yaddaşlar yoxdur; nəticə sayı > 0. | K44: Gözlənilən nəticəyə uyğundur. | L44: Pass | M44: Avtomat | N44: A1, A2 — 3 ölçülü AND məntiqi | O44: Bəli | P44: Xeyr | R44: BR-18 | S44: Avtomatlaşdırılıb — PASS, 16.10.2026 | T44: Seriya + Yaddaş + Rəng (Gümüş → Qara); bütün adlarda tam kombinasiya ('iPhone 18 Pro, 1 TB, Gümüş') yoxlanır
A45: TC_FLT_EDGE_018 | B45: SC-009 | C45: Kateqoriya (PLP) | D45: Filtr və 'Aşağı qiymət' sıralaması ilə səhifələr arasında keçdikdə filtr və sıra bütün səhifələrdə saxlanır | E45: P2 — High | F45: Edge Case · Funksional | G45: Ümumi ön şərt (P0): Chrome son versiya, inkognito pəncərə, 1920×1080, AZ dili, login olmadan; filtr seçilməyib | H45: 1. https://ispace.az/category/iphone ünvanını aç 2. 'Stokda var' qrupunda 'Mövcud deyil (N)' seç 3. Filtr panelinin altındakı 'Tətbiq et' düyməsini bas 4. Sıralama siyahısından 'Aşağı qiymət' seç 5. Səhifələmədən '2' bas — filtr və sıralamanın qaldığını yoxla 6. Son səhifəni aç — səhifə sayını və kart sayını qeyd et | I45: 10.10: Mövcud deyil (167) → ⌈167/21⌉ = 8 səhifə, sonuncuda 20 kart | J45: Hər səhifədə filtr və sıralama saxlanır (URL və UI); bütün kartlar stokda deyil; qiymətlər səhifələr boyu artan; səhifə sayı 8, son səhifədə 20 kart. | K45: Gözlənilən nəticəyə uyğundur. | L45: Pass | M45: Avtomat | N45: A2, A3 | O45: Bəli | P45: Xeyr | R45: BR-03, BR-14 | S45: Avtomatlaşdırılıb — PASS, 16.10.2026 | T45: 12.10: data dəyişdi — 'Mövcud deyil' 171 məhsul, 9 səhifə; son səhifədə qiyməti olmayan 'Tezliklə satışda' kartları (iPhone Duo) var. Ona görə son səhifədə qiymət sırası yox, filtr/sıralamanın saxlanması və 'Səbətə' olmaması yoxlanır. Sıra səhifə 1, 2 və səhifələr arası yoxlanır 15.10: 'Mənə xəbər ver' sayı yoxlaması çıxarıldı — stokda olmayan kartların düymə növü dəyişə bilir; stokda olmamaq 'Səbətə' sayı = 0 ilə yoxlanır.
A46: TC_FLT_EDGE_019 | B46: SC-009 | C46: Kateqoriya (PLP) | D46: Brauzerin 'Geri' düyməsi əvvəlki filtr vəziyyətini bərpa edir | E46: P3 — Medium | F46: Edge Case · Funksional | G46: Ümumi ön şərt (P0): Chrome son versiya, inkognito pəncərə, 1920×1080, AZ dili, login olmadan; filtr seçilməyib | H46: 1. https://ispace.az/category/iphone ünvanını aç 2. '256 GB' seç və 'Tətbiq et' bas (vəziyyət A) 3. Əlavə olaraq 'Qara' seç və 'Tətbiq et' bas (vəziyyət B) 4. Brauzerin 'Geri' düyməsini bas 5. URL-ə, filtr panelinə və nəticələrə bax | I46: — | J46: Vəziyyət A bərpa olunur: URL, panel checkbox-ları və nəticələr yalnız 256 GB-dır. URL A-ya qayıdıb panel B-ni göstərirsə — ziddiyyət. | K46: Gözlənilən nəticəyə uyğundur. | L46: Pass | M46: Avtomat | N46: A2 | O46: Xeyr | P46: Xeyr | R46: BR-18
A47: TC_FLT_EDGE_020 | B47: SC-009 | C47: Kateqoriya (PLP) | D47: Dil dəyişəndə filtr qorunur və sayğaclar eynidir | E47: P4 — Low | F47: Edge Case · Funksional | G47: Ümumi ön şərt (P0): Chrome son versiya, inkognito pəncərə, 1920×1080, AZ dili, login olmadan; filtr seçilməyib | H47: 1. https://ispace.az/category/iphone ünvanını aç 2. '512 GB' və 'Mövcuddur' seç 3. Filtr panelinin altındakı 'Tətbiq et' düyməsini bas 4. Səhifənin yuxarısındakı 'N Məhsul' mətnindən nəticə sayını qeyd et 5. Header-dəki dil seçimindən 'English' seç 6. Filtr panelində seçimlərə və nəticə sayına bax | I47: — | J47: EN versiyada eyni filtrlər seçili, nəticə sayı eynidir; filtr adları ingiliscədir. | K47: Filtrlər tətbiq edildikdən sonra dil EN-ə dəyişdirildikdə filtrlər silindi, bütün məhsullar göstərildi. | L47: Fail | M47: Manual | N47: M1 | O47: Xeyr | P47: Xeyr | Q47: BUG-022 | R47: BR-10
A48: TC_FLT_EDGE_021 | B48: SC-009 | C48: Kateqoriya (PLP) | D48: Endirimli məhsul qiymət filtrində endirimli (faktiki) qiymətinə görə tapılır | E48: P2 — High | F48: Edge Case · Funksional | G48: Ümumi ön şərt (P0): Chrome son versiya, inkognito pəncərə, 1920×1080, AZ dili, login olmadan; endirimli məhsul olan kateqoriya açıqdır (məs. https://ispace.az/category/extra-deals) | H48: 1. https://ispace.az/category/extra-deals ünvanını aç 2. Endirimli məhsulun köhnə (K, üstündən xətt) və yeni (Y) qiymətini qeyd et 3. 'Qiymət ₼' qrupunda 'dən' = Y − 1, 'qədər' = Y + 1 yaz 4. Filtr panelinin altındakı 'Tətbiq et' düyməsini bas 5. Məhsulun nəticədə olduğunu yoxla 6. 'dən' = K − 1, 'qədər' = K + 1 yaz 7. Filtr panelinin altındakı 'Tətbiq et' düyməsini bas 8. Məhsulun nəticədə olmadığını yoxla | I48: K və Y icra zamanı oxunur | J48: 1-ci aralıqda (yeni qiymət) məhsul nəticədədir, 2-ci aralıqda (köhnə qiymət) yoxdur. | K48: Gözlənilən nəticəyə uyğundur. | L48: Pass | M48: Manual | N48: M3 — endirimlər kampaniyaya bağlıdır | O48: Xeyr | P48: Xeyr | R48: BR-18
A49: TC_FLT_BVA_022 | B49: SC-009 | C49: Kateqoriya (PLP) | D49: Qiymət filtrində yalnız 'dən', yalnız 'qədər' və ən yüksək qiymətdən böyük dəyər daxil edildikdə nəticə sərhədə uyğundur | E49: P3 — Medium | F49: BVA · Funksional | G49: Ümumi ön şərt (P0): Chrome son versiya, inkognito pəncərə, 1920×1080, AZ dili, login olmadan; filtr seçilməyib | H49: 1. https://ispace.az/category/iphone ünvanını aç 2. Yalnız 'dən' = 7000 yaz 3. Filtr panelinin altındakı 'Tətbiq et' düyməsini bas 4. Nəticələrin qiymətini yoxla 5. Sahələri təmizlə; yalnız 'qədər' = 1100 yaz 6. Filtr panelinin altındakı 'Tətbiq et' düyməsini bas 7. Nəticələrin qiymətini yoxla 8. Sahələri təmizlə; 'qədər' = 99999 yaz 9. Filtr panelinin altındakı 'Tətbiq et' düyməsini bas 10. Səhifənin yuxarısındakı 'N Məhsul' mətnindən nəticə sayını qeyd et 11. 'dən' = 'Ən yüksək qiymət' dəyəri yaz 12. Filtr panelinin altındakı 'Tətbiq et' düyməsini bas 13. Nəticələrin qiymətini yoxla 14. 'dən' = 'Ən yüksək qiymət' + 1 yaz 15. Filtr panelinin altındakı 'Tətbiq et' düyməsini bas 16. Göstərilən mesaja bax | I49: 10.10: Ən yüksək qiymət 7 229 ₼ | J49: 1) bütün nəticələr ≥ 7 000; 2) hamısı ≤ 1 100 (və ya boş vəziyyət); 3) 213 məhsul; 4) yalnız 7 229 ₼-lıq məhsul(lar); 5) 'Məhsul tapılmadı'. Səhifə xəta vermir. | K49: 1) ≥ 7 000 ✔; 2) ≤ 1 100 ✔; 3) 'qədər' sahəsinə Ən yüksək qiymətdən böyük dəyər yazılanda avtomatik 7 229-a endirilir (clamp) və bütün məhsullar göstərilir ✔; 4) ✔; 5) 'dən' = 7 230 yazılanda da avtomatik 7 229-a endirilir — 'Məhsul tapılmadı' əvəzinə 7 229 ₼-lıq məhsullar göstərilir. Davranış ardıcıldır və məqbuldur (sahə sərhədə bərabərləşdirilir). | L49: Pass | M49: Avtomat | N49: A2 — BVA sərhədləri 'Ən yüksək qiymət'dən icra zamanı hesablanır | O49: Xeyr | P49: Xeyr | R49: BR-04, BR-05
A50: TC_FLT_EDGE_023 | B50: SC-009 | C50: Kateqoriya (PLP) | D50: Filtrli URL-də parametr əl ilə səhv dəyərə dəyişdirildikdə boş vəziyyət və ya filtrsiz siyahı göstərilir | E50: P4 — Low | F50: Edge Case · Funksional | G50: Ümumi ön şərt (P0): Chrome son versiya, inkognito pəncərə, 1920×1080, AZ dili, login olmadan; filtr seçilməyib | H50: 1. https://ispace.az/category/iphone ünvanını aç 2. '256 GB' seç 3. Filtr panelinin altındakı 'Tətbiq et' düyməsini bas 4. URL-dəki filtr parametrini qeyd et 5. URL-də parametrin dəyərinin sonuna 'xyz' əlavə et və Enter bas 6. Səhifədə göstərilənə bax 7. URL-də parametrin dəyərini tamamilə sil və Enter bas 8. Səhifədə göstərilənə bax | I50: — | J50: Səhv dəyərdə boş vəziyyət mesajı və ya filtrsiz siyahı göstərilir; texniki xəta mesajı və ya boş ağ səhifə yoxdur. | K50: Gözlənilən nəticəyə uyğundur. | L50: Pass | M50: Manual | N50: M5 | O50: Xeyr | P50: Xeyr | R50: BR-18
A51: TC_PDP_POS_001 | B51: SC-010 | C51: Məhsul səhifəsi (PDP) | D51: Stokda olan məhsulun səhifəsində ad, məhsul kodu, qiymət, aylıq ödəniş, 'Səbətə' və '1 kliklə al' göstərilir | E51: P1 — Critical | F51: Pozitiv · Funksional | G51: Ümumi ön şərt (P0): Chrome son versiya, inkognito pəncərə, 1920×1080, AZ dili, login olmadan | H51: 1. Test datasındakı məhsul səhifəsini aç 2. 'Mağazanın yüklənməsi' yazısı yox olana qədər gözlə 3. Ad, məhsul kodu, qiymət və aylıq ödəniş mətnini yoxla 4. Breadcrumb-u və ən azı 1 şəklin göstərildiyini yoxla 5. 'Səbətə' və '1 kliklə al' düymələrini yoxla | I51: https://ispace.az/product/iphone-17-256-gb-lavender-mg6m4af-a (icra günü stokda olduğunu yoxla) | J51: Ad, məhsul kodu, qiymət, aylıq ödəniş, breadcrumb, ən azı 1 şəkil, 'Səbətə' və '1 kliklə al' düymələri göstərilir. | K51: Ad, məhsul kodu, qiymət, aylıq ödəniş, breadcrumb, şəkil, 'Səbətə' və '1 kliklə al' düymələri göstərilir — gözlənilən nəticəyə uyğundur. | L51: Pass | M51: Avtomat | N51: A1 | O51: Bəli | P51: Bəli | R51: BR-01, BR-08 | S51: Avtomatlaşdırılıb — PASS, 16.10.2026 | T51: Test datası icra zamanı seçilir: 'Mövcuddur' filtrli siyahıdan ilk iPhone. '1 kliklə al' yalnız görünürlük yoxlanır, kliklənmir
A52: TC_PDP_POS_002 | B52: SC-010 | C52: Məhsul səhifəsi (PDP) | D52: PDP-dəki aylıq ödəniş listing kartındakı ilə eynidir | E52: P3 — Medium | F52: Pozitiv · Funksional | G52: Ümumi ön şərt (P0): Chrome son versiya, inkognito pəncərə, 1920×1080, AZ dili, login olmadan | H52: 1. https://ispace.az/category/iphone ünvanını aç 2. Stokda olan məhsul kartındakı aylıq ödəniş məbləğini və ay sayını qeyd et 3. Karta klik et — məhsul səhifəsi açılır 4. Qiymətin altındakı aylıq ödəniş məbləğini və ay sayını kartdakı ilə müqayisə et | I52: Stokda olan istənilən məhsul | J52: Aylıq məbləğ və ay sayı eynidir. | K52: Aylıq məbləğ və ay sayı listing kartı ilə eynidir. | L52: Pass | M52: Avtomat | N52: A2 — pul məlumatıdır; formula yox, uyğunluq yoxlanılır | O52: Bəli | P52: Xeyr | R52: BR-08, BR-09 | S52: Avtomatlaşdırılıb — PASS, 16.10.2026 | T52: Data: stokdakı ilk kart; Java: kartdakı və PDP-dəki aylıq ödəniş mətnində məbləğ və ay sayı eynidir
A53: TC_PDP_UI_003 | B53: SC-010 | C53: Məhsul səhifəsi (PDP) | D53: AZ versiyada məhsul təsviri və texniki göstəricilər tərcümə və orfoqrafiya səhvi olmadan göstərilir | E53: P4 — Low | F53: UI | G53: Ümumi ön şərt (P0): Chrome son versiya, inkognito pəncərə, 1920×1080, AZ dili, login olmadan | H53: 1. https://ispace.az/product/iphone-17-256-gb-lavender-mg6m4af-a ünvanını aç 2. Səhifəni aşağı sürüşdür, 'Məhsul təsviri' bölməsini aç və oxu 3. 'Texniki göstəricilər' bölməsini aç və başlıqları oxu | I53: — | J53: Mətnlər azərbaycancadır, orfoqrafik səhv və tərcümə olunmamış başlıq yoxdur. | K53: Təsvir və texniki göstəricilər azərbaycancadır; orfoqrafik səhv və tərcümə olunmamış başlıq yoxdur. | L53: Pass | M53: Manual | N53: M1 — mətn keyfiyyəti | O53: Xeyr | P53: Xeyr | R53: BR-01, BR-08
A54: TC_PDP_POS_004 | B54: SC-011 | C54: Məhsul səhifəsi (PDP) | D54: Yaddaş variantı dəyişəndə məhsul məlumatları yenilənir | E54: P2 — High | F54: Pozitiv · Funksional | G54: Ümumi ön şərt (P0): Chrome son versiya, inkognito pəncərə, 1920×1080, AZ dili, login olmadan | H54: 1. https://ispace.az/product/iphone-17-256-gb-lavender-mg6m4af-a ünvanını aç 2. Ad, məhsul kodu, qiymət və URL-i qeyd et 3. 'Yaddaş' seçimində '512 GB' bas 4. Yeni ad, məhsul kodu, qiymət, URL və seçili rəngi qeyd et | I54: 256 GB → 512 GB | J54: URL, ad ('512 GB'), məhsul kodu və qiymət yeni varianta aiddir; qiymət 256 GB-dan fərqlidir; rəng seçimi qorunur; 512 GB seçili göstərilir. | K54: 256 GB → 512 GB: URL, ad, məhsul kodu və qiymət yeni varianta keçdi; rəng seçimi qorundu. | L54: Pass | M54: Avtomat | N54: A1, A2 — səhv variantın satışı riski | O54: Bəli | P54: Xeyr | R54: BR-06 | S54: Avtomatlaşdırılıb — PASS, 16.10.2026 | T54: Data icra zamanı: stokdakı ilk iPhone və stokda olan başqa yaddaş variantı (16.10: əvvəlki konkret məhsulun 512 GB-ı stokdan çıxdı). Ad, SKU və qiymət dəyişir, rəng qorunur
A55: TC_PDP_POS_005 | B55: SC-011 | C55: Məhsul səhifəsi (PDP) | D55: Rəng variantı dəyişəndə məhsul məlumatları yenilənir | E55: P2 — High | F55: Pozitiv · Funksional | G55: Ümumi ön şərt (P0): Chrome son versiya, inkognito pəncərə, 1920×1080, AZ dili, login olmadan | H55: 1. https://ispace.az/product/iphone-17-256-gb-lavender-mg6m4af-a ünvanını aç 2. Ad, məhsul kodu, qiymət və URL-i qeyd et 3. 'Rəng' seçimində 'Black' bas 4. Yeni ad, məhsul kodu, qiymət, URL, seçili yaddaş və şəkli qeyd et | I55: Lavender → Black | J55: URL, ad və məhsul kodu yeni rəngə aiddir; yaddaş (256 GB) seçimi dəyişmir; qiymət eyni qalır (eyni yaddaş); şəkil dəyişir. | K55: Lavender → Black: URL, ad, məhsul kodu və şəkil dəyişdi; yaddaş seçimi və qiymət eyni qaldı. | L55: Pass | M55: Avtomat | N55: A1, A2 (şəkil dəyişikliyi manual baxılır) | O55: Bəli | P55: Xeyr | R55: BR-06 | S55: Avtomatlaşdırılıb — PASS, 16.10.2026 | T55: Data icra zamanı: stokdakı ilk iPhone və onun başqa rəngi; ad, SKU, rəng dəyişir, yaddaş və qiymət qorunur. Şəkil dəyişikliyi manual baxılır
A56: TC_PDP_BVA_006 | B56: SC-011 | C56: Məhsul səhifəsi (PDP) | D56: Miqdar 1-dən aşağı enmir, '+' ilə artır | E56: P2 — High | F56: BVA · Funksional | G56: Ümumi ön şərt (P0): Chrome son versiya, inkognito pəncərə, 1920×1080, AZ dili, login olmadan | H56: 1. Stokda olan məhsulun səhifəsini aç (məs. test datası) 2. Miqdar sahəsinin default dəyərini oxu 3. '+' düyməsini bas 4. Miqdarı oxu 5. '−' düyməsini bas 6. Miqdarı oxu 7. '−' düyməsini bir daha bas 8. Miqdarı və '−' düyməsinin vəziyyətini oxu | I56: Miqdar: 1 → 2 → 1 → 1 (min = 1) | J56: Default = 1; '+' sonrası 2; '−' sonrası 1; 1-də '−' deaktivdir və ya dəyər 0-a enmir. | K56: Default miqdar 1; '+' → 2; '−' → 1; 1-də aşağı enmir. | L56: Pass | M56: Avtomat | N56: A2 — sərhəd | O56: Bəli | P56: Xeyr | R56: BR-06, BR-15 | S56: Avtomatlaşdırılıb — PASS, 16.10.2026 | T56: Test datası icra zamanı seçilir: 'Mövcuddur' filtrli siyahıdan ilk iPhone. Miqdar 1-də '−' düyməsinin deaktiv olduğu yoxlanır
A57: TC_PDP_BVA_007 | B57: SC-011 | C57: Məhsul səhifəsi (PDP) | D57: Miqdarın yuxarı həddi stok/limitlə məhdudlaşır | E57: P3 — Medium | F57: BVA · Funksional | G57: Ümumi ön şərt (P0): Chrome son versiya, inkognito pəncərə, 1920×1080, AZ dili, login olmadan | H57: 1. Stokda olan məhsulun səhifəsini aç 2. Miqdarın '+' düyməsini ardıcıl 20 dəfə bas 3. Miqdarın dayandığı dəyəri və göstərilən mesajı qeyd et | I57: — | J57: Müəyyən həddən sonra miqdar artmır və istifadəçiyə bildirilir; və ya limit yoxdursa, səbətdə stokdan artıq sifariş qarşısı alınır. | K57: Miqdar mövcud stok sayına qədər artır; həddə çatanda altda mövcud miqdar barədə mesaj göstərilir (BR-15 təsdiqləndi). | L57: Pass | M57: Manual | N57: M5 — limit tələbdə göstərilməyib, əvvəl müşahidə və biznes təsdiqi lazımdır | O57: Xeyr | P57: Xeyr | R57: BR-06, BR-15
A58: TC_PDP_POS_008 | B58: SC-011 | C58: Məhsul səhifəsi (PDP) | D58: Qoruma proqramı seçimi göstərilən məbləğə təsir edir | E58: P3 — Medium | F58: Pozitiv · Funksional | G58: Ümumi ön şərt (P0): Chrome son versiya, inkognito pəncərə, 1920×1080, AZ dili, login olmadan | H58: 1. Stokda olan iPhone məhsul səhifəsini aç 2. Göstərilən yekun məbləği qeyd et 3. '+1 il zədələrə qarşı qorunma' seçimini bas 4. Seçimin işarələndiyini və məbləği qeyd et 5. 'Əlavə proqram olmadan' seçimini bas 6. Seçimin dəyişdiyini və məbləği qeyd et | I58: Proqram qiyməti icra zamanı oxunur (04.10: 362 ₼) | J58: Proqram seçiləndə seçim vizual işarələnir və yekun məbləğ (göstərilirsə) proqram qiyməti qədər artır; ləğv ediləndə ilkin vəziyyətə qayıdır. | K58: Gözlənilən nəticəyə uyğundur: proqram seçildikdə işarələnir, 'Əlavə proqram olmadan' seçildikdə seçim ləğv olunur və ilkin vəziyyət bərpa olunur (10.10 təkrar yoxlama). | L58: Pass | M58: Avtomat | N58: A2 | O58: Xeyr | P58: Xeyr | R58: BR-06, BR-15 | S58: Avtomatlaşdırılıb — PASS, 16.10.2026 | T58: PDP-dəki yekun məbləğ (aşağı panel) = qiymət + proqram; ləğvdən sonra ilkin məbləğ
A59: TC_PDP_POS_009 | B59: SC-011 | C59: Məhsul səhifəsi (PDP) | D59: '1 kliklə al' formasında səhv formatlı telefon nömrəsi yazıldıqda sahənin altında xəta mesajı göstərilir (göndərmədən) | E59: P3 — Medium | F59: Pozitiv · Funksional | G59: Ümumi ön şərt (P0): Chrome son versiya, inkognito pəncərə, 1920×1080, AZ dili, login olmadan | H59: 1. Stokda olan məhsulun səhifəsini aç 2. '1 kliklə al' düyməsini bas — forma açılır 3. Sahələri boş saxla və formanın təsdiq düyməsini bas 4. Hər sahənin altındakı mesajı oxu 5. Telefon sahəsinə '123' yaz və təsdiq düyməsini bas 6. Göstərilən mesajı oxu 7. Formanı 'X' ilə bağla — sorğu GÖNDƏRİLMİR | I59: Boş; telefon '123' | J59: Telefon sahəsinin altında nömrənin yanlış olduğu barədə aydın mesaj göstərilir; forma göndərilmir. | K59: Gözlənilən nəticəyə uyğundur: səhv formatlı telefon nömrəsində sahəyə aid 'telefon nömrəsi yanlışdır' mesajı göstərilir; forma göndərilmədi (10.10 təkrar yoxlama). | L59: Pass | M59: Manual | N59: M2 — submit real sifariş yaradır | O59: Xeyr | P59: Xeyr | R59: BR-06, BR-15
A60: TC_PDP_POS_010 | B60: SC-011 | C60: Məhsul səhifəsi (PDP) | D60: Variant (yaddaş və rəng) seçildikdən sonra səhifə yeniləndikdə seçilmiş variant, URL və qiymət saxlanılır | E60: P3 — Medium | F60: Pozitiv · Funksional | G60: Ümumi ön şərt (P0): Chrome son versiya, inkognito pəncərə, 1920×1080, AZ dili, login olmadan | H60: 1. https://ispace.az/product/iphone-18-pro-256-gb-black-mjrp4af-a ünvanını aç 2. Yaddaş seçimində '512 GB' bas 3. Rəng seçimində 'Qara'dan fərqli rəng bas 4. URL-i, adı, seçili yaddaşı, rəngi və qiyməti qeyd et 5. Brauzerin 'Yenilə' düyməsini (F5) bas 6. 'Mağazanın yüklənməsi' yazısı yox olana qədər gözlə 7. URL-i, adı, seçili yaddaşı, rəngi və qiyməti 4-cü addımdakı dəyərlərlə müqayisə et | I60: Başlanğıc: iPhone 18 Pro, 256 GB, Qara (https://ispace.az/product/iphone-18-pro-256-gb-black-mjrp4af-a); seçim: 512 GB + başqa rəng | J60: Yeniləmədən sonra URL, ad, seçili yaddaş və rəng, qiymət yeniləmədən əvvəlki ilə eynidir; səhifə ilkin variantına (256 GB, Qara) qayıtmır. | K60: 512 GB və başqa rəng seçilib səhifə yeniləndikdən sonra URL, ad, seçili yaddaş və rəng, qiymət dəyişmədi; səhifə ilkin variantına qayıtmadı (11.10 icrası). | L60: Pass | M60: Avtomat | N60: A2 — deterministik: URL, ad və seçili variant yoxlanılır | O60: Xeyr | P60: Xeyr | R60: BR-06
A61: TC_PDP_POS_011 | B61: SC-012 | C61: Məhsul səhifəsi (PDP) | D61: Stokda olmayan məhsul alına bilmir | E61: P2 — High | F61: Pozitiv · Funksional | G61: Ümumi ön şərt (P0): Chrome son versiya, inkognito pəncərə, 1920×1080, AZ dili, login olmadan | H61: 1. Test datasındakı stokda olmayan məhsulun səhifəsini aç 2. 'Səbətə' və '1 kliklə al' düymələrinin olub-olmadığını yoxla 3. Göstərilən düymənin mətnini qeyd et 4. Miqdar seçimini və çatdırılma blokunu yoxla | I61: https://ispace.az/product/iphone-16e-128-gb-black-md1q4hx-a (icra günü stokda olmadığını yoxla) | J61: 'Səbətə' və '1 kliklə al' yoxdur; 'Mövcud olduqda bildirin' düyməsi var; miqdar seçimi yoxdur; çatdırılma növləri 'Mövcud deyil' göstərilir. | K61: Stokda olmayan məhsulda 'Səbətə' və '1 kliklə al' yoxdur; 'Mövcud deyil' və 'Mövcud olduqda bildirin' göstərilir. | L61: Pass | M61: Avtomat | N61: A1, A2 — test datası filtrdən icra zamanı götürülür | O61: Bəli | P61: Xeyr | R61: BR-11 | S61: Avtomatlaşdırılıb — PASS, 16.10.2026 | T61: Data: 'Mövcud deyil' siyahısından ilk məhsul; 'Səbətə', '1 kliklə al' və miqdar sahəsi yoxdur, 'Mənə xəbər ver' var
A62: TC_PDP_UI_012 | B62: SC-012 | C62: Məhsul səhifəsi (PDP) | D62: Stokda olmayan məhsul üçün düymə mətnləri listing və PDP-də eynidir | E62: P4 — Low | F62: UI | G62: Ümumi ön şərt (P0): Chrome son versiya, inkognito pəncərə, 1920×1080, AZ dili, login olmadan | H62: 1. https://ispace.az/category/iphone ünvanını aç 2. 'Mövcud deyil' filtrini tətbiq et 3. Bir kartın düyməsinin mətnini qeyd et 4. Həmin karta klik et — məhsul səhifəsi açılır 5. Məhsul səhifəsindəki düymənin mətnini kartdakı ilə müqayisə et | I62: — | J62: Eyni hərəkət üçün eyni mətn işlədilir. | K62: Stokda olmayan məhsulların bir qismində 'Ön sifariş', bir qismində 'Mənə xəbər ver' göstərilir. Hansı vəziyyətin hansı düyməni göstərdiyi biznesdən təsdiqlənməlidir. | L62: Pass | M62: Manual | N62: M1 — terminologiya qiymətləndirməsi | O62: Xeyr | P62: Xeyr | R62: BR-11
A63: TC_FIN_POS_001 | B63: SC-013 | C63: Taksit proqramları | D63: 'Bütün proqramlara baxın' 'Taksitlə alış' pəncərəsini PDP-dəki məhsulla açır | E63: P2 — High | F63: Pozitiv · Funksional | G63: Ümumi ön şərt (P0): Chrome son versiya, inkognito pəncərə, 1920×1080, AZ dili, login olmadan; iPhone 18 Pro, 256 GB, Qara PDP-si açıqdır (3 589 ₼; icra günü stokda olduğunu yoxla) | H63: 1. Qiymətin altındakı 'Bütün proqramlara baxın' linkinə klik et — 'Taksitlə alış' pəncərəsi açılır 2. Pəncərənin başlığını oxu 3. Pəncərədəki məhsul adını, Seriya/Yaddaş/Rəngi, miqdarı və qiyməti məhsul səhifəsi ilə müqayisə et 4. Qoruma blokunun, müddət düymələrinin, tərəfdaşların, 'Ödəmək', 'Almaq' və 'Taksitlə davam et' düymələrinin göstərildiyini yoxla | I63: Pəncərənin quruluşu (08.10 ekran görüntüsü): məhsul (ad, Seriya/Yaddaş/Rəng), miqdar (− 1 +), qiymət; 'Bütün risklərdən qorunma' (+1 il zədələrə qarşı qorunma 538 ₼ / Əlavə proqram olmadan); 'Zəmanət'; 'Taksit kartları' müddət düymələri (3/6/9/12/18 ay); tərəfdaşlar ('UCard' / Unibank, Leobank) — 'A ₼ × N ödəniş' və 'Ümumi ödəniş məbləği'; 'Ödəmək'; 'Almaq' və 'Taksitlə davam et' düymələri. | J63: 1. 'Taksitlə alış' başlıqlı pəncərə açılır. 2. Ad, variant, miqdar (1) və qiymət (3 589 ₼) PDP ilə eynidir. 3. Qoruma bloku, 'Taksit kartları' müddətləri, ən azı 1 tərəfdaş, 'Ödəmək', 'Almaq' və 'Taksitlə davam et' göstərilir. | K63: Pəncərə 'Taksitlə alış' başlığı ilə açılır; məhsul, variant, miqdar 1 və 3 589 ₼ PDP ilə eynidir; qoruma bloku, müddətlər, tərəfdaşlar, 'Ödəmək', 'Almaq' və 'Taksitlə davam et' göstərilir. | L63: Pass | M63: Avtomat | N63: A1 — taksit qərarının giriş nöqtəsi | O63: Bəli | P63: Xeyr | R63: BR-17 | S63: Avtomatlaşdırılıb — PASS, 16.10.2026 | T63: Pəncərədəki ad və qiymət PDP ilə eynidir; 'Almaq' / 'Taksitlə davam et' yalnız görünürlük yoxlanır, kliklənmir
A64: TC_FIN_POS_002 | B64: SC-013 | C64: Taksit proqramları | D64: PDP-dəki aylıq ödəniş pəncərədəki müddət və tərəfdaş məbləği ilə eynidir | E64: P1 — Critical | F64: Pozitiv · Funksional | G64: Ümumi ön şərt (P0): Chrome son versiya, inkognito pəncərə, 1920×1080, AZ dili, login olmadan; iPhone 18 Pro, 256 GB, Qara PDP-si açıqdır (3 589 ₼; icra günü stokda olduğunu yoxla) | H64: 1. Məhsul səhifəsində qiymətin altındakı aylıq məbləği və ay sayını qeyd et 2. Qiymətin altındakı 'Bütün proqramlara baxın' linkinə klik et — 'Taksitlə alış' pəncərəsi açılır 3. Həmin ay sayının düyməsini və tərəfdaşların aylıq məbləğini oxu 4. Qeyd etdiyin məbləğlə müqayisə et 5. iPhone 17, 256 GB məhsul səhifəsində 1–4-cü addımları təkrarla | I64: iPhone 18 Pro: PDP '199 ₼/ay 18 ay' → pəncərə '18 ay 199 ₼'. iPhone 17: 24 ay və 18 ay təklifləri | J64: PDP-dəki hər 'məbləğ + müddət' pəncərədə eyni məbləğlə mövcuddur. PDP-də göstərilən müddətin (məs. 24 ay) pəncərədə düyməsi var. | K64: Məhsul səhifəsindəki '199 ₼/ay 18 ay' pəncərədə '18 ay — 199 ₼' ilə eynidir; iPhone 17 üçün göstərilən müddətlərin də pəncərədə düyməsi var. | L64: Pass | M64: Avtomat | N64: A1, A2 | O64: Bəli | P64: Xeyr | R64: BR-08, BR-09 | S64: Avtomatlaşdırılıb — PASS, 16.10.2026 | T64: Java: PDP-dəki 'X ₼/ay N aya' mətnindən N ay düyməsi tapılır və basılır; pəncərədə aylıq məbləğ X olmalıdır
A65: TC_FIN_POS_003 | B65: SC-013 | C65: Taksit proqramları | D65: Hər tərəfdaş üçün 'aylıq × ödəniş sayı' 'Ümumi ödəniş məbləği'nə bərabərdir | E65: P1 — Critical | F65: Pozitiv · Funksional | G65: Ümumi ön şərt (P0): Chrome son versiya, inkognito pəncərə, 1920×1080, AZ dili, login olmadan; iPhone 18 Pro, 256 GB, Qara PDP-si açıqdır (3 589 ₼; icra günü stokda olduğunu yoxla); 'Bütün proqramlara baxın' → 'Taksitlə alış' pəncərəsi açılıb | H65: 1. Pəncərədə '18 ay' düyməsini bas 2. Hər tərəfdaş üçün 'A ₼ × N ödəniş' və 'Ümumi ödəniş məbləği'ni qeyd et 3. Hər tərəfdaş üçün A × N hesabla və 'Ümumi ödəniş məbləği' ilə müqayisə et 4. '3 ay', '6 ay', '9 ay', '12 ay' üçün 1–3-cü addımları təkrarla | I65: Gözlənilən hesab: UCard 199 × 18 = 3 582; Leobank 217 × 18 = 3 906 | J65: Hər tərəfdaş və hər müddət üçün A × N = 'Ümumi ödəniş məbləği'. Əgər son ödəniş fərqlidirsə, bu, pəncərədə açıq göstərilir (məs. '17 × 199 ₼ + 1 × 206 ₼'). | K65: 08.10 ekran görüntüsü (iPhone 18 Pro 256 GB Qara, 3 589 ₼, '18 ay'): UCard/Unibank — '199 ₼ × 18 ödəniş', 'Ümumi ödəniş məbləği 3 589 ₼', amma 199 × 18 = 3 582 ₼ (−7 ₼). Leobank — '217 ₼ × 18 ödəniş', ümumi 3 912 ₼, amma 217 × 18 = 3 906 ₼ (−6 ₼). Pəncərənin göstərdiyi aylıq məbləğ və ödəniş sayı ümumi məbləği vermir; son ödənişin fərqli olduğu göstərilmir. 3/6/9/12 ay üçün yoxlama davam edir. | L65: Fail | M65: Avtomat | N65: A1, A2 — pəncərənin öz rəqəmləri bir-birini təsdiqləməlidir | O65: Bəli | P65: Xeyr | Q65: BUG-017 | R65: BR-08, BR-17 | S65: Avtomatlaşdırılıb — FAIL (BUG-017, gözlənilən), 16.10.2026 | T65: Tag: known-bug. 12.10-da da FAIL: UCard 199 × 18 = 3 582 ≠ 3 589; Leobank 217 × 18 = 3 906 ≠ 3 912. Yalnız məlumat pəncərəsi açılır, 'Almaq' / 'Taksitlə davam et' kliklənmir
A66: TC_FIN_POS_004 | B66: SC-013 | C66: Taksit proqramları | D66: 0% tərəfdaşda ümumi məbləğ qiymətə bərabərdir, faizlidə əlavə xərc görünür | E66: P1 — Critical | F66: Pozitiv · Funksional | G66: Ümumi ön şərt (P0): Chrome son versiya, inkognito pəncərə, 1920×1080, AZ dili, login olmadan; iPhone 18 Pro, 256 GB, Qara PDP-si açıqdır (3 589 ₼; icra günü stokda olduğunu yoxla); 'Bütün proqramlara baxın' → 'Taksitlə alış' pəncərəsi açılıb | H66: 1. Pəncərədə '18 ay' düyməsini bas 2. Hər tərəfdaşın 'Ümumi ödəniş məbləği'ni qeyd et 3. Hər məbləği məhsulun qiyməti (3 589 ₼) ilə müqayisə et 4. Fərqi və faizini hesabla 5. Pəncərədə faizin və ya əlavə xərcin yazılıb-yazılmadığına bax | I66: 08.10: UCard 3 589 ₼ (0%); Leobank 3 912 ₼ → +323 ₼ (+9,0%) | J66: Qiymətə bərabər olan proqram 0% kimi qəbul edilir. Qiymətdən baha olan proqramda ümumi məbləğ göstərilir və istifadəçi əlavə xərci (323 ₼) aydın görür. Proqram '0%' kimi təqdim olunub ümumi məbləği qiymətdən çoxdursa — bug. | K66: 18 ay: UCard ümumi ödəniş = 3 589 ₼ (qiymət, 0%); Leobank ümumi 3 912 ₼ açıq göstərilir — əlavə xərc (323 ₼) istifadəçiyə görünür. | L66: Pass | M66: Avtomat | N66: A2, A3 | O66: Bəli | P66: Xeyr | R66: BR-17 | S66: Avtomatlaşdırılıb — PASS, 16.10.2026 | T66: 18 ay: 'Ödəmək' = qiymət (0%); heç bir tərəfdaşın ümumi ödəniş məbləği qiymətdən az deyil
A67: TC_FIN_BVA_005 | B67: SC-013 | C67: Taksit proqramları | D67: Bütün müddət düymələrində aylıq məbləğ yuvarlaqlaşdırması ardıcıldır | E67: P3 — Medium | F67: BVA · Funksional | G67: Ümumi ön şərt (P0): Chrome son versiya, inkognito pəncərə, 1920×1080, AZ dili, login olmadan; iPhone 18 Pro, 256 GB, Qara PDP-si açıqdır (3 589 ₼; icra günü stokda olduğunu yoxla); 'Bütün proqramlara baxın' → 'Taksitlə alış' pəncərəsi açılıb | H67: 1. Pəncərədə hər müddət düyməsindəki (3, 6, 9, 12, 18 ay) məbləği qeyd et 2. Hər müddət üçün 3 589 / ay sayını hesabla və göstərilən məbləğlə müqayisə et 3. Hər müddət düyməsini bas və 'Ümumi ödəniş məbləği'ni qeyd et 4. Hər müddət üçün 'aylıq × ay sayı'nı 'Ümumi ödəniş məbləği' ilə müqayisə et | I67: Məhsul: iPhone 18 Pro, 256 GB, Qara — qiyməti 3 589 ₼ (https://ispace.az/product/iphone-18-pro-256-gb-black-mjrp4af-a). Hesab: 3 589 / 3 = 1 196,33 → 1 196 (×3 = 3 588); / 6 = 598,17 → 598 (3 588); / 9 = 398,78 → 399 (3 591); / 12 = 299,08 → 299 (3 588); / 18 = 199,39 → 199 (3 582) | J67: Yuvarlaqlaşdırma bütün müddətlərdə eyni qaydadır və ümumi məbləğ bütün 0% müddətlərdə 3 589 ₼-dır. 9 ayda müştəri 3 591 ₼ (qiymətdən çox) ödəyəcək kimi görünmür. | K67: 10.10 ekran görüntüsü (iPhone 18 Pro 3 589 ₼, zəmanət 'Əlavə proqram olmadan', '3 ay', UCard və Tamkart): düymələr 3 ay 1 196 / 6 ay 598 / 9 ay 399 / 12 ay 299 / 18 ay 199 ₼. Yuvarlaqlaşdırma qaydası ardıcıldır: hamısı ən yaxın tam manata (1 196,33 → 1 196; 398,78 → 399) — bu hissə uyğundur. Amma A × N heç bir müddətdə 3 589 vermir: 3 ay 1 196 × 3 = 3 588 (−1); 6 ay 3 588 (−1); 9 ay 399 × 9 = 3 591 (+2, qiymətdən çox); 12 ay 3 588 (−1); 18 ay 3 582 (−7). 3 ayda pəncərədə 'Ümumi ödəniş məbləği' və 'Ödəmək' 3 589 ₼ göstərilir, yəni ümumi məbləğ düzgündür, aylıq ödəniş isə qəpiksiz yuvarlaqlaşdırılıb və son ödənişin fərqli olacağı göstərilmir. Fərq müddətdən asılı olaraq həm mənfi, həm müsbət olur. 6/9/12 ay üçün ümumi məbləğ pəncərədə ayrıca yoxlanmalıdır. | L67: Fail | M67: Manual | N67: M5 — yuvarlaqlaşdırma qaydası biznesdən təsdiqlənməlidir | O67: Xeyr | P67: Xeyr | Q67: BUG-017 | R67: BR-08, BR-17
A68: TC_FIN_BVA_006 | B68: SC-013 | C68: Taksit proqramları | D68: iPhone keyslərindən ən ucuzunda (9 ₼) taksitin aylıq məbləği × ay sayı məhsulun qiymətindən çox olmur | E68: P2 — High | F68: BVA · Funksional | G68: Ümumi ön şərt (P0): Chrome son versiya, inkognito pəncərə, 1920×1080, AZ dili, login olmadan | H68: 1. https://ispace.az/accessories-for-iphone ünvanını aç 2. 'Keyslər' bölməsinə keç 3. Sıralama siyahısından 'Aşağı qiymət' seç 4. Ən ucuz keysin şəklinə klik et və qiymətini (Q) qeyd et 5. Qiymətin altındakı 'Bütün proqramlara baxın' linkinə klik et — 'Taksitlə alış' pəncərəsi açılır 6. '18 ay' düyməsini bas 7. 'A ₼ × N ödəniş' və 'Ümumi ödəniş məbləği'ni qeyd et 8. A × N-i hesabla və Q ilə müqayisə et | I68: iPhone üçün aksesuarlar → Keyslər, 'Aşağı qiymət' ilə ən ucuz keys: Q = 9 ₼ (10.10) | J68: Aylıq məbləğ qəpiklə göstərilir (9 / 18 = 0,50 ₼) və ya bu qədər ucuz məhsula taksit təklif olunmur; A × N məhsulun qiymətindən (9 ₼) çox deyil. | K68: iPhone üçün aksesuarlardan 'Keyslər' bölməsinə keçildi və 'Aşağı qiymət' ilə ən ucuz keys seçildi — qiyməti 9 ₼. 'Bütün proqramlara baxın' açıldıqda 18 aya qədər taksit '1 ₼-dan' göstərilir: 1 ₼ × 18 = 18 ₼, keysin qiyməti isə 9 ₼ — müştəriyə göstərilən aylıq ödəniş qiymətin 2 mislini verir (aylıq 0,50 ₼ olmalı idi). (10.10 icrası) | L68: Fail | M68: Avtomat | N68: A2 — test datası sıralamadan icra zamanı götürülür | O68: Bəli | P68: Xeyr | Q68: BUG-016 | R68: BR-08, BR-17 | S68: Avtomatlaşdırılıb — FAIL (BUG-016, gözlənilən), 16.10.2026 | T68: Tag: known-bug. Data: aksesuarlar 'Aşağı qiymət' + 'Mövcuddur', ilk məhsul (≤ 20 ₼), ən uzun müddət. 16.10-da FAIL: 1 ₼ × 18 = 18 ≠ 9 ₼ (BUG-016)
A69: TC_FIN_EDGE_007 | B69: SC-013 | C69: Taksit proqramları | D69: Müddət düyməsindəki məbləğin hansı tərəfdaşa aid olduğu aydındır | E69: P3 — Medium | F69: Edge Case · UI | G69: Ümumi ön şərt (P0): Chrome son versiya, inkognito pəncərə, 1920×1080, AZ dili, login olmadan; iPhone 18 Pro, 256 GB, Qara PDP-si açıqdır (3 589 ₼; icra günü stokda olduğunu yoxla); 'Bütün proqramlara baxın' → 'Taksitlə alış' pəncərəsi açılıb | H69: 1. Pəncərədə '18 ay' düyməsindəki məbləği qeyd et 2. Tərəfdaşların aylıq məbləğlərini oxu və düymədəki məbləğin hansına aid olduğunu müəyyən et 3. 'Leobank' radio düyməsini seç 4. '18 ay' düyməsindəki məbləğə yenidən bax | I69: iPhone 18 Pro, 256 GB, Qara — https://ispace.az/product/iphone-18-pro-256-gb-black-mjrp4af-a | J69: Düymədəki məbləğ ya seçilmiş tərəfdaşa uyğun yenilənir, ya da '-dan' kimi minimum məbləğ olduğu yazılır. Leobank seçili ikən düymədə izahsız 199 ₼ qalması — uyğunsuzluq. | K69: '18 ay' düyməsində 199 ₼ göstərilir (UCard-ın aylıq məbləği). Leobank seçildikdə 'Taksit kartları' hissəsindəki '18 ay' düyməsində məbləğ dəyişmir, 199 ₼ qalır; Leobank-ın öz sətrində isə '217 ₼ × 18 ödəniş' yazılıb (10.10 icrası). | L69: Fail | M69: Manual | N69: M1 | O69: Xeyr | P69: Xeyr | Q69: BUG-029 | R69: BR-08, BR-17
A70: TC_FIN_EDGE_008 | B70: SC-013 | C70: Taksit proqramları | D70: Endirimli məhsulun taksit pəncərəsində hər müddət üçün 'aylıq × ay sayı' endirimli qiymətə bərabərdir | E70: P2 — High | F70: Edge Case · Funksional | G70: Ümumi ön şərt (P0): Chrome son versiya, inkognito pəncərə, 1920×1080, AZ dili, login olmadan | H70: 1. https://ispace.az/category/extra-deals ünvanını aç 2. Üstündən xətt çəkilmiş köhnə qiyməti (K) olan məhsulu seç — test datası 3. Yeni (endirimli) qiyməti (Y) qeyd et 4. 'Səbətə' bas 5. Header-in sağındakı səbət ikonuna klik et və 'Səbətimə baxın' bas — https://ispace.az/cart açılır 6. Səbətdə 'Bütün proqramlara baxın' linkinə klik et 7. Pəncərədə 3, 6, 9, 12 və 18 ay düymələrini ardıcıl bas və hər birində aylıq məbləği (A) qeyd et 8. Hər müddət üçün A × ay sayını hesabla və Y ilə müqayisə et | I70: Ev audio sistemi BANG & OLUFSEN Beosound A9, Gen.5, Black Anthracite — endirimli qiymət Y = 5 999 ₼ (https://ispace.az/product/home-audio-system-bang-olufsen-beosound-a9-5th-gen-black-anthracite-1200632) | J70: Pəncərə endirimli qiyməti (5 999 ₼) istifadə edir və hər müddətdə aylıq × ay sayı = 5 999 ₼; fərq varsa (məs. son ödəniş fərqlidir), bu pəncərədə yazılır. | K70: Pəncərə endirimli qiyməti (5 999 ₼) istifadə edir, amma heç bir müddətdə aylıq × ay sayı 5 999 ₼ deyil: 3 ay — 2 000 × 3 = 6 000 (1 ₼ çox); 6 ay — 1 000 × 6 = 6 000 (1 ₼ çox); 9 ay — 667 × 9 = 6 003 (4 ₼ çox); 12 ay — 500 × 12 = 6 000 (1 ₼ çox); 18 ay — 333 × 18 = 5 994 (5 ₼ az). Son ödənişin fərqli olacağı pəncərədə yazılmır (10.10 icrası). | L70: Fail | M70: Manual | N70: M3 — endirimli məhsullar kampaniyaya görə dəyişir | O70: Xeyr | P70: Xeyr | Q70: BUG-017 | R70: BR-17
A71: TC_FIN_POS_009 | B71: SC-014 | C71: Taksit proqramları | D71: Müddət düyməsi dəyişdikdə tərəfdaş məbləğləri və 'Ödəmək' yenilənir | E71: P2 — High | F71: Pozitiv · Funksional | G71: Ümumi ön şərt (P0): Chrome son versiya, inkognito pəncərə, 1920×1080, AZ dili, login olmadan; iPhone 18 Pro, 256 GB, Qara PDP-si açıqdır (3 589 ₼; icra günü stokda olduğunu yoxla); 'Bütün proqramlara baxın' → 'Taksitlə alış' pəncərəsi açılıb | H71: 1. Pəncərədə '18 ay' seçili ikən tərəfdaş məbləğlərini və 'Ödəmək'i qeyd et 2. '3 ay' düyməsini bas və dəyərləri qeyd et 3. '12 ay' düyməsini bas və dəyərləri qeyd et 4. Yenidən '18 ay' bas və dəyərləri ilkin dəyərlərlə müqayisə et | I71: Gözlənilən: 3 ay ≈ 1 196 ₼, 12 ay ≈ 299 ₼ | J71: Hər keçiddə seçili düymə vurğulanır; tərəfdaş məbləğləri və ödəniş sayı ('× N ödəniş') yeni müddətə uyğun yenilənir; həmin müddəti dəstəkləməyən tərəfdaş gizlənir və ya deaktivdir; '18 ay'a qayıdanda ilkin dəyərlər bərpa olunur. | K71: Müddət düymələri arasında keçiddə seçili düymə vurğulanır, tərəfdaş məbləğləri və ödəniş sayı yeni müddətə uyğun yenilənir; 18 aya qayıdanda ilkin dəyərlər bərpa olunur. | L71: Pass | M71: Avtomat | N71: A2 | O71: Xeyr | P71: Xeyr | R71: BR-17 | S71: Avtomatlaşdırılıb — PASS, 16.10.2026 | T71: 18 ay → 12 ay → 18 ay: ödəniş sayı və aylıq məbləğ dəyişir, 18-ə qayıdanda ilkin məbləğ bərpa olunur
A72: TC_FIN_POS_010 | B72: SC-014 | C72: Taksit proqramları | D72: Tərəfdaş dəyişdikdə 'Ödəmək' və seçim məlumatı uyğun dəyişir | E72: P2 — High | F72: Pozitiv · Funksional | G72: Ümumi ön şərt (P0): Chrome son versiya, inkognito pəncərə, 1920×1080, AZ dili, login olmadan; iPhone 18 Pro, 256 GB, Qara PDP-si açıqdır (3 589 ₼; icra günü stokda olduğunu yoxla); 'Bütün proqramlara baxın' → 'Taksitlə alış' pəncərəsi açılıb | H72: 1. Pəncərədə '18 ay' bas 2. 'UCard' seçili ikən 'Ödəmək' dəyərini qeyd et 3. 'Leobank' radio düyməsini seç 4. 'Ödəmək' dəyərinə və radio düymələrinin vəziyyətinə bax | I72: UCard ümumi 3 589 ₼; Leobank ümumi 3 912 ₼ | J72: Yalnız bir tərəfdaş seçili olur. 'Ödəmək' ya seçilmiş proqramın ümumi məbləğini (3 912 ₼) göstərir, ya da açıq şəkildə 'məhsulun qiyməti' kimi işarələnir. Leobank seçildikdə 3 589 ₼-ın işarəsiz qalması müştərini çaşdırır. | K72: Tərəfdaş dəyişdikdə yalnız bir radio seçili olur; 'Ödəmək' və seçim məlumatı gözlənilən nəticəyə uyğundur. | L72: Pass | M72: Manual | N72: M5 — 'Ödəmək' sahəsinin mənası tələbdə yoxdur | O72: Xeyr | P72: Xeyr | R72: BR-17
A73: TC_FIN_POS_011 | B73: SC-014 | C73: Taksit proqramları | D73: Variant dəyişdikdə pəncərədə köhnə qiymətin məbləğləri qalmır | E73: P2 — High | F73: Pozitiv · Funksional | G73: Ümumi ön şərt (P0): Chrome son versiya, inkognito pəncərə, 1920×1080, AZ dili, login olmadan; iPhone 18 Pro, 256 GB, Qara PDP-si açıqdır (3 589 ₼; icra günü stokda olduğunu yoxla) | H73: 1. Qiymətin altındakı 'Bütün proqramlara baxın' linkinə klik et — 'Taksitlə alış' pəncərəsi açılır 2. '18 ay' məbləğini qeyd et 3. Pəncərəni 'X' ilə bağla 4. Məhsul səhifəsində 'Yaddaş' seçimində '512 GB' bas (səhifəni yeniləmə) 5. Pəncərəni yenidən aç 6. Ad, qiymət və '18 ay' məbləğini yoxla | I73: 256 GB → 512 GB (04.10: 4 129 ₼ → 18 ay ≈ 229 ₼) | J73: Pəncərədə ad '512 GB', qiymət və bütün taksit məbləğləri yeni qiymətə görədir; 256 GB-ın dəyərləri keşdə qalmır. | K73: 512 GB seçildikdən sonra pəncərədə ad, qiymət və taksit məbləğləri yeni variantadır; köhnə dəyərlər qalmır. | L73: Pass | M73: Avtomat | N73: A1, A2 — keş regression-u | O73: Xeyr | P73: Xeyr | R73: BR-06
A74: TC_FIN_POS_012 | B74: SC-014 | C74: Taksit proqramları | D74: Pəncərədə qoruma proqramı seçimi 'Ödəmək' və taksit məbləğlərini yeniləyir, ləğv bərpa edir | E74: P1 — Critical | F74: Pozitiv · Funksional | G74: Ümumi ön şərt (P0): Chrome son versiya, inkognito pəncərə, 1920×1080, AZ dili, login olmadan; iPhone 18 Pro, 256 GB, Qara PDP-si açıqdır (3 589 ₼; icra günü stokda olduğunu yoxla); 'Bütün proqramlara baxın' → 'Taksitlə alış' pəncərəsi açılıb | H74: 1. Pəncərədə '+1 il zədələrə qarşı qorunma' seç 2. 'Ödəmək'i və '18 ay' məbləğlərini qeyd et 3. 'Əlavə proqram olmadan' seç 4. 'Ödəmək'i və '18 ay' məbləğlərini yenidən qeyd et | I74: 3 589 + 538 = 4 127 ₼; 4 127 / 18 = 229,28 ≈ 229 ₼ | J74: Seçimdən sonra 'Ödəmək' = 4 127 ₼ və taksit məbləğləri yeni bazaya görə hesablanır (18 ay ≈ 229 ₼). 'Əlavə proqram olmadan' seçiləndə dəyərlər 3 589 ₼ və 199 ₼-a qayıdır — səhifəni yeniləmək lazım olmur. | K74: Qoruma proqramı seçildikdə 'Ödəmək' və taksit məbləğləri yeni bazaya görə yenilənir; 'Əlavə proqram olmadan' seçildikdə ilkin dəyərlər bərpa olunur (səhifəni yeniləmək lazım olmur). | L74: Pass | M74: Avtomat | N74: A1, A2 — pul hesablaması; BUG-002 ilə əlaqəli | O74: Bəli | P74: Xeyr | R74: BR-17 | S74: Avtomatlaşdırılıb — PASS, 16.10.2026 | T74: Pəncərədə proqram seçiləndə 'Ödəmək' və ümumi məbləğ = qiymət + proqram, aylıq məbləğ dəyişir; ləğvdən sonra ilkin dəyərlər qayıdır
A75: TC_FIN_BVA_013 | B75: SC-014 | C75: Taksit proqramları | D75: Pəncərədəki miqdar dəyişdikdə qiymət və taksitlər yenilənir | E75: P2 — High | F75: BVA · Funksional | G75: Ümumi ön şərt (P0): Chrome son versiya, inkognito pəncərə, 1920×1080, AZ dili, login olmadan; iPhone 18 Pro, 256 GB, Qara PDP-si açıqdır (3 589 ₼; icra günü stokda olduğunu yoxla); 'Bütün proqramlara baxın' → 'Taksitlə alış' pəncərəsi açılıb | H75: 1. Pəncərədə miqdar 1 ikən '−' düyməsinin vəziyyətinə bax 2. '+' düyməsini bas (miqdar 2) 3. Qiyməti, 'Ödəmək'i və '18 ay' məbləğlərini qeyd et 4. '−' düyməsini bas (miqdar 1) 5. Dəyərlərin ilkin vəziyyətə qayıtdığını yoxla | I75: 2 × 3 589 = 7 178 ₼; 7 178 / 18 = 398,78 ≈ 399 ₼ | J75: 1-də '−' deaktivdir. Miqdar 2-də qiymət/Ödəmək 7 178 ₼, 18 ay ≈ 399 ₼ (və hər tərəfdaşda A × N = ümumi). 1-ə qaytaranda ilkin dəyərlər bərpa olunur. | K75: Miqdar 1-də '−' deaktivdir; 2-də qiymət, 'Ödəmək' və taksitlər iki qat hesablanır; 1-ə qaytaranda ilkin dəyərlər bərpa olunur. | L75: Pass | M75: Avtomat | N75: A2 | O75: Bəli | P75: Xeyr | R75: BR-15 | S75: Avtomatlaşdırılıb — PASS, 16.10.2026 | T75: Pəncərədə miqdar 1 → 2 → 1: qiymət, 'Ödəmək' və ümumi məbləğ × 2; 1-də '−' deaktivdir
A76: TC_FIN_EDGE_014 | B76: SC-014 | C76: Taksit proqramları | D76: Pəncərədə edilən seçimlər 'Almaq' ilə səbətə eynilə ötürülür, 'X' ilə heç nə dəyişmir | E76: P2 — High | F76: Edge Case · Funksional | G76: Ümumi ön şərt (P0): Chrome son versiya, inkognito pəncərə, 1920×1080, AZ dili, login olmadan; səbət boşdur; iPhone 18 Pro, 256 GB, Qara PDP-si açıqdır (3 589 ₼; icra günü stokda olduğunu yoxla); 'Bütün proqramlara baxın' → 'Taksitlə alış' pəncərəsi açılıb | H76: 1. Pəncərədə miqdarı '+' ilə 2 et 2. '+1 il zədələrə qarşı qorunma' seç 3. Pəncərəni 'X' ilə bağla 4. Header-in sağındakı səbət ikonuna klik et və 'Səbətimə baxın' bas — https://ispace.az/cart açılır və məzmununa bax 5. Məhsul səhifəsinə qayıt və pəncərəni yenidən aç 6. Miqdarı 2 et və qoruma proqramını seç 7. 'Almaq' düyməsini bas 8. Header-in sağındakı səbət ikonuna klik et və 'Səbətimə baxın' bas — https://ispace.az/cart açılır 9. Səbətin məzmununu və 'Cəmi'ni pəncərədəki 'Ödəmək' ilə müqayisə et | I76: — | J76: 'X'dan sonra səbət boş qalır (pəncərədəki seçimlər gizli əlavə olunmur). 'Almaq'dan sonra səbətdə iPhone 18 Pro × 2 + qoruma proqramı var və cəm pəncərədəki 'Ödəmək' ilə eynidir. | K76: Gözlənilən nəticəyə uyğundur. | L76: Pass | M76: Manual | N76: M5 — 'Almaq' davranışı əvvəl müşahidə edilməlidir | O76: Xeyr | P76: Xeyr | R76: BR-07
A77: TC_FIN_EDGE_015 | B77: SC-014 | C77: Taksit proqramları | D77: Taksit pəncərəsi bağlandıqda və 'Geri' basıldıqda məhsul səhifəsi ilkin vəziyyətdə qalır | E77: P3 — Medium | F77: Edge Case · Funksional | G77: Ümumi ön şərt (P0): Chrome son versiya, inkognito pəncərə, 1920×1080, AZ dili, login olmadan; iPhone 18 Pro, 256 GB, Qara PDP-si açıqdır (3 589 ₼; icra günü stokda olduğunu yoxla) | H77: 1. Qiymətin altındakı 'Bütün proqramlara baxın' linkinə klik et — 'Taksitlə alış' pəncərəsi açılır 2. Brauzerin 'Geri' düyməsini bas və səhifəyə bax 3. Məhsul səhifəsinə qayıt və pəncərəni yenidən aç 4. Pəncərəni 'X' ilə bağla 5. Səhifəni aşağı sürüşdür 6. 'Səbətə' düyməsini bas | I77: — | J77: 'Geri' pəncərəni bağlayır və ya əvvəlki səhifəyə təmiz qayıdır (qaranlıq fon qalmır). Bağlandıqdan sonra səhifə sürüşür, düymələr işləyir. | K77: 'Geri' pəncərəni təmiz bağlayır, qaranlıq fon qalmır; bağlandıqdan sonra səhifə sürüşür və düymələr işləyir. | L77: Pass | M77: Avtomat | N77: A2 | O77: Xeyr | P77: Xeyr | R77: BR-17
A78: TC_FIN_POS_016 | B78: SC-014 | C78: Taksit proqramları | D78: Səbətdən açılan taksit pəncərəsində məhsul qiymətləri və 'Ödəmək' səbətdəki qiymətlər və 'Cəmi' ilə eynidir | E78: P1 — Critical | F78: Pozitiv · Funksional | G78: Ümumi ön şərt (P0); səbətdə 2 fərqli məhsul var (məs. iPhone 18 Pro 256 GB Qara + AirPods 4) | H78: 1. Header-in sağındakı səbət ikonuna klik et və 'Səbətimə baxın' bas — https://ispace.az/cart açılır 2. Hər sətrin qiymətini və 'Cəmi'ni qeyd et 3. Səbətdə 'Bütün proqramlara baxın' linkinə klik et 4. Pəncərədəki məhsul qiymətlərini və 'Ödəmək'i qeyd et 5. Qeyd etdiyin dəyərləri müqayisə et | I78: Məs. 3 589 + 2 409 = 5 998 ₼ | J78: Pəncərədəki hər məhsulun qiyməti və 'Ödəmək' səbət səhifəsindəki qiymətlər və 'Cəmi' ilə eynidir; fərq varsa, səbəbi pəncərədə yazılır. | K78: Səbətdə AirPods 4 — 246 ₼, 'Cəmi' — 3 835 ₼; həmin səbətdən açılan pəncərədə AirPods 4 — 289 ₼, 'Ödəmək' — 3 878 ₼. Eyni səbət üçün iki fərqli cəm göstərilir (fərq 43 ₼), səbəbi yazılmır (10.10 ekran görüntüləri). | L78: Fail | M78: Avtomat | N78: A1, A2 | O78: Bəli | P78: Xeyr | Q78: BUG-024 | R78: BR-07, BR-17 | S78: Manual regression (prod riski) | T78: Manual regression — prod-da avtomatlaşdırılmır: səbətdəki 'Maliyyə prosesinə başlamaq' real maliyyə müraciəti axınıdır
A79: TC_CART_POS_001 | B79: SC-015 | C79: Səbət | D79: Məhsul PDP-dən səbətə əlavə olunur | E79: P1 — Critical | F79: Pozitiv · Funksional | G79: Ümumi ön şərt (P0): Chrome son versiya, inkognito pəncərə, 1920×1080, AZ dili, login olmadan; səbət boşdur | H79: 1. Stokda olan məhsulun səhifəsini aç; adı, variantı və qiyməti qeyd et 2. 'Səbətə' düyməsini bas 3. Açılan bildirişə / mini-səbətə bax 4. Header-dəki səbət nişanındakı rəqəmi oxu 5. Header-in sağındakı səbət ikonuna klik et və 'Səbətimə baxın' bas — https://ispace.az/cart açılır 6. Sətirdəki ad, variant, qiymət, miqdar və 'Cəmi'ni yoxla | I79: Stokda olan istənilən məhsul | J79: 1. Uğurlu əlavə bildirişi/mini-səbət göstərilir. 2. Sayğac 1-dir. 3. Səbətdə 1 sətir: ad, variant, qiymət PDP ilə eyni, miqdar 1. 4. Cəm = qiymət. | K79: PDP-dən əlavə: bildiriş göstərildi, sayğac 1, səbətdə 1 sətir, ad/variant/qiymət PDP ilə eyni, cəm = qiymət. | L79: Pass | M79: Avtomat | N79: A1 — gəlir axınının əsası | O79: Bəli | P79: Bəli | R79: BR-01, BR-07 | S79: Avtomatlaşdırılıb — PASS, 16.10.2026 | T79: Test datası icra zamanı seçilir: 'Mövcuddur' filtrli siyahıdan ilk məhsul (concept: '<url> siyahısından stokda olan ilk məhsulu aç'); ad və qiymət ${dəyişən} ilə müqayisə olunur
A80: TC_CART_POS_002 | B80: SC-015 | C80: Səbət | D80: Məhsul listing kartından birbaşa səbətə əlavə olunur | E80: P2 — High | F80: Pozitiv · Funksional | G80: Ümumi ön şərt (P0): Chrome son versiya, inkognito pəncərə, 1920×1080, AZ dili, login olmadan; səbət boşdur | H80: 1. https://ispace.az/category/iphone ünvanını aç 2. 'Səbətə' düyməsi olan kartın adını və qiymətini qeyd et 3. Həmin kartda 'Səbətə' bas 4. Header-in sağındakı səbət ikonuna klik et və 'Səbətimə baxın' bas — https://ispace.az/cart açılır 5. Sətirdəki ad, qiymət və miqdarı yoxla | I80: — | J80: Səbətdə həmin məhsul, kartdakı qiymətlə, miqdar 1. | K80: Listing kartından əlavə edilən məhsul səbətdə kartdakı qiymətlə, miqdar 1 ilə göstərilir. | L80: Pass | M80: Avtomat | N80: A1 | O80: Bəli | P80: Xeyr | R80: BR-07 | S80: Avtomatlaşdırılıb — PASS, 16.10.2026 | T80: Listing kartındakı 'Səbətə' (stokdakı ilk iPhone); səbətdə ad, qiymət və miqdar 1 kartla eynidir
A81: TC_CART_POS_003 | B81: SC-015 | C81: Səbət | D81: Eyni məhsul iki dəfə əlavə edildikdə bir sətirdə miqdar 2 və sətir cəmi = qiymət × 2 olur | E81: P2 — High | F81: Pozitiv · Funksional | G81: Ümumi ön şərt (P0): Chrome son versiya, inkognito pəncərə, 1920×1080, AZ dili, login olmadan; səbət boşdur | H81: 1. Stokda olan məhsulun səhifəsini aç və qiymətini (Q) qeyd et 2. 'Səbətə' bas 3. Bildirişi bağla və 'Səbətə' düyməsini yenidən bas 4. Header-in sağındakı səbət ikonuna klik et və 'Səbətimə baxın' bas — https://ispace.az/cart açılır 5. Sətir sayını, miqdarı, sətir cəmini və header nişanını yoxla | I81: — | J81: Məhsul bir sətirdə miqdar 2 ilə göstərilir; cəm = 2 × qiymət; sayğac 2. | K81: Eyni məhsul iki dəfə əlavə edildikdə bir sətirdə miqdar 2 ilə birləşir; cəm = 2 × qiymət (BR-07 təsdiqləndi). | L81: Pass | M81: Avtomat | N81: A1, A2 | O81: Bəli | P81: Xeyr | R81: BR-07 | S81: Avtomatlaşdırılıb — PASS, 16.10.2026 | T81: Test datası icra zamanı seçilir: 'Mövcuddur' filtrli siyahıdan ilk məhsul (concept: '<url> siyahısından stokda olan ilk məhsulu aç'); ad və qiymət ${dəyişən} ilə müqayisə olunur; Java addımı: sətir cəmi = qiymət × 2
A82: TC_CART_POS_004 | B82: SC-016 | C82: Səbət | D82: İki fərqli məhsul olduqda 'Cəmi' sətir məbləğlərinin cəminə bərabərdir | E82: P1 — Critical | F82: Pozitiv · Funksional | G82: Ümumi ön şərt (P0): Chrome son versiya, inkognito pəncərə, 1920×1080, AZ dili, login olmadan; səbət boşdur | H82: 1. Məhsul A-nın səhifəsini aç, qiymətini (QA) qeyd et və 'Səbətə' bas 2. Məhsul B-nin səhifəsini aç, qiymətini (QB) qeyd et və 'Səbətə' bas 3. Header-in sağındakı səbət ikonuna klik et və 'Səbətimə baxın' bas — https://ispace.az/cart açılır 4. Sətir sayını, 'Cəmi'ni və header nişanını yoxla | I82: A, B — stokda olan iki fərqli məhsul | J82: 2 sətir; cəm = QA + QB; sayğac 2. | K82: İki fərqli məhsul: 2 sətir, cəm = QA + QB, sayğac 2. | L82: Pass | M82: Avtomat | N82: A1, A2 — pul hesablaması | O82: Bəli | P82: Xeyr | R82: BR-07 | S82: Avtomatlaşdırılıb — PASS, 16.10.2026 | T82: Data icra zamanı seçilir: stokdakı ilk iPhone + stokdakı ilk AirPods; Java: sətirlərin cəmi = Cəmi
A83: TC_CART_POS_005 | B83: SC-016 | C83: Səbət | D83: Səbətdə miqdar dəyişəndə sətir və ümumi cəm yenilənir | E83: P1 — Critical | F83: Pozitiv · Funksional | G83: Ümumi ön şərt (P0); səbətdə 1 məhsul var (qiymət Q, miqdar 1) | H83: 1. Header-in sağındakı səbət ikonuna klik et və 'Səbətimə baxın' bas — https://ispace.az/cart açılır 2. Məhsul sətrində '+' düyməsini 2 dəfə bas (miqdar 3) 3. Sətir cəmini, 'Cəmi'ni və header nişanını qeyd et 4. '−' düyməsini bas (miqdar 2) 5. Sətir cəmini, 'Cəmi'ni və header nişanını qeyd et | I83: — | J83: Miqdar 3 → cəm 3Q; miqdar 2 → cəm 2Q; header sayğacı müvafiq dəyişir; səhifəni yeniləmədən yenilənir. | K83: Miqdar 3 → cəm 3Q; miqdar 2 → cəm 2Q; sayğac yeniləmə olmadan dəyişir. | L83: Pass | M83: Avtomat | N83: A1, A2 | O83: Bəli | P83: Xeyr | R83: BR-07 | S83: Avtomatlaşdırılıb — PASS, 16.10.2026 | T83: Data: stokdakı ilk AirPods (icra zamanı seçilir); miqdar 1 → 2 → 3 → 2, hər addımda sətir cəmi, Cəmi və sayğac
A84: TC_CART_BVA_006 | B84: SC-016 | C84: Səbət | D84: Səbətdə miqdar 1-dən aşağı enmir | E84: P3 — Medium | F84: BVA · Funksional | G84: Ümumi ön şərt (P0); səbətdə 1 məhsul var (miqdar 1) | H84: 1. Header-in sağındakı səbət ikonuna klik et və 'Səbətimə baxın' bas — https://ispace.az/cart açılır 2. Miqdarı 1 olan sətirdə '−' düyməsinin vəziyyətinə bax 3. '−' düyməsini bas 4. Miqdara və göstərilən mesaja bax | I84: — | J84: Miqdar 1 qalır ('−' deaktiv) və ya məhsulun silinməsi üçün təsdiq istənilir; miqdar 0 və ya mənfi göstərilmir. | K84: Miqdar 1-də '−' ilə 0-a enmir. | L84: Pass | M84: Avtomat | N84: A2 | O84: Xeyr | P84: Xeyr | R84: BR-07 | S84: Avtomatlaşdırılıb — PASS, 16.10.2026 | T84: Data: stokdakı ilk AirPods; səbətdə miqdar 1-də '−' deaktivdir
A85: TC_CART_POS_007 | B85: SC-016 | C85: Səbət | D85: Məhsul səbətdən silinir | E85: P2 — High | F85: Pozitiv · Funksional | G85: Ümumi ön şərt (P0); səbətdə 2 fərqli məhsul var | H85: 1. Header-in sağındakı səbət ikonuna klik et və 'Səbətimə baxın' bas — https://ispace.az/cart açılır 2. Birinci məhsulun sətrindəki silmə (zibil qabı) ikonuna bas 3. Qalan sətirləri, 'Cəmi'ni və header nişanını yoxla | I85: — | J85: Sətir yox olur; cəm = qalan məhsulun qiyməti; sayğac 1. | K85: Silinən sətir yox oldu; cəm qalan məhsulun qiymətinə bərabərdir; sayğac 1. | L85: Pass | M85: Avtomat | N85: A1 | O85: Bəli | P85: Xeyr | R85: BR-07 | S85: Avtomatlaşdırılıb — PASS, 16.10.2026 | T85: Ön şərt concept: 'Səbətə iki fərqli məhsul əlavə et və səbəti aç' (stokdakı ilk iPhone + ilk AirPods)
A86: TC_CART_POS_008 | B86: SC-016 | C86: Səbət | D86: Sonuncu məhsul silinəndə boş səbət vəziyyəti göstərilir | E86: P3 — Medium | F86: Pozitiv · Funksional | G86: Ümumi ön şərt (P0); səbətdə yalnız 1 məhsul var | H86: 1. Header-in sağındakı səbət ikonuna klik et və 'Səbətimə baxın' bas — https://ispace.az/cart açılır 2. Yeganə məhsulun silmə ikonuna bas 3. Səhifədə göstərilən mesaja, linkə, header nişanına və checkout düyməsinə bax | I86: — | J86: Boş səbət mesajı və alış-verişə qayıtmaq linki göstərilir; sayğac 0 və ya gizlidir; checkout düyməsi yoxdur/deaktivdir. | K86: Sonuncu məhsul silindikdə boş səbət vəziyyəti göstərildi; checkout düyməsi yoxdur. | L86: Pass | M86: Avtomat | N86: A2 | O86: Xeyr | P86: Xeyr | R86: BR-07 | S86: Avtomatlaşdırılıb — PASS, 16.10.2026 | T86: Sonuncu məhsul silinir: 'Səbətiniz boşdur' göstərilir
A87: TC_CART_POS_009 | B87: SC-016 | C87: Səbət | D87: Qoruma proqramı ilə əlavə edilən məhsulda proqram ayrıca sətir kimi göstərilir və cəmə daxil olur | E87: P3 — Medium | F87: Pozitiv · Funksional | G87: Ümumi ön şərt (P0): Chrome son versiya, inkognito pəncərə, 1920×1080, AZ dili, login olmadan; səbət boşdur | H87: 1. iPhone məhsul səhifəsini aç 2. '+1 il zədələrə qarşı qorunma' seç və proqramın qiymətini (P) qeyd et 3. 'Səbətə' bas 4. Header-in sağındakı səbət ikonuna klik et və 'Səbətimə baxın' bas — https://ispace.az/cart açılır 5. Proqram sətrinə və 'Cəmi'yə bax | I87: Proqram qiyməti P (icra zamanı oxunur) | J87: Proqram səbətdə göstərilir; cəm = məhsulun qiyməti + P. | K87: Qoruma proqramı səbətdə seçili qalır və cəmə daxil olur. Amma 16.10 avtomat icrada: PDP-də '+1 il zədələrə qarşı qorunma' 539 ₼, səbətdə 538 ₼; Cəmi 4 127 ₼ = 3 589 + 538 (PDP-dəki qiymətlə 4 128 olmalı idi) — BUG-032. | L87: Fail | M87: Avtomat | N87: A2 — pul hesablaması | O87: Bəli | P87: Xeyr | Q87: BUG-032 | R87: BR-07 | S87: Avtomatlaşdırılıb — FAIL (BUG-032, gözlənilən), 16.10.2026 | T87: Tag: known-bug. 16.10: PDP-də proqram 539 ₼, səbətdə 538 ₼ (Cəmi 4 127 = 3 589 + 538) — BUG-032
A88: TC_CART_POS_010 | B88: SC-017 | C88: Səbət | D88: Səbət səhifə yenilənəndə və yeni tabda qorunur | E88: P2 — High | F88: Pozitiv · Funksional | G88: Ümumi ön şərt (P0); səbətdə 1 məhsul var | H88: 1. Header-in sağındakı səbət ikonuna klik et və 'Səbətimə baxın' bas — https://ispace.az/cart açılır 2. Məzmunu, miqdarı və 'Cəmi'ni qeyd et 3. F5 ilə səhifəni yenilə və müqayisə et 4. Yeni tab aç, https://ispace.az/cart ünvanını aç və müqayisə et | I88: — | J88: Hər iki halda səbətin məzmunu, miqdar və cəm dəyişmir. | K88: Səbət səhifə yenilənəndə və yeni tabda qorunur. | L88: Pass | M88: Avtomat | N88: A1 | O88: Bəli | P88: Xeyr | R88: BR-07, BR-10 | S88: Avtomatlaşdırılıb — PASS, 16.10.2026 | T88: Data: stokdakı ilk AirPods (icra zamanı seçilir); ad, miqdar və Cəmi F5-dən sonra və yeni tabda müqayisə olunur
A89: TC_CART_POS_011 | B89: SC-017 | C89: Səbət | D89: Dil dəyişəndə səbətin məzmunu qorunur | E89: P3 — Medium | F89: Pozitiv · Funksional | G89: Ümumi ön şərt (P0); səbətdə 1 məhsul var | H89: 1. Header-in sağındakı səbət ikonuna klik et və 'Səbətimə baxın' bas — https://ispace.az/cart açılır 2. Məzmunu və 'Cəmi'ni qeyd et 3. Header-dəki dil seçimindən 'English' seç 4. Səbətin məzmununu və cəmini müqayisə et 5. Dili 'Azərbaycan' et və yenidən müqayisə et | I89: — | J89: Məhsul, miqdar və cəm eynidir; yalnız mətnlər dilə görə dəyişir. | K89: EN dilinə keçdikdə və AZ-a qayıtdıqda məhsul, miqdar və cəm dəyişmir. | L89: Pass | M89: Avtomat | N89: A2 | O89: Xeyr | P89: Xeyr | R89: BR-10
A90: TC_CART_POS_012 | B90: SC-017 | C90: Səbət | D90: Səbətdən checkout-a keçiddə məhsullar, qiymətlər və cəm eynilə ötürülür | E90: P2 — High | F90: Pozitiv · Funksional | G90: Ümumi ön şərt (P0): Chrome son versiya, inkognito pəncərə, 1920×1080, AZ dili, login olmadan; səbətdə iPhone 18 Pro, 256 GB, Qara (3 589 ₼) + Qulaqlıqlar APPLE AirPods 4, Ağ (listing: 349 ₼ üstündən xətt, 289 ₼, '−15% VİSA' nişanı); TƏHLÜKƏSİZLİK: 'Mən razıyam şəxsi məlumatların işlənməsinə…' checkbox-u HEÇ VAXT işarələnmir və bütün məcburi sahələr eyni anda düzgün doldurulmur — real sifariş yaranmamalıdır | H90: 1. Header-in sağındakı səbət ikonuna klik et və 'Səbətimə baxın' bas — https://ispace.az/cart açılır 2. Hər sətrin adını, variantını, miqdarını, qiymətini və 'Cəmi'ni qeyd et 3. 'Sifarişi rəsmiləşdirmək' bas 4. Checkout xülasəsindəki sətirləri, qiymətləri, 'Cəmi • N məhsul' və 'Ödəmək'i qeyd etdiyin dəyərlərlə müqayisə et 5. HEÇ NƏ GÖNDƏRMƏ — səhifəni bağla | I90: 10.10 ekran görüntüləri: səbət — iPhone 3 589 ₼ ('ya Ayda 199 ₼-dan, 18 ay'), AirPods 4 '349 ₼' xətli → 246 ₼ ('ya Ayda 16 ₼-dan, 18 ay'), Cəmi 3 835 ₼, alt blok '215 ₼/ay üçün 18 ay' və 'Tam ödəmək 3 835 ₼'. Checkout: Cəmi • 2 məhsul 3 835 ₼, Çatdırılma Ödənişsiz, Ödəmək 3 835 ₼, ödəniş üsulu default 'Apple Pay vasitəsilə Visa ilə ödənişdə –15%'. | J90: Checkout-da eyni sətirlər (ad + variant + miqdar nişanı), eyni qiymətlər (xətli köhnə qiymət daxil), 'Cəmi • 2 məhsul' = səbətin 'Cəmi' (3 835 ₼), 'Ödəmək' = Cəmi + çatdırılma. SİFARİŞ GÖNDƏRİLMİR. | K90: Gözlənilən nəticəyə uyğundur. | L90: Pass | M90: Avtomat | N90: A1, A2 — checkout səhifəsi göndərmədən açılır və oxunur | O90: Bəli | P90: Xeyr | R90: BR-07, BR-10 | S90: Manual regression (prod riski) | T90: Manual regression — prod-da avtomatlaşdırılmır: checkout-a keçid real sifariş axınına girir
A91: TC_CART_EDGE_013 | B91: SC-018 | C91: Səbət | D91: İki tabda eyni səbət dəyişdirildikdə yeniləmədən sonra hər iki tab son vəziyyəti göstərir | E91: P2 — High | F91: Edge Case · Funksional | G91: Ümumi ön şərt (P0); səbətdə 1 məhsul var (miqdar 1) | H91: 1. Header-in sağındakı səbət ikonuna klik et və 'Səbətimə baxın' bas — https://ispace.az/cart açılır (Tab A) 2. Səbəti yeni tabda da aç (Tab B) 3. Tab A-da miqdarı '+' ilə 3 et 4. Tab B-də (yeniləmədən) '+' bas 5. Hər iki tabı F5 ilə yenilə 6. Hər iki tabda miqdarı, 'Cəmi'ni və header nişanını müqayisə et | I91: — | J91: Yeniləmədən sonra hər iki tab eyni miqdarı və cəmi göstərir; miqdar məntiqlidir (4 və ya Tab B-nin əməliyyatı rədd edilib bildirilir); header sayğacı sətirlərlə uyğundur. | K91: Tab B-də miqdar 2 edildi; hər iki tab yeniləndikdən sonra 2 göstərir — son yazılan dəyər qəbul olunur, vəziyyət iki tabda ardıcıldır. | L91: Pass | M91: Manual | N91: M3 — eyni anda dəyişiklik | O91: Xeyr | P91: Xeyr | R91: BR-07, BR-15
A92: TC_CART_EDGE_014 | B92: SC-018 | C92: Səbət | D92: Miqdar düyməsinə tez-tez klikdə sayğac, sətir və cəm uyğun qalır | E92: P3 — Medium | F92: Edge Case · Funksional | G92: Ümumi ön şərt (P0); səbətdə 1 məhsul var (qiymət Q) | H92: 1. Header-in sağındakı səbət ikonuna klik et və 'Səbətimə baxın' bas — https://ispace.az/cart açılır 2. Məhsul sətrində '+' düyməsinə 1 saniyə ərzində 5 dəfə klik et 3. Miqdarı, sətir cəmini və header nişanını qeyd et 4. F5 ilə səhifəni yenilə 5. Miqdarı, sətir cəmini və header nişanını yenidən qeyd et və müqayisə et | I92: — | J92: Yeniləmədən əvvəl və sonra miqdar eynidir; cəm = miqdar × Q; header sayğacı = miqdar. | K92: Tez kliklərdən sonra yeniləmədən əvvəl və sonra miqdar, cəm və sayğac uyğundur. Qeyd: '+' kliklərinə gecikmə ilə reaksiya verir — OBS-06. | L92: Pass | M92: Manual | N92: M3 | O92: Xeyr | P92: Xeyr | R92: BR-07, BR-15
A93: TC_CART_EDGE_015 | B93: SC-018 | C93: Səbət | D93: Silinmiş məhsul brauzerin 'Geri' düyməsindən sonra qayıtmır | E93: P3 — Medium | F93: Edge Case · Funksional | G93: Ümumi ön şərt (P0); səbətdə 2 fərqli məhsul var | H93: 1. Header-in sağındakı səbət ikonuna klik et və 'Səbətimə baxın' bas — https://ispace.az/cart açılır 2. Bir məhsulun silmə ikonuna bas 3. Qalan məhsulun adına klik et — məhsul səhifəsi açılır 4. Brauzerin 'Geri' düyməsini bas 5. Silinmiş məhsulun göründüyünü yoxla 6. F5 ilə yenilə və yenidən yoxla | I93: — | J93: Silinmiş məhsul nə keşlənmiş görünüşdə, nə yeniləmədən sonra görünür; sayğac 1. | K93: Silinmiş məhsul 'Geri' və yeniləmədən sonra görünmür; sayğac 1. | L93: Pass | M93: Avtomat | N93: A2 | O93: Xeyr | P93: Xeyr | R93: BR-07, BR-15
A94: TC_CART_EDGE_016 | B94: SC-018 | C94: Səbət | D94: Eyni modelin fərqli variantları ayrı sətirlərdə saxlanılır | E94: P3 — Medium | F94: Edge Case · Funksional | G94: Ümumi ön şərt (P0): Chrome son versiya, inkognito pəncərə, 1920×1080, AZ dili, login olmadan; səbət boşdur | H94: 1. https://ispace.az/product/iphone-17-256-gb-lavender-mg6m4af-a ünvanını aç və 'Səbətə' bas 2. 'Rəng' seçimində 'Black' bas və 'Səbətə' bas 3. 'Yaddaş' seçimində '512 GB' bas və 'Səbətə' bas 4. Header-in sağındakı səbət ikonuna klik et və 'Səbətimə baxın' bas — https://ispace.az/cart açılır 5. Sətir sayını, hər sətrin variantını, qiymətini və 'Cəmi'ni yoxla | I94: 3 fərqli məhsul kodu | J94: 3 ayrı sətir, hər birində öz məhsul kodu/rəng/yaddaş və qiyməti; cəm 3 qiymətin cəmidir. | K94: Üç variant ayrı sətirlərdə öz məhsul kodu, rəng/yaddaş və qiyməti ilə göstərilir; cəm düzgündür. | L94: Pass | M94: Avtomat | N94: A2 | O94: Xeyr | P94: Xeyr | R94: BR-07 | S94: Avtomatlaşdırılıb — PASS, 16.10.2026 | T94: Stokdakı ilk 3 iPhone: 3 sətir, sayğac 3, sətirlərin cəmi = Cəmi
A95: TC_CART_POS_017 | B95: SC-019 | C95: Səbət | D95: Səbət sətrində şəkil, ad, variant, qiymət və miqdar göstərilir, klik eyni variantın PDP-sini açır | E95: P3 — Medium | F95: Pozitiv · Funksional | G95: Ümumi ön şərt (P0): Chrome son versiya, inkognito pəncərə, 1920×1080, AZ dili, login olmadan; səbət boşdur (yeni inkognito pəncərə) | H95: 1. iPhone 17, 512 GB, Sage məhsul səhifəsini aç və məhsul kodunu qeyd et 2. 'Səbətə' bas 3. Header-in sağındakı səbət ikonuna klik et və 'Səbətimə baxın' bas — https://ispace.az/cart açılır 4. Sətirdə şəkil, ad, yaddaş, rəng, vahid qiymət, miqdar və sətir cəmini yoxla 5. Sətirdə məhsulun adına klik et 6. Açılan səhifənin URL-ini və məhsul kodunu qeyd etdiyinlə müqayisə et | I95: Variant seçimi məqsədli olaraq default deyil (512 GB, Sage) | J95: Sətirdə şəkil, ad, '512 GB', 'Sage', vahid qiymət, miqdar və sətir cəmi göstərilir. Klik eyni variantın PDP-sini açır (URL və məhsul kodu eynidir), default variant (256 GB) açılmır. | K95: Gözlənilən nəticəyə uyğundur. | L95: Pass | M95: Avtomat | N95: A2 | O95: Xeyr | P95: Xeyr | R95: BR-06
A96: TC_CART_EDGE_018 | B96: SC-019 | C96: Səbət | D96: Endirimli məhsul səbətdə endirimli qiymətlə hesablanır | E96: P2 — High | F96: Edge Case · Funksional | G96: Ümumi ön şərt (P0): Chrome son versiya, inkognito pəncərə, 1920×1080, AZ dili, login olmadan; səbət boşdur (yeni inkognito pəncərə) | H96: 1. https://ispace.az/category/extra-deals ünvanını aç 2. Endirimli məhsulun köhnə (K) və yeni (Y) qiymətini qeyd et 3. 'Səbətə' bas 4. Header-in sağındakı səbət ikonuna klik et və 'Səbətimə baxın' bas — https://ispace.az/cart açılır 5. Sətirdəki qiyməti və 'Cəmi'ni yoxla 6. Miqdarı '+' ilə 2 et 7. Sətir cəmini, endirim sətrini (varsa) və 'Cəmi'ni yoxla | I96: K və Y icra zamanı oxunur | J96: Sətirdə yeni qiymət (Y) və üstündən xətt çəkilmiş köhnə qiymət (K) göstərilir; sətir cəmi və 'Cəmi' Y əsasındadır (2 ədəddə 2 × Y). | K96: Gözlənilən nəticəyə uyğundur. | L96: Pass | M96: Manual | N96: M3 — endirimlər kampaniyaya bağlıdır | O96: Xeyr | P96: Xeyr | R96: BR-07, BR-19
A97: TC_CART_EDGE_019 | B97: SC-019 | C97: Səbət | D97: Məhsul silinəndə ona bağlı qoruma proqramı sətri də silinir | E97: P2 — High | F97: Edge Case · Funksional | G97: Ümumi ön şərt (P0): Chrome son versiya, inkognito pəncərə, 1920×1080, AZ dili, login olmadan; səbət boşdur (yeni inkognito pəncərə) | H97: 1. iPhone məhsul səhifəsində '+1 il zədələrə qarşı qorunma' seç və 'Səbətə' bas 2. Header-in sağındakı səbət ikonuna klik et və 'Səbətimə baxın' bas — https://ispace.az/cart açılır 3. Məhsul və proqram sətirlərinə bax 4. Məhsul sətrinin silmə ikonuna bas 5. F5 ilə yenilə 6. Proqram sətrinin qalıb-qalmadığını və 'Cəmi'ni yoxla | I97: — | J97: Məhsul silindikdə proqram da silinir (və ya silinməsi təklif olunur); cihazsız 'yetim' qoruma proqramı səbətdə qalmır və ödənilə bilmir; cəm 0 ₼, boş səbət göstərilir. | K97: Gözlənilən nəticəyə uyğundur. | L97: Pass | M97: Avtomat | N97: A2 — deterministik vəziyyət keçidi | O97: Bəli | P97: Xeyr | R97: BR-07, BR-19 | S97: Avtomatlaşdırılıb — PASS, 16.10.2026 | T97: Proqramlı məhsul silinir; F5-dən sonra səbət boşdur, proqram sətri və Cəmi qalmır
A98: TC_CART_EDGE_020 | B98: SC-019 | C98: Səbət | D98: Qoruma proqramlı məhsulun miqdarı artanda proqram miqdarı da uyğunlaşır | E98: P3 — Medium | F98: Edge Case · Funksional | G98: Ümumi ön şərt (P0); səbətdə qoruma proqramı ilə əlavə edilmiş 1 iPhone var (proqram qiyməti P) | H98: 1. Header-in sağındakı səbət ikonuna klik et və 'Səbətimə baxın' bas — https://ispace.az/cart açılır 2. Proqramlı iPhone sətrində '+' bas (miqdar 2) 3. Proqram sətrinin miqdarını, qiymətini və 'Cəmi'ni oxu 4. '−' bas (miqdar 1) 5. Dəyərlərə yenidən bax | I98: P icra zamanı oxunur (iPhone 18 Pro: 538 ₼) | J98: Qayda ardıcıldır və görünür: ya proqram da 2 ədəd olur (2·P), ya da '1 proqram 1 cihaz üçün' yazılır. 2 cihaz + 1 proqram izahsız qalarsa — müştəri hər iki cihazın qorunduğunu düşünür. | K98: Qoruma proqramlı iPhone-un miqdarı 2 edildikdə proqram da 2 cihaz üçün tətbiq olunur — qayda ardıcıl və görünəndir. | L98: Pass | M98: Manual | N98: M5 — biznes qaydası məlum deyil | O98: Xeyr | P98: Xeyr | R98: BR-07, BR-19
A99: TC_CART_EDGE_021 | B99: SC-019 | C99: Səbət | D99: Mini-səbətdə eyni modelin fərqli variantları ayırd edilir | E99: P3 — Medium | F99: Edge Case · UI | G99: Ümumi ön şərt (P0): Chrome son versiya, inkognito pəncərə, 1920×1080, AZ dili, login olmadan; səbət boşdur | H99: 1. iPhone 18 Pro, 256 GB, Qara məhsul səhifəsində 'Səbətə' bas 2. iPhone 18 Pro, 512 GB, Gümüş məhsul səhifəsində 'Səbətə' bas 3. Açılan mini-səbətdə ('Əşyalar səbətə əlavə edildi') hər sətrin adını oxu 4. Sətirlərdə yaddaş və rəngin göstərildiyini yoxla | I99: 10.10 ekran görüntüsü: mini-səbətdə yalnız 'iPhone 18 Pro' yazılır (yaddaş və rəng yoxdur) | J99: Mini-səbətdə hər sətrin variantı (yaddaş, rəng) görünür; istifadəçi iki sətri qiymətdən başqa da fərqləndirə bilir. | K99: Mini-səbətdə hər sətir yaddaş və rəngi ilə göstərilir, eyni modelin iki variantı ayırd edilir (10.10 təkrar yoxlama). | L99: Pass | M99: Manual | N99: M1 | O99: Xeyr | P99: Xeyr | R99: BR-07, BR-19
A100: TC_CART_EDGE_022 | B100: SC-019 | C100: Səbət | D100: Səbətdəki aylıq ödəniş mətnləri və 'X ₼/ay üçün 18 ay' bloku eyni bazaya əsaslanır | E100: P2 — High | F100: Edge Case · Funksional | G100: Ümumi ön şərt (P0): Chrome son versiya, inkognito pəncərə, 1920×1080, AZ dili, login olmadan; səbətdə iPhone 18 Pro, 256 GB, Qara (3 589 ₼) + Qulaqlıqlar APPLE AirPods 4, Ağ (listing: 349 ₼ üstündən xətt, 289 ₼, '−15% VİSA' nişanı) | H100: 1. Header-in sağındakı səbət ikonuna klik et və 'Səbətimə baxın' bas — https://ispace.az/cart açılır 2. Hər sətirdəki 'ya Ayda X ₼-dan, 18 ay' məbləğini qeyd et 3. Səbətin altındakı '… ₼/ay üçün 18 ay' və 'Tam ödəmək … ₼' dəyərlərini qeyd et 4. Sətir aylıqlarının cəmini, 'Tam ödəmək' / 18-i və endirimsiz cəm / 18-i hesabla 5. Fərqin səbətdə izah olunub-olunmadığını axtar | I100: 10.10: 199 + 16 = 215 ✔; 3 878 (endirimsiz) / 18 = 215,4 → 215; Tam ödəmək 3 835 / 18 = 213,1. AirPods sətrində qiymət 246 ₼, aylıq 16 ₼ isə 289 ₼-a görədir (246 / 18 = 13,7) | J100: Hər qiymətin yanında göstərilən aylıq ödəniş həmin qiymətdən hesablanır və ya fərqli bazanın səbəbi yazılır ('taksitdə Visa endirimi tətbiq olunmur'). 'Tam ödəmək 3 835 ₼' ilə '215 ₼ × 18 = 3 870 ₼' arasındakı fərq istifadəçiyə izah edilir. | K100: Səbətdə qiymətlər Visa endirimli göstərilir ('Cəmi' 3 835 ₼, AirPods 246 ₼), '215 ₼ × 18' isə 3 870 ₼ edir; eyni səbətdən açılan taksit pəncərəsində 'Ödəmək' 3 878 ₼. Taksitdə Visa endiriminin tətbiq olunmadığı səbətdə yazılmır — fərq istifadəçiyə izah edilmir (10.10 ekran görüntüləri). | L100: Fail | M100: Manual | N100: M5 — hansı qiymətin hansı ödəniş üçün keçərli olduğu biznes qaydasıdır | O100: Xeyr | P100: Xeyr | Q100: BUG-024 | R100: BR-07, BR-19
A101: TC_CART_POS_023 | B101: SC-019 | C101: Səbət | D101: Səbətdə qoruma proqramı seçimi Cəmi və taksit blokunu yeniləyir | E101: P2 — High | F101: Pozitiv · Funksional | G101: Ümumi ön şərt (P0): Chrome son versiya, inkognito pəncərə, 1920×1080, AZ dili, login olmadan; səbətdə iPhone 18 Pro, 256 GB, Qara (3 589 ₼) + Qulaqlıqlar APPLE AirPods 4, Ağ (listing: 349 ₼ üstündən xətt, 289 ₼, '−15% VİSA' nişanı) | H101: 1. Header-in sağındakı səbət ikonuna klik et və 'Səbətimə baxın' bas — https://ispace.az/cart açılır 2. iPhone sətrində 'Məhsulunuzu qoruyun' bölməsində '+1 il zədələrə qarşı qorunma' seç 3. 'Cəmi', 'Tam ödəmək' və '… ₼/ay üçün 18 ay' dəyərlərini qeyd et 4. 'Əlavə proqram olmadan' seç 5. Dəyərləri yenidən qeyd et və müqayisə et | I101: 3 835 + 538 = 4 373 ₼; taksit (3 878 + 538) / 18 = 245,3 ≈ 245 ₼ | J101: Seçimdən sonra Cəmi və Tam ödəmək = 4 373 ₼, taksit ≈ 245 ₼/ay; ləğvdən sonra 3 835 ₼ və 215 ₼ bərpa olunur; header nişanı və sətir sayı məntiqli dəyişir. | K101: Gözlənilən nəticəyə uyğundur. | L101: Pass | M101: Avtomat | N101: A1, A2 | O101: Bəli | P101: Xeyr | R101: BR-07 | S101: Avtomatlaşdırılıb — PASS, 16.10.2026 | T101: Ön şərt concept: stokdakı ilk iPhone + ilk AirPods. Proqram seçiləndə Cəmi və 'Tam ödəmək' = əvvəlki + proqram, taksit mətni dəyişir; ləğv bərpa edir
A102: TC_CART_EDGE_024 | B102: SC-019 | C102: Səbət | D102: Səbətdəki çatdırılma/mağaza seçimi checkout-a ötürülür | E102: P3 — Medium | F102: Edge Case · Funksional | G102: Ümumi ön şərt (P0): Chrome son versiya, inkognito pəncərə, 1920×1080, AZ dili, login olmadan; səbətdə iPhone 18 Pro, 256 GB, Qara (3 589 ₼) + Qulaqlıqlar APPLE AirPods 4, Ağ (listing: 349 ₼ üstündən xətt, 289 ₼, '−15% VİSA' nişanı); TƏHLÜKƏSİZLİK: 'Mən razıyam şəxsi məlumatların işlənməsinə…' checkbox-u HEÇ VAXT işarələnmir və bütün məcburi sahələr eyni anda düzgün doldurulmur — real sifariş yaranmamalıdır | H102: 1. Header-in sağındakı səbət ikonuna klik et və 'Səbətimə baxın' bas — https://ispace.az/cart açılır 2. iPhone sətrinin altındakı 'Özün götürmə' blokunda mağazanı qeyd et 3. 'Çatdırılma' seçiminə klik et və nəticəni qeyd et 4. 'Sifarişi rəsmiləşdirmək' bas 5. Checkout-un 'Çatdırılma' bölməsində seçili növü və mağazanı oxu 6. HEÇ NƏ GÖNDƏRMƏ — səhifəni bağla | I102: 10.10: səbətdə 'Özün götürmə — Gənclik Mall', checkout-da default 'Kuryer ilə çatdırılma' | J102: Səbətdə edilən seçim checkout-da qorunur (və ya səbətdəki blok yalnız məlumat xarakterlidirsə, bu aydın görünür). Səbətdə 'Özün götürmə' seçib checkout-da default 'Kuryer' görmək — ziddiyyət. | K102: Gözlənilən nəticəyə uyğundur. | L102: Pass | M102: Manual | N102: M5 | O102: Xeyr | P102: Xeyr | R102: BR-07, BR-19
...

Sheet RTM
A1: Requirement Traceability Matrix (RTM) — iSpace.az
E3: Eyni məhsulun qiyməti listing, PDP və səbətdə eynidir | F3: Filtr yanındakı sayğac (N) filtr tətbiq edildikdən sonrakı n | G3: 'Aşağı qiymət' artan, 'Yüksək qiymət' azalan sıra verir — bü | H3: Qiymət aralığı filtri yalnız [min; max] daxilində (sərhədlər | I3: Filtrdə göstərilən 'Ən yüksək qiymət' kateqoriyadakı ən baha | J3: Variant (yaddaş/rəng) dəyişəndə məhsul kodu, qiymət və URL müvafiq v | K3: Səbət cəmi = Σ (qiymət × miqdar) + seçilmiş əlavə proqramlar | L3: 0% taksitdə aylıq məbləğ = qiymət / ay sayı, ən yaxın tam ma | M3: 24 aylıq taksitdə aylıq məbləğ qiymət/24-dən ~12–13% yüksəkd | N3: Dil keçidi istifadəçini eyni səhifənin digər dil versiyasına | O3: Məhsul kartında vəziyyətə görə 4 düymədən biri göstərilir: ' | P3: Bir-birini istisna edən filtr qrupunda (stok, yaddaş, SIM, e | Q3: Bakı: 16:00-dək rəsmiləşdirilən sifariş eyni gün; haqq 4–50 | R3: Səhifədə 21 məhsul göstərilir; səhifə sayı = ⌈N/21⌉ | S3: Miqdar mövcud stok sayından artıq seçilə bilmir; həddə çatan | T3: Axtarış sorğusu ən az 3 simvol olmalıdır; daha qısa sorğuda | U3: 0% hissə-hissə ödəniş: 2–24 ay (/credit) və ya 3–24 ay (/pay | V3: Filtrlər 'Tətbiq et' ilə tətbiq olunur. Hər filtr dəyəri məh | W3: −15% VİSA' endirimi yalnız 'Apple Pay vasitəsilə Visa ilə ö | X3: Checkout formasında telefon və e-poçt formatı yoxlanılır; sə
A4: TC ID | B4: Başlıq | C4: Ssenari | D4: Status | E4: BR-01 | F4: BR-02 | G4: BR-03 | H4: BR-04 | I4: BR-05 | J4: BR-06 | K4: BR-07 | L4: BR-08 | M4: BR-09 | N4: BR-10 | O4: BR-11 | P4: BR-12 | Q4: BR-13 | R4: BR-14 | S4: BR-15 | T4: BR-16 | U4: BR-17 | V4: BR-18 | W4: BR-19 | X4: BR-20
A5: ='Web Test Cases'!A5 -> TC_PLP_POS_001 | B5: ='Web Test Cases'!D5 -> iPhone kateqoriyası açıldıqda başlıq, breadcrumb, məhsul sayı və məhsul kartları göstərilir | C5: ='Web Test Cases'!B5 -> SC-001 | D5: ='Web Test Cases'!L5 -> Pass | E5: ✓ | O5: ✓
A6: ='Web Test Cases'!A6 -> TC_PLP_POS_002 | B6: ='Web Test Cases'!D6 -> Hər məhsul kartında ad, qiymət, aylıq ödəniş və düymə göstərilir | C6: ='Web Test Cases'!B6 -> SC-001 | D6: ='Web Test Cases'!L6 -> Pass | E6: ✓ | O6: ✓
A7: ='Web Test Cases'!A7 -> TC_PLP_POS_003 | B7: ='Web Test Cases'!D7 -> Kartdakı qiymət məhsul səhifəsindəki qiymətlə eynidir | C7: ='Web Test Cases'!B7 -> SC-001 | D7: ='Web Test Cases'!L7 -> Pass | E7: ✓
A8: ='Web Test Cases'!A8 -> TC_PLP_POS_004 | B8: ='Web Test Cases'!D8 -> Stokda olan məhsulun kartında 'Səbətə', olmayanda 'Ön sifariş' / 'Mənə xəbər ver' düyməsi göstərilir | C8: ='Web Test Cases'!B8 -> SC-001 | D8: ='Web Test Cases'!L8 -> Pass | O8: ✓
A9: ='Web Test Cases'!A9 -> TC_PLP_POS_005 | B9: ='Web Test Cases'!D9 -> 'Mövcuddur' filtri: nəticə sayı sayğaca bərabərdir | C9: ='Web Test Cases'!B9 -> SC-002 | D9: ='Web Test Cases'!L9 -> Pass | F9: ✓
A10: ='Web Test Cases'!A10 -> TC_PLP_POS_006 | B10: ='Web Test Cases'!D10 -> Bir filtr qrupunda sayğacların cəmi ümumi məhsul sayına bərabərdir | C10: ='Web Test Cases'!B10 -> SC-002 | D10: ='Web Test Cases'!L10 -> Pass | P10: ✓
A11: ='Web Test Cases'!A11 -> TC_PLP_POS_007 | B11: ='Web Test Cases'!D11 -> Yaddaş filtri yalnız seçilmiş yaddaşlı məhsulları göstərir | C11: ='Web Test Cases'!B11 -> SC-002 | D11: ='Web Test Cases'!L11 -> Pass | F11: ✓
A12: ='Web Test Cases'!A12 -> TC_PLP_POS_008 | B12: ='Web Test Cases'!D12 -> Rəng filtri yalnız seçilmiş rəngli məhsulları göstərir | C12: ='Web Test Cases'!B12 -> SC-002 | D12: ='Web Test Cases'!L12 -> Pass | F12: ✓
A13: ='Web Test Cases'!A13 -> TC_PLP_POS_009 | B13: ='Web Test Cases'!D13 -> '256 GB' və 'Mövcuddur' birlikdə seçildikdə yalnız hər iki şərtə uyğun məhsullar göstərilir (VƏ məntiqi) | C13: ='Web Test Cases'!B13 -> SC-002 | D13: ='Web Test Cases'!L13 -> Pass | F13: ✓ | P13: ✓
A14: ='Web Test Cases'!A14 -> TC_PLP_POS_010 | B14: ='Web Test Cases'!D14 -> '256 GB' və '512 GB' birlikdə seçildikdə nəticə sayı iki sayğacın cəminə bərabərdir (VƏ YA məntiqi) | C14: ='Web Test Cases'!B14 -> SC-002 | D14: ='Web Test Cases'!L14 -> Pass | P14: ✓
A15: ='Web Test Cases'!A15 -> TC_PLP_POS_011 | B15: ='Web Test Cases'!D15 -> Filtrlər təmizlənəndə ilkin siyahı bərpa olunur | C15: ='Web Test Cases'!B15 -> SC-002 | D15: ='Web Test Cases'!L15 -> Pass | F15: ✓ | P15: ✓
A16: ='Web Test Cases'!A16 -> TC_PLP_POS_012 | B16: ='Web Test Cases'!D16 -> Filtrli səhifə yeniləndikdə və link yeni tabda açıldıqda filtr qorunur | C16: ='Web Test Cases'!B16 -> SC-002 | D16: ='Web Test Cases'!L16 -> Pass | F16: ✓ | P16: ✓
A17: ='Web Test Cases'!A17 -> TC_PLP_NEG_013 | B17: ='Web Test Cases'!D17 -> Nəticəsiz filtr kombinasiyasında boş vəziyyət mesajı göstərilir | C17: ='Web Test Cases'!B17 -> SC-002 | D17: ='Web Test Cases'!L17 -> Pass | F17: ✓ | P17: ✓
A18: ='Web Test Cases'!A18 -> TC_PLP_POS_014 | B18: ='Web Test Cases'!D18 -> Qiymət aralığı daxilində olan məhsullar göstərilir | C18: ='Web Test Cases'!B18 -> SC-003 | D18: ='Web Test Cases'!L18 -> Pass | H18: ✓
A19: ='Web Test Cases'!A19 -> TC_PLP_BVA_015 | B19: ='Web Test Cases'!D19 -> Qiymət filtrinin sərhədləri daxildir (min = max = məhsulun qiyməti) | C19: ='Web Test Cases'!B19 -> SC-003 | D19: ='Web Test Cases'!L19 -> Pass | H19: ✓
A20: ='Web Test Cases'!A20 -> TC_PLP_BVA_016 | B20: ='Web Test Cases'!D20 -> Sərhəddən bir vahid kənar dəyər məhsulu xaric edir | C20: ='Web Test Cases'!B20 -> SC-003 | D20: ='Web Test Cases'!L20 -> Pass | H20: ✓
A21: ='Web Test Cases'!A21 -> TC_PLP_NEG_017 | B21: ='Web Test Cases'!D21 -> Minimum maksimumdan böyük olduqda sistem istifadəçini məlumatlandırır | C21: ='Web Test Cases'!B21 -> SC-003 | D21: ='Web Test Cases'!L21 -> Pass | H21: ✓
A22: ='Web Test Cases'!A22 -> TC_PLP_NEG_018 | B22: ='Web Test Cases'!D22 -> Qiymət sahəsi qeyri-rəqəm və mənfi dəyərləri qəbul etmir | C22: ='Web Test Cases'!B22 -> SC-003 | D22: ='Web Test Cases'!L22 -> Pass | H22: ✓
A23: ='Web Test Cases'!A23 -> TC_PLP_POS_019 | B23: ='Web Test Cases'!D23 -> 'Aşağı qiymət' sıralaması qiymətləri artan sırada göstərir | C23: ='Web Test Cases'!B23 -> SC-004 | D23: ='Web Test Cases'!L23 -> Pass | G23: ✓
A24: ='Web Test Cases'!A24 -> TC_PLP_POS_020 | B24: ='Web Test Cases'!D24 -> 'Yüksək qiymət' sıralaması azalan sıradadır və ilk məhsul ən bahalısıdır | C24: ='Web Test Cases'!B24 -> SC-004 | D24: ='Web Test Cases'!L24 -> Pass | G24: ✓ | I24: ✓
A25: ='Web Test Cases'!A25 -> TC_PLP_POS_021 | B25: ='Web Test Cases'!D25 -> Sıralama növbəti səhifədə də davam edir | C25: ='Web Test Cases'!B25 -> SC-004 | D25: ='Web Test Cases'!L25 -> Pass | G25: ✓
A26: ='Web Test Cases'!A26 -> TC_PLP_POS_022 | B26: ='Web Test Cases'!D26 -> Səhifə ölçüsü və səhifə sayı ümumi məhsul sayına uyğundur | C26: ='Web Test Cases'!B26 -> SC-004 | D26: ='Web Test Cases'!L26 -> Pass | R26: ✓
A27: ='Web Test Cases'!A27 -> TC_PLP_POS_023 | B27: ='Web Test Cases'!D27 -> Səhifələr arasında məhsul təkrarlanmır və itmir | C27: ='Web Test Cases'!B27 -> SC-004 | D27: ='Web Test Cases'!L27 -> Pass | G27: ✓ | I27: ✓ | R27: ✓
A28: ='Web Test Cases'!A28 -> TC_FLT_POS_001 | B28: ='Web Test Cases'!D28 -> 'iPhone 18 Pro & Pro Max' çipi seçildikdə nəticə sayı həmin seriyaların sayğaclarının cəminə bərabərdir | C28: ='Web Test Cases'!B28 -> SC-005 | D28: ='Web Test Cases'!L28 -> Pass | P28: ✓
A29: ='Web Test Cases'!A29 -> TC_FLT_POS_002 | B29: ='Web Test Cases'!D29 -> Seriya filtri yalnız dəqiq seriyanı qaytarır (alt-seriyaları qarışdırmır) | C29: ='Web Test Cases'!B29 -> SC-005 | D29: ='Web Test Cases'!L29 -> Pass | F29: ✓
A30: ='Web Test Cases'!A30 -> TC_FLT_POS_003 | B30: ='Web Test Cases'!D30 -> Bütün Seriya sayğaclarının cəmi ümumi məhsul sayına bərabərdir ('Daha çox göstər' açıq) | C30: ='Web Test Cases'!B30 -> SC-005 | D30: ='Web Test Cases'!L30 -> Pass | P30: ✓
A31: ='Web Test Cases'!A31 -> TC_FLT_POS_004 | B31: ='Web Test Cases'!D31 -> Ekran diaqonalı filtri: say və PDP göstəricisi uyğundur | C31: ='Web Test Cases'!B31 -> SC-006 | D31: ='Web Test Cases'!L31 -> Pass | P31: ✓
A32: ='Web Test Cases'!A32 -> TC_FLT_POS_005 | B32: ='Web Test Cases'!D32 -> '48 MP' əsas kamera filtri seçildikdə yalnız tək arxa kameralı modellər göstərilir (12 məhsul) | C32: ='Web Test Cases'!B32 -> SC-006 | D32: ='Web Test Cases'!L32 -> Pass | P32: ✓
A33: ='Web Test Cases'!A33 -> TC_FLT_EDGE_006 | B33: ='Web Test Cases'!D33 -> 'Video izləmə müddəti' filtrinin bütün dəyərləri azərbaycanca və eyni vahidlə ('saat') yazılır | C33: ='Web Test Cases'!B33 -> SC-006 | D33: ='Web Test Cases'!L33 -> Fail | V33: ✓
A34: ='Web Test Cases'!A34 -> TC_FLT_EDGE_007 | B34: ='Web Test Cases'!D34 -> '36 Hours' filtri ilə tapılan modellərin məhsul səhifəsindəki video izləmə müddəti 36 saatdır | C34: ='Web Test Cases'!B34 -> SC-006 | D34: ='Web Test Cases'!L34 -> Fail | V34: ✓
A35: ='Web Test Cases'!A35 -> TC_FLT_POS_008 | B35: ='Web Test Cases'!D35 -> SIM kart növü filtri bir-birini istisna edir | C35: ='Web Test Cases'!B35 -> SC-006 | D35: ='Web Test Cases'!L35 -> Pass | P35: ✓
A36: ='Web Test Cases'!A36 -> TC_FLT_EDGE_009 | B36: ='Web Test Cases'!D36 -> Hər məhsul ən azı bir Rəng dəyərinə bağlıdır (rəng sayğacları cəmi = 213) | C36: ='Web Test Cases'!B36 -> SC-007 | D36: ='Web Test Cases'!L36 -> Pass | P36: ✓
A37: ='Web Test Cases'!A37 -> TC_FLT_EDGE_010 | B37: ='Web Test Cases'!D37 -> Hər modelin Apple rəng adı vizual rənginə uyğun Rəng filtri dəyərində tapılır | C37: ='Web Test Cases'!B37 -> SC-007 | D37: ='Web Test Cases'!L37 -> Pass | V37: ✓
A38: ='Web Test Cases'!A38 -> TC_FLT_EDGE_011 | B38: ='Web Test Cases'!D38 -> 'Əlavə xüsusiyyətlər' filtri bütün uyğun məhsulları qaytarır (data tamlığı) | C38: ='Web Test Cases'!B38 -> SC-007 | D38: ='Web Test Cases'!L38 -> Pass | V38: ✓
A39: ='Web Test Cases'!A39 -> TC_FLT_UI_012 | B39: ='Web Test Cases'!D39 -> 'Əlavə xüsusiyyətlər' dəyərləri azərbaycancadır | C39: ='Web Test Cases'!B39 -> SC-007 | D39: ='Web Test Cases'!L39 -> Fail | V39: ✓
A40: ='Web Test Cases'!A40 -> TC_FLT_POS_013 | B40: ='Web Test Cases'!D40 -> Filtr seçildikdən sonra digər qrupların sayğacları nəticəyə görə yenilənir | C40: ='Web Test Cases'!B40 -> SC-008 | D40: ='Web Test Cases'!L40 -> Pass | P40: ✓
A41: ='Web Test Cases'!A41 -> TC_FLT_POS_014 | B41: ='Web Test Cases'!D41 -> 'Tətbiq et' basılmadan seçim nəticəni dəyişmir və itmir | C41: ='Web Test Cases'!B41 -> SC-008 | D41: ='Web Test Cases'!L41 -> Pass | F41: ✓ | P41: ✓
A42: ='Web Test Cases'!A42 -> TC_FLT_POS_015 | B42: ='Web Test Cases'!D42 -> '+ Daha çox göstər' gizli dəyəri seçdikdən sonra aktiv filtr görünür qalır | C42: ='Web Test Cases'!B42 -> SC-008 | D42: ='Web Test Cases'!L42 -> Pass | F42: ✓ | P42: ✓
A43: ='Web Test Cases'!A43 -> TC_FLT_POS_016 | B43: ='Web Test Cases'!D43 -> Aktiv filtrlər görünür və tək-tək silinə bilir | C43: ='Web Test Cases'!B43 -> SC-008 | D43: ='Web Test Cases'!L43 -> Pass | F43: ✓ | P43: ✓
A44: ='Web Test Cases'!A44 -> TC_FLT_POS_017 | B44: ='Web Test Cases'!D44 -> Üç fərqli qrupdan filtr kombinasiyası dəqiq nəticə verir | C44: ='Web Test Cases'!B44 -> SC-009 | D44: ='Web Test Cases'!L44 -> Pass | V44: ✓
A45: ='Web Test Cases'!A45 -> TC_FLT_EDGE_018 | B45: ='Web Test Cases'!D45 -> Filtr və 'Aşağı qiymət' sıralaması ilə səhifələr arasında keçdikdə filtr və sıra bütün səhifələrdə saxlanır | C45: ='Web Test Cases'!B45 -> SC-009 | D45: ='Web Test Cases'!L45 -> Pass | G45: ✓ | R45: ✓
A46: ='Web Test Cases'!A46 -> TC_FLT_EDGE_019 | B46: ='Web Test Cases'!D46 -> Brauzerin 'Geri' düyməsi əvvəlki filtr vəziyyətini bərpa edir | C46: ='Web Test Cases'!B46 -> SC-009 | D46: ='Web Test Cases'!L46 -> Pass | V46: ✓
A47: ='Web Test Cases'!A47 -> TC_FLT_EDGE_020 | B47: ='Web Test Cases'!D47 -> Dil dəyişəndə filtr qorunur və sayğaclar eynidir | C47: ='Web Test Cases'!B47 -> SC-009 | D47: ='Web Test Cases'!L47 -> Fail | N47: ✓
A48: ='Web Test Cases'!A48 -> TC_FLT_EDGE_021 | B48: ='Web Test Cases'!D48 -> Endirimli məhsul qiymət filtrində endirimli (faktiki) qiymətinə görə tapılır | C48: ='Web Test Cases'!B48 -> SC-009 | D48: ='Web Test Cases'!L48 -> Pass | V48: ✓
A49: ='Web Test Cases'!A49 -> TC_FLT_BVA_022 | B49: ='Web Test Cases'!D49 -> Qiymət filtrində yalnız 'dən', yalnız 'qədər' və ən yüksək qiymətdən böyük dəyər daxil edildikdə nəticə sərhədə uyğundur | C49: ='Web Test Cases'!B49 -> SC-009 | D49: ='Web Test Cases'!L49 -> Pass | H49: ✓ | I49: ✓
A50: ='Web Test Cases'!A50 -> TC_FLT_EDGE_023 | B50: ='Web Test Cases'!D50 -> Filtrli URL-də parametr əl ilə səhv dəyərə dəyişdirildikdə boş vəziyyət və ya filtrsiz siyahı göstərilir | C50: ='Web Test Cases'!B50 -> SC-009 | D50: ='Web Test Cases'!L50 -> Pass | V50: ✓
A51: ='Web Test Cases'!A51 -> TC_PDP_POS_001 | B51: ='Web Test Cases'!D51 -> Stokda olan məhsulun səhifəsində ad, məhsul kodu, qiymət, aylıq ödəniş, 'Səbətə' və '1 kliklə al' göstərilir | C51: ='Web Test Cases'!B51 -> SC-010 | D51: ='Web Test Cases'!L51 -> Pass | E51: ✓ | L51: ✓
A52: ='Web Test Cases'!A52 -> TC_PDP_POS_002 | B52: ='Web Test Cases'!D52 -> PDP-dəki aylıq ödəniş listing kartındakı ilə eynidir | C52: ='Web Test Cases'!B52 -> SC-010 | D52: ='Web Test Cases'!L52 -> Pass | L52: ✓ | M52: ✓
A53: ='Web Test Cases'!A53 -> TC_PDP_UI_003 | B53: ='Web Test Cases'!D53 -> AZ versiyada məhsul təsviri və texniki göstəricilər tərcümə və orfoqrafiya səhvi olmadan göstərilir | C53: ='Web Test Cases'!B53 -> SC-010 | D53: ='Web Test Cases'!L53 -> Pass | E53: ✓ | L53: ✓
A54: ='Web Test Cases'!A54 -> TC_PDP_POS_004 | B54: ='Web Test Cases'!D54 -> Yaddaş variantı dəyişəndə məhsul məlumatları yenilənir | C54: ='Web Test Cases'!B54 -> SC-011 | D54: ='Web Test Cases'!L54 -> Pass | J54: ✓
A55: ='Web Test Cases'!A55 -> TC_PDP_POS_005 | B55: ='Web Test Cases'!D55 -> Rəng variantı dəyişəndə məhsul məlumatları yenilənir | C55: ='Web Test Cases'!B55 -> SC-011 | D55: ='Web Test Cases'!L55 -> Pass | J55: ✓
A56: ='Web Test Cases'!A56 -> TC_PDP_BVA_006 | B56: ='Web Test Cases'!D56 -> Miqdar 1-dən aşağı enmir, '+' ilə artır | C56: ='Web Test Cases'!B56 -> SC-011 | D56: ='Web Test Cases'!L56 -> Pass | J56: ✓ | S56: ✓
A57: ='Web Test Cases'!A57 -> TC_PDP_BVA_007 | B57: ='Web Test Cases'!D57 -> Miqdarın yuxarı həddi stok/limitlə məhdudlaşır | C57: ='Web Test Cases'!B57 -> SC-011 | D57: ='Web Test Cases'!L57 -> Pass | J57: ✓ | S57: ✓
A58: ='Web Test Cases'!A58 -> TC_PDP_POS_008 | B58: ='Web Test Cases'!D58 -> Qoruma proqramı seçimi göstərilən məbləğə təsir edir | C58: ='Web Test Cases'!B58 -> SC-011 | D58: ='Web Test Cases'!L58 -> Pass | J58: ✓ | S58: ✓
A59: ='Web Test Cases'!A59 -> TC_PDP_POS_009 | B59: ='Web Test Cases'!D59 -> '1 kliklə al' formasında səhv formatlı telefon nömrəsi yazıldıqda sahənin altında xəta mesajı göstərilir (göndərmədən) | C59: ='Web Test Cases'!B59 -> SC-011 | D59: ='Web Test Cases'!L59 -> Pass | J59: ✓ | S59: ✓
A60: ='Web Test Cases'!A60 -> TC_PDP_POS_010 | B60: ='Web Test Cases'!D60 -> Variant (yaddaş və rəng) seçildikdən sonra səhifə yeniləndikdə seçilmiş variant, URL və qiymət saxlanılır | C60: ='Web Test Cases'!B60 -> SC-011 | D60: ='Web Test Cases'!L60 -> Pass | J60: ✓
A61: ='Web Test Cases'!A61 -> TC_PDP_POS_011 | B61: ='Web Test Cases'!D61 -> Stokda olmayan məhsul alına bilmir | C61: ='Web Test Cases'!B61 -> SC-012 | D61: ='Web Test Cases'!L61 -> Pass | O61: ✓
A62: ='Web Test Cases'!A62 -> TC_PDP_UI_012 | B62: ='Web Test Cases'!D62 -> Stokda olmayan məhsul üçün düymə mətnləri listing və PDP-də eynidir | C62: ='Web Test Cases'!B62 -> SC-012 | D62: ='Web Test Cases'!L62 -> Pass | O62: ✓
A63: ='Web Test Cases'!A63 -> TC_FIN_POS_001 | B63: ='Web Test Cases'!D63 -> 'Bütün proqramlara baxın' 'Taksitlə alış' pəncərəsini PDP-dəki məhsulla açır | C63: ='Web Test Cases'!B63 -> SC-013 | D63: ='Web Test Cases'!L63 -> Pass | U63: ✓
A64: ='Web Test Cases'!A64 -> TC_FIN_POS_002 | B64: ='Web Test Cases'!D64 -> PDP-dəki aylıq ödəniş pəncərədəki müddət və tərəfdaş məbləği ilə eynidir | C64: ='Web Test Cases'!B64 -> SC-013 | D64: ='Web Test Cases'!L64 -> Pass | L64: ✓ | M64: ✓
A65: ='Web Test Cases'!A65 -> TC_FIN_POS_003 | B65: ='Web Test Cases'!D65 -> Hər tərəfdaş üçün 'aylıq × ödəniş sayı' 'Ümumi ödəniş məbləği'nə bərabərdir | C65: ='Web Test Cases'!B65 -> SC-013 | D65: ='Web Test Cases'!L65 -> Fail | L65: ✓ | U65: ✓
A66: ='Web Test Cases'!A66 -> TC_FIN_POS_004 | B66: ='Web Test Cases'!D66 -> 0% tərəfdaşda ümumi məbləğ qiymətə bərabərdir, faizlidə əlavə xərc görünür | C66: ='Web Test Cases'!B66 -> SC-013 | D66: ='Web Test Cases'!L66 -> Pass | U66: ✓
A67: ='Web Test Cases'!A67 -> TC_FIN_BVA_005 | B67: ='Web Test Cases'!D67 -> Bütün müddət düymələrində aylıq məbləğ yuvarlaqlaşdırması ardıcıldır | C67: ='Web Test Cases'!B67 -> SC-013 | D67: ='Web Test Cases'!L67 -> Fail | L67: ✓ | U67: ✓
A68: ='Web Test Cases'!A68 -> TC_FIN_BVA_006 | B68: ='Web Test Cases'!D68 -> iPhone keyslərindən ən ucuzunda (9 ₼) taksitin aylıq məbləği × ay sayı məhsulun qiymətindən çox olmur | C68: ='Web Test Cases'!B68 -> SC-013 | D68: ='Web Test Cases'!L68 -> Fail | L68: ✓ | U68: ✓
A69: ='Web Test Cases'!A69 -> TC_FIN_EDGE_007 | B69: ='Web Test Cases'!D69 -> Müddət düyməsindəki məbləğin hansı tərəfdaşa aid olduğu aydındır | C69: ='Web Test Cases'!B69 -> SC-013 | D69: ='Web Test Cases'!L69 -> Fail | L69: ✓ | U69: ✓
A70: ='Web Test Cases'!A70 -> TC_FIN_EDGE_008 | B70: ='Web Test Cases'!D70 -> Endirimli məhsulun taksit pəncərəsində hər müddət üçün 'aylıq × ay sayı' endirimli qiymətə bərabərdir | C70: ='Web Test Cases'!B70 -> SC-013 | D70: ='Web Test Cases'!L70 -> Fail | U70: ✓
A71: ='Web Test Cases'!A71 -> TC_FIN_POS_009 | B71: ='Web Test Cases'!D71 -> Müddət düyməsi dəyişdikdə tərəfdaş məbləğləri və 'Ödəmək' yenilənir | C71: ='Web Test Cases'!B71 -> SC-014 | D71: ='Web Test Cases'!L71 -> Pass | U71: ✓
A72: ='Web Test Cases'!A72 -> TC_FIN_POS_010 | B72: ='Web Test Cases'!D72 -> Tərəfdaş dəyişdikdə 'Ödəmək' və seçim məlumatı uyğun dəyişir | C72: ='Web Test Cases'!B72 -> SC-014 | D72: ='Web Test Cases'!L72 -> Pass | U72: ✓
A73: ='Web Test Cases'!A73 -> TC_FIN_POS_011 | B73: ='Web Test Cases'!D73 -> Variant dəyişdikdə pəncərədə köhnə qiymətin məbləğləri qalmır | C73: ='Web Test Cases'!B73 -> SC-014 | D73: ='Web Test Cases'!L73 -> Pass | J73: ✓
A74: ='Web Test Cases'!A74 -> TC_FIN_POS_012 | B74: ='Web Test Cases'!D74 -> Pəncərədə qoruma proqramı seçimi 'Ödəmək' və taksit məbləğlərini yeniləyir, ləğv bərpa edir | C74: ='Web Test Cases'!B74 -> SC-014 | D74: ='Web Test Cases'!L74 -> Pass | U74: ✓
A75: ='Web Test Cases'!A75 -> TC_FIN_BVA_013 | B75: ='Web Test Cases'!D75 -> Pəncərədəki miqdar dəyişdikdə qiymət və taksitlər yenilənir | C75: ='Web Test Cases'!B75 -> SC-014 | D75: ='Web Test Cases'!L75 -> Pass | S75: ✓
A76: ='Web Test Cases'!A76 -> TC_FIN_EDGE_014 | B76: ='Web Test Cases'!D76 -> Pəncərədə edilən seçimlər 'Almaq' ilə səbətə eynilə ötürülür, 'X' ilə heç nə dəyişmir | C76: ='Web Test Cases'!B76 -> SC-014 | D76: ='Web Test Cases'!L76 -> Pass | K76: ✓
A77: ='Web Test Cases'!A77 -> TC_FIN_EDGE_015 | B77: ='Web Test Cases'!D77 -> Taksit pəncərəsi bağlandıqda və 'Geri' basıldıqda məhsul səhifəsi ilkin vəziyyətdə qalır | C77: ='Web Test Cases'!B77 -> SC-014 | D77: ='Web Test Cases'!L77 -> Pass | U77: ✓
A78: ='Web Test Cases'!A78 -> TC_FIN_POS_016 | B78: ='Web Test Cases'!D78 -> Səbətdən açılan taksit pəncərəsində məhsul qiymətləri və 'Ödəmək' səbətdəki qiymətlər və 'Cəmi' ilə eynidir | C78: ='Web Test Cases'!B78 -> SC-014 | D78: ='Web Test Cases'!L78 -> Fail | K78: ✓ | U78: ✓
A79: ='Web Test Cases'!A79 -> TC_CART_POS_001 | B79: ='Web Test Cases'!D79 -> Məhsul PDP-dən səbətə əlavə olunur | C79: ='Web Test Cases'!B79 -> SC-015 | D79: ='Web Test Cases'!L79 -> Pass | E79: ✓ | K79: ✓
A80: ='Web Test Cases'!A80 -> TC_CART_POS_002 | B80: ='Web Test Cases'!D80 -> Məhsul listing kartından birbaşa səbətə əlavə olunur | C80: ='Web Test Cases'!B80 -> SC-015 | D80: ='Web Test Cases'!L80 -> Pass | K80: ✓
A81: ='Web Test Cases'!A81 -> TC_CART_POS_003 | B81: ='Web Test Cases'!D81 -> Eyni məhsul iki dəfə əlavə edildikdə bir sətirdə miqdar 2 və sətir cəmi = qiymət × 2 olur | C81: ='Web Test Cases'!B81 -> SC-015 | D81: ='Web Test Cases'!L81 -> Pass | K81: ✓
A82: ='Web Test Cases'!A82 -> TC_CART_POS_004 | B82: ='Web Test Cases'!D82 -> İki fərqli məhsul olduqda 'Cəmi' sətir məbləğlərinin cəminə bərabərdir | C82: ='Web Test Cases'!B82 -> SC-016 | D82: ='Web Test Cases'!L82 -> Pass | K82: ✓
A83: ='Web Test Cases'!A83 -> TC_CART_POS_005 | B83: ='Web Test Cases'!D83 -> Səbətdə miqdar dəyişəndə sətir və ümumi cəm yenilənir | C83: ='Web Test Cases'!B83 -> SC-016 | D83: ='Web Test Cases'!L83 -> Pass | K83: ✓
A84: ='Web Test Cases'!A84 -> TC_CART_BVA_006 | B84: ='Web Test Cases'!D84 -> Səbətdə miqdar 1-dən aşağı enmir | C84: ='Web Test Cases'!B84 -> SC-016 | D84: ='Web Test Cases'!L84 -> Pass | K84: ✓
A85: ='Web Test Cases'!A85 -> TC_CART_POS_007 | B85: ='Web Test Cases'!D85 -> Məhsul səbətdən silinir | C85: ='Web Test Cases'!B85 -> SC-016 | D85: ='Web Test Cases'!L85 -> Pass | K85: ✓
A86: ='Web Test Cases'!A86 -> TC_CART_POS_008 | B86: ='Web Test Cases'!D86 -> Sonuncu məhsul silinəndə boş səbət vəziyyəti göstərilir | C86: ='Web Test Cases'!B86 -> SC-016 | D86: ='Web Test Cases'!L86 -> Pass | K86: ✓
A87: ='Web Test Cases'!A87 -> TC_CART_POS_009 | B87: ='Web Test Cases'!D87 -> Qoruma proqramı ilə əlavə edilən məhsulda proqram ayrıca sətir kimi göstərilir və cəmə daxil olur | C87: ='Web Test Cases'!B87 -> SC-016 | D87: ='Web Test Cases'!L87 -> Fail | K87: ✓
A88: ='Web Test Cases'!A88 -> TC_CART_POS_010 | B88: ='Web Test Cases'!D88 -> Səbət səhifə yenilənəndə və yeni tabda qorunur | C88: ='Web Test Cases'!B88 -> SC-017 | D88: ='Web Test Cases'!L88 -> Pass | K88: ✓ | N88: ✓
A89: ='Web Test Cases'!A89 -> TC_CART_POS_011 | B89: ='Web Test Cases'!D89 -> Dil dəyişəndə səbətin məzmunu qorunur | C89: ='Web Test Cases'!B89 -> SC-017 | D89: ='Web Test Cases'!L89 -> Pass | N89: ✓
A90: ='Web Test Cases'!A90 -> TC_CART_POS_012 | B90: ='Web Test Cases'!D90 -> Səbətdən checkout-a keçiddə məhsullar, qiymətlər və cəm eynilə ötürülür | C90: ='Web Test Cases'!B90 -> SC-017 | D90: ='Web Test Cases'!L90 -> Pass | K90: ✓ | N90: ✓
A91: ='Web Test Cases'!A91 -> TC_CART_EDGE_013 | B91: ='Web Test Cases'!D91 -> İki tabda eyni səbət dəyişdirildikdə yeniləmədən sonra hər iki tab son vəziyyəti göstərir | C91: ='Web Test Cases'!B91 -> SC-018 | D91: ='Web Test Cases'!L91 -> Pass | K91: ✓ | S91: ✓
A92: ='Web Test Cases'!A92 -> TC_CART_EDGE_014 | B92: ='Web Test Cases'!D92 -> Miqdar düyməsinə tez-tez klikdə sayğac, sətir və cəm uyğun qalır | C92: ='Web Test Cases'!B92 -> SC-018 | D92: ='Web Test Cases'!L92 -> Pass | K92: ✓ | S92: ✓
A93: ='Web Test Cases'!A93 -> TC_CART_EDGE_015 | B93: ='Web Test Cases'!D93 -> Silinmiş məhsul brauzerin 'Geri' düyməsindən sonra qayıtmır | C93: ='Web Test Cases'!B93 -> SC-018 | D93: ='Web Test Cases'!L93 -> Pass | K93: ✓ | S93: ✓
A94: ='Web Test Cases'!A94 -> TC_CART_EDGE_016 | B94: ='Web Test Cases'!D94 -> Eyni modelin fərqli variantları ayrı sətirlərdə saxlanılır | C94: ='Web Test Cases'!B94 -> SC-018 | D94: ='Web Test Cases'!L94 -> Pass | K94: ✓
A95: ='Web Test Cases'!A95 -> TC_CART_POS_017 | B95: ='Web Test Cases'!D95 -> Səbət sətrində şəkil, ad, variant, qiymət və miqdar göstərilir, klik eyni variantın PDP-sini açır | C95: ='Web Test Cases'!B95 -> SC-019 | D95: ='Web Test Cases'!L95 -> Pass | J95: ✓
A96: ='Web Test Cases'!A96 -> TC_CART_EDGE_018 | B96: ='Web Test Cases'!D96 -> Endirimli məhsul səbətdə endirimli qiymətlə hesablanır | C96: ='Web Test Cases'!B96 -> SC-019 | D96: ='Web Test Cases'!L96 -> Pass | K96: ✓ | W96: ✓
A97: ='Web Test Cases'!A97 -> TC_CART_EDGE_019 | B97: ='Web Test Cases'!D97 -> Məhsul silinəndə ona bağlı qoruma proqramı sətri də silinir | C97: ='Web Test Cases'!B97 -> SC-019 | D97: ='Web Test Cases'!L97 -> Pass | K97: ✓ | W97: ✓
A98: ='Web Test Cases'!A98 -> TC_CART_EDGE_020 | B98: ='Web Test Cases'!D98 -> Qoruma proqramlı məhsulun miqdarı artanda proqram miqdarı da uyğunlaşır | C98: ='Web Test Cases'!B98 -> SC-019 | D98: ='Web Test Cases'!L98 -> Pass | K98: ✓ | W98: ✓
A99: ='Web Test Cases'!A99 -> TC_CART_EDGE_021 | B99: ='Web Test Cases'!D99 -> Mini-səbətdə eyni modelin fərqli variantları ayırd edilir | C99: ='Web Test Cases'!B99 -> SC-019 | D99: ='Web Test Cases'!L99 -> Pass | K99: ✓ | W99: ✓
A100: ='Web Test Cases'!A100 -> TC_CART_EDGE_022 | B100: ='Web Test Cases'!D100 -> Səbətdəki aylıq ödəniş mətnləri və 'X ₼/ay üçün 18 ay' bloku eyni bazaya əsaslanır | C100: ='Web Test Cases'!B100 -> SC-019 | D100: ='Web Test Cases'!L100 -> Fail | K100: ✓ | W100: ✓
A101: ='Web Test Cases'!A101 -> TC_CART_POS_023 | B101: ='Web Test Cases'!D101 -> Səbətdə qoruma proqramı seçimi Cəmi və taksit blokunu yeniləyir | C101: ='Web Test Cases'!B101 -> SC-019 | D101: ='Web Test Cases'!L101 -> Pass | K101: ✓
...

Sheet Decision Matrix
A1: Manual / Avtomat Qərar Matrisi
A4: Kod | B4: Qərar | C4: Meyar | D4: İzah | E4: Nümunə
A5: A1 | B5: Avtomat | C5: Kritik və tez-tez təkrarlanan | D5: Gəlir axınına (kataloq → məhsul → səbət) birbaşa təsir edir və hər release-də yoxlanmalıdır. | E5: Səbətə əlavə, səbət cəmi, qiymət uyğunluğu
A6: A2 | B6: Avtomat | C6: Deterministik və ölçülə bilən nəticə | D6: Nəticə hər icrada eynidir və konkret qayda ilə yoxlanılır (say, sıra, uyğunluq). Assertion dəyişkən dataya yox, qaydaya əsaslanır. | E6: Sıralama artan sırada, filtr sayğacı = nəticə sayı
A7: A3 | B7: Avtomat | C7: Çox data / kombinasiya | D7: Eyni yoxlama çoxlu dəyər və ya kombinasiya ilə təkrarlanır — əl ilə yorucu və səhvə meyillidir. | E7: Filtr kombinasiyaları, səhifələr boyu sıra
A8: M1 | B8: Manual | C8: İnsan qiymətləndirməsi lazımdır | D8: Vizual görünüş, UX, mətn və tərcümə keyfiyyəti, axtarış nəticələrinin 'uyğunluğu' — kodla etibarlı ölçülmür. | E8: Orfoqrafiya səhvləri, qalereya, axtarışda yazı səhvi
A9: M2 | B9: Manual | C9: Real / geri qaytarılmaz əməliyyat | D9: Prodda real sifariş, müraciət və ya bildiriş yaradır. Yalnız submit-ə qədər manual yoxlanılır. | E9: 1 kliklə al, checkout, 'Mövcud olduqda bildirin'
A10: M3 | B10: Manual | C10: Qeyri-deterministik nəticə | D10: Nəticə kataloqdan, kampaniyadan və ya eyni qiymətli məhsulların sırasından asılıdır — avtomat test flaky olar. | E10: Banner linkləri, nəticəsiz filtr kombinasiyası
A11: M4 | B11: Manual | C11: Kənar asılılıq | D11: Üçüncü tərəf servis, ünvana görə dəyişən tarif, SMS və s. | E11: Çatdırılma haqqı (4–50 ₼, ünvandan asılı)
A12: M5 | B12: Manual | C12: Aşağı risk / tələb qeyri-müəyyən | D12: Bir dəfəlik yoxlama, aşağı biznes riski və ya gözlənilən davranış tələbdə yoxdur — əvvəl biznes qərarı lazımdır. | E12: ?page=0, miqdarın yuxarı həddi, min > max
A15: Regression seçimi qaydası
A16: 1. Case avtomatlaşdırılır (A1–A3) VƏ prioriteti P1 — Critical və ya P2 — High-dır → Regression: Bəli.
A17: 2. P3 — Medium prioritetli avtomat case → yalnız pul/say/qiymət ilə bağlıdırsa və ya əvvəl bug tapılan yerdədirsə Regression: Bəli.
A18: 3. Smoke = regression-un alt dəsti: sistemin ümumiyyətlə işlədiyini 2–3 dəqiqədə göstərən ən kritik case-lər.
A19: 4. Manual case regression-a daxil edilmir; release öncəsi riskə görə seçmə icra olunur.
A20: 5. 'Avtomat' = avtomatlaşdırmağa uyğundur. Regression = Bəli olan 40 case-dən 20-i avtomatlaşdırılıb (prioritet: pul hesablamaları, əsas axın, filtr/sıralama, BVA), 2-si prod-da real sifariş/maliyyə riski səbəbindən manual regression kimi qalır, 18-i növbəti mərhələdə avtomatlaşdırılacaq ('Web Test Cases' → 'Avtomatlaşdırma statusu' sütunu).

Sheet Bug Reports
A1: Bug Report-lar — iSpace.az
A4: Bug ID | B4: Başlıq | C4: Modul | D4: Mühit | E4: Addımlar | F4: Gözlənilən nəticə | G4: Faktiki nəticə | H4: Severity | I4: Priority | J4: Təkrarlanma | K4: Status | L4: Sübut | M4: Əlaqəli test case
A5: BUG-001 | B5: Səhifələmə zamanı məhsulun təkrarlanması və ya itməsi | C5: Kateqoriya — pagination | D5: Production · Chrome (son) · Windows/macOS desktop · inkognito · AZ dili | E5: 1. https://ispace.az/category/iphone aç 2. Bütün səhifələrdən məhsul URL-lərini topla 3. Təkrarlanan və itən məhsulu yoxla | F5: Bütün səhifələrdə toplanan URL-lərin sayı = N, təkrar yoxdur | G5: 10.10 təkrar icrasında təkrarlanma/itmə müşahidə olunmadı | H5: — | I5: — | J5: 0/1 | K5: Rejected | L5: 10.10 təkrar icrası (TC_PLP_POS_023 — Pass) | M5: TC_PLP_POS_023
A6: BUG-002 | B6: Qoruma proqramı seçimi ləğv olunmur, yalnız səhifə yeniləndikdə sıfırlanır | C6: PDP — əlavə proqram | D6: Production · Chrome (son) · Windows/macOS desktop · inkognito · AZ dili | E6: 1. Stokda olan iPhone PDP-sini aç 2. '+1 il zədələrə qarşı qorunma' seç 3. Eyni seçimə yenidən klik et 4. 'Əlavə proqram olmadan' seçiminə klik et | F6: Addım 4-dən sonra proqram ləğv olunur və qiymət ilkin vəziyyətə qayıdır | G6: Addım 3-dən sonra seçim ləğv olunmur; yalnız səhifə yeniləndikdə sıfırlanır. Addım 4-ün nəticəsi qeyd edilməlidir | H6: Medium | I6: P3 | K6: Rejected (təkrar yoxlamada təkrarlanmadı) | L6: Video/ekran görüntüsü | M6: TC_PDP_POS_008
A7: BUG-003 | B7: Səbət sayğacı faktiki əlavə edilən miqdardan çox göstərir | C7: Səbət | D7: Production · Chrome (son) · Windows/macOS desktop · inkognito · AZ dili | E7: 1. YENİ inkognito pəncərə aç (səbət boş olmalıdır) 2. Bir məhsulu 1 dəfə səbətə əlavə et 3. Header sayğacına və səbətdəki miqdara bax 4. Səhifəni yenilə | F7: Sayğac və miqdar 1-dir | G7: İlk icrada 1 məhsul əlavə edilsə də 4 göstərildi. 10.10 təkrar yoxlamasında (yeni inkognito sessiya) sayğac və miqdar düzgündür: sayğac qaydası ardıcıldır (TC_CART_EDGE_025), səbət sessiyaya bağlıdır və təmizlənəndə sıfırlanır (TC_CART_EDGE_028). Nəticə: '4' əvvəlki case-lərdən qalan səbət idi, defekt deyil — test datası problemi | H7: — | I7: — | J7: 0/2 (təmiz sessiyada) | K7: Rejected (təkrarlanmır) | L7: Ekran görüntüsü (ilk müşahidə); 10.10 təkrar yoxlama: TC_CART_EDGE_025, TC_CART_EDGE_028 — Pass | M7: TC_CART_EDGE_028
A8: BUG-004 | B8: Səbətdə 1 məhsul əvəzinə 4 göstərilir | C8: Səbət | D8: Production · Chrome (son) · Windows/macOS desktop · inkognito · AZ dili | E8: BUG-003 ilə eyni | F8: — | G8: TC_CART_POS_012 icrasında eyni müşahidə | H8: — | I8: — | J8: — | K8: Duplicate (BUG-003) | L8: — | M8: TC_CART_POS_012
A9: BUG-005 | B9: RU versiyada kateqoriya başlığında tərcümə olunmamış mətn var | C9: Lokalizasiya — RU | D9: Production · Chrome (son) · Windows/macOS desktop · inkognito · AZ dili | E9: 1. https://ispace.az/ru/category/iphone aç 2. Kateqoriya başlığı blokuna bax | F9: Bütün mətnlər rus dilindədir | G9: Kateqoriya başlığında bir hissə tərcümə olunmayıb (dəqiq mətn və ekran görüntüsü əlavə edilməlidir) | H9: Low | I9: P3 | K9: New | L9: Ekran görüntüsü | M9: TC_LOC_UI_005
A10: BUG-006 | B10: Stok filtrində orfoqrafik səhv: 'Movcuddur' | C10: Kateqoriya — filtr / Lokalizasiya | D10: Production · Chrome (son) · Windows/macOS desktop · inkognito · AZ dili | E10: 1. https://ispace.az/category/iphone aç 2. 'Stokda var' filtr blokuna bax | F10: 'Mövcuddur' | G10: 'Movcuddur' (ö əvəzinə o) | H10: Low | I10: P4 | J10: 3/3 | K10: New | L10: Ekran görüntüsü | M10: TC_LOC_UI_003
A11: BUG-007 | B11: '1 kliklə al' formasında sahə səviyyəsində validasiya yoxdur — boş forma ümumi xəta verir | C11: PDP — 1 kliklə al | D11: Production · Chrome (son) · Windows/macOS desktop · inkognito · AZ dili | E11: 1. Stokda olan məhsulun PDP-sini aç 2. '1 kliklə al' bas 3. Sahələri boş saxlayıb təsdiq düyməsinə bas | F11: Məcburi sahələr işarələnir, hər sahənin altında aydın mesaj göstərilir; sorğu serverə göndərilmir | G11: Ümumi mesaj: 'Xəta baş verdi. Müraciəti yenidən göndərməyə cəhd edin.' — hansı sahənin səhv olduğu göstərilmir | H11: Medium | I11: P3 | K11: Rejected (təkrar yoxlamada təkrarlanmadı) | L11: Ekran görüntüsü | M11: TC_PDP_POS_009
A12: BUG-008 | B12: Menyuda orfoqrafik səhv: 'Acıq qutu' | C12: Naviqasiya | D12: Production · Chrome (son) · Windows/macOS desktop · inkognito · AZ dili | E12: 1. Ana səhifəni aç 2. Mac / iPad / iPhone menyusunu aç | F12: 'Açıq qutu' | G12: 'Acıq qutu' | H12: Low | I12: P4 | K12: Rejected (icrada təsdiqlənmədi) | L12: Ekran görüntüsü | M12: TC_LOC_UI_003
A13: BUG-009 | B13: PDP texniki göstəricilərdə səhv başlıq: 'Camera Video Featuers' | C13: PDP | D13: Production · Chrome (son) · Windows/macOS desktop · inkognito · AZ dili | E13: iPhone 17 PDP → Texniki göstəricilər → Kamera | F13: Azərbaycanca düzgün başlıq | G13: 'Camera Video Featuers' | H13: Low | I13: P4 | J13: 0/1 | K13: Rejected | L13: 08.10 icrasında təkrarlanmadı (TC_PDP_UI_003) | M13: TC_PDP_UI_003
A14: BUG-010 | B14: PDP-də orfoqrafik səhv: 'Proqramm təminatı' | C14: PDP | D14: Production · Chrome (son) · Windows/macOS desktop · inkognito · AZ dili | E14: iPhone 17 PDP → Texniki göstəricilər | F14: 'Proqram təminatı' | G14: 'Proqramm təminatı' | H14: Low | I14: P4 | J14: 0/1 | K14: Rejected | L14: 08.10 icrasında təkrarlanmadı (TC_PDP_UI_003) | M14: TC_PDP_UI_003
A15: BUG-011 | B15: AZ versiyada filtr dəyərləri tərcümə olunmayıb: '36 Hours', '45 Hours' | C15: Kateqoriya — filtr | D15: Production · Chrome (son) · Windows/macOS desktop · inkognito · AZ dili | E15: /category/iphone → 'Video izləmə müddəti' filtri | F15: '36 saat', '45 saat' | G15: '36 Hours', '45 Hours' (10.10 icrasında təsdiqləndi) | H15: Low | I15: P3 | J15: 1/1 | K15: New | L15: Ekran görüntüsü | M15: TC_FLT_EDGE_006
A16: BUG-012 | B16: Kateqoriya karuselində qarışıq dilli mətn: 'View all iPhone -lara bax' | C16: Naviqasiya / Lokalizasiya | D16: Production · Chrome (son) · Windows/macOS desktop · inkognito · AZ dili | E16: /category/iphone → yuxarıdakı model karuselinin sonu | F16: Tam azərbaycanca mətn | G16: 'View all iPhone -lara bax' | H16: Low | I16: P3 | K16: Rejected (icrada təsdiqlənmədi) | L16: Ekran görüntüsü | M16: TC_LOC_UI_003
A17: BUG-013 | B17: PDP təsvirində yanlış tərcümə: 'Ceramic Shield 2 ön kamerası' | C17: PDP | D17: Production · Chrome (son) · Windows/macOS desktop · inkognito · AZ dili | E17: iPhone 17 PDP → Xüsusiyyətlər, 1-ci bənd | F17: Ceramic Shield ön örtük kimi təsvir olunur | G17: 'ön kamerası' kimi təsvir olunub | H17: Low | I17: P4 | J17: 0/1 | K17: Rejected | L17: 08.10 icrasında təkrarlanmadı (TC_PDP_UI_003) | M17: TC_PDP_UI_003
A18: BUG-014 | B18: Listing kartında '0% · 12 ay' etiketi ilə '24 ay' aylıq məbləği yanaşı göstərilir | C18: Kateqoriya / UX | D18: Production · Chrome (son) · Windows/macOS desktop · inkognito · AZ dili | E18: /category/iphone → iPhone 17 Pro Max 256 GB kartı | F18: Etiket və aylıq məbləğ eyni taksit şərtinə aid olur | G18: '0% · 12 ay' etiketi, altında 'Ayda 161 ₼-dan, 24 ay' — istifadəçi 0%-i 24 aya aid edə bilər | H18: Medium | I18: P3 | K18: Rejected (icrada təsdiqlənmədi) | L18: Ekran görüntüsü | M18: TC_PDP_POS_002, TC_FIN_POS_004
A19: BUG-015 | B19: Aylıq ödənişdəki '*' işarəsinin izahı tapılmır | C19: PDP / Taksit | D19: Production · Chrome (son) · Windows/macOS desktop · inkognito · AZ dili | E19: 1. iPhone 17 256 GB PDP-sini aç 2. Qiymətin altındakı '113 ₼/ay 24 ay*' mətninə bax 3. '*' izahını səhifədə və proqramlar pəncərəsində axtar | F19: '*' işarəsinin mənası (faiz, şərt) istifadəçiyə görünən yerdə izah olunur | G19: Səhifə məzmununda '*' üçün izah tapılmadı (08.10 müşahidəsi) | H19: Low | I19: P3 | K19: Rejected (icrada təsdiqlənmədi) | L19: Ekran görüntüsü | M19: TC_FIN_POS_002
A20: BUG-016 | B20: Ucuz məhsullarda aylıq ödəniş yuvarlaqlaşdırma ilə qiymətin 2 mislinə çatır (9 ₼ → 1 ₼ × 18 ay = 18 ₼) | C20: Taksit / Kateqoriya | D20: Production · Chrome (son) · Windows/macOS desktop · inkognito · AZ dili | E20: 1. https://ispace.az/accessories-for-iphone aç, 'Aşağı qiymət' sırala 2. 9 ₼-lıq aksesuarın PDP-sini aç 3. 'Bütün proqramlara baxın' → '18 ay' seç 4. 'A ₼ × N ödəniş' və 'Ümumi ödəniş məbləği'ni müqayisə et | F20: Aylıq məbləğ qəpiklə (0,50 ₼) göstərilir və ya bu məbləğ üçün taksit təklif olunmur; 0% proqramda ödənişlərin cəmi ≈ qiymət | G20: Ana səhifədə '1 ₼/ay × 18 ay' (= 18 ₼). 08.10 icrası (TC_FIN_BVA_006): 9 ₼-lıq aksesuarın 'Taksitlə alış' pəncərəsində 18 ay üçün '1 ₼ × 18 ödəniş', 'Ümumi ödəniş məbləği' isə 9 ₼ — göstərilən aylıq ödəniş ümumi məbləğin 2 mislini verir | H20: Medium | I20: P2 | J20: 1/1 | K20: New | L20: Ekran görüntüsü (əlavə edilməlidir) | M20: TC_FIN_BVA_006
A21: BUG-017 | B21: 'Taksitlə alış' pəncərəsində 'aylıq × ödəniş sayı' ümumi ödəniş məbləğinə bərabər deyil | C21: Taksit proqramları | D21: Production · Chrome (son) · Windows/macOS desktop · inkognito · AZ dili | E21: 1. https://ispace.az/ saytında iPhone 18 Pro, 256 GB, Qara PDP-sini aç (3 589 ₼) 2. Qiymətin altındakı 'Bütün proqramlara baxın' bas 3. 'Taksit kartları' bölməsində '18 ay' seç 4. Hər tərəfdaşın 'A ₼ × N ödəniş' və 'Ümumi ödəniş məbləği' dəyərlərini müqayisə et | F21: A × N = 'Ümumi ödəniş məbləği'; son ödəniş fərqlidirsə, açıq göstərilir | G21: iPhone 18 Pro, 256 GB, Qara (3 589 ₼): UCard 199 ₼ × 18 = 3 582 ₼, ümumi 3 589 ₼ (7 ₼ az); 9 ay 399 × 9 = 3 591 ₼ (2 ₼ çox). Beosound A9 (endirimli 5 999 ₼): 3 ay 2 000 × 3 = 6 000; 9 ay 667 × 9 = 6 003; 18 ay 333 × 18 = 5 994. Heç bir məhsulda və müddətdə aylıq × ay sayı ümumi məbləğə bərabər deyil və son ödəniş fərqi göstərilmir (08.10 və 10.10 icrası) | H21: Medium | I21: P2 | J21: 2/2 (ekran görüntüləri) | K21: New | L21: Ekran görüntüləri: 08.10 PDP (UCard 199 × 18 = 3 582 ≠ 3 589; Leobank 217 × 18 = 3 906 ≠ 3 912); 10.10 səbət (UCard 215 × 18 = 3 870 ≠ 3 878); 10.10 PDP '3 ay' (UCard/Tamkart 1 196 × 3 = 3 588 ≠ 3 589) | M21: TC_FIN_POS_003, TC_FIN_BVA_005, TC_FIN_EDGE_008
A22: BUG-018 | B22: Endirimli məhsul üçün taksit pəncərəsi endirimsiz qiymətlə hesablanır | C22: Taksit proqramları / Səbət | D22: Production · Chrome (son) · Windows/macOS desktop · inkognito · AZ dili | E22: 1. Endirimli məhsulu tap (məs. https://ispace.az/category/extra-deals) — köhnə və yeni qiyməti qeyd et 2. Məhsulu səbətə əlavə et 3. 'Bütün proqramlara baxın' aç 4. Pəncərədəki qiyməti, 'Ödəmək'i və taksit məbləğlərini endirimli qiymətlə müqayisə et | F22: Taksit məbləğləri və 'Ödəmək' endirimli (faktiki satış) qiymətə görə hesablanır | G22: Pəncərədə endirimsiz qiymət göstərilir və taksit ona görə hesablanır — müştəriyə endirimdən artıq məbləğ təklif olunur (08.10 icrası; məhsul URL-i və ekran görüntüsü əlavə edilməlidir). 10.10 təkrar yoxlama: endirimli məhsulun (Beosound A9, 5 999 ₼) taksit pəncərəsi endirimli qiyməti istifadə edir — bug təkrarlanmadı | H22: High | I22: P1 | J22: 1/1 | K22: Rejected (təkrar yoxlamada təkrarlanmadı) | L22: Ekran görüntüsü + məhsul URL-i (əlavə edilməlidir) | M22: TC_FIN_EDGE_008
A23: BUG-019 | B23: 'Əlavə xüsusiyyətlər' filtri yalnız 8 məhsulda doldurulub — uyğun modellərin çoxu filtrlə tapılmır | C23: Kateqoriya — filtr | D23: Production · Chrome (son) · Windows/macOS desktop · inkognito · AZ dili | E23: 1. https://ispace.az/category/iphone aç 2. 'Əlavə xüsusiyyətlər' → 'Dynamic Island (8)' seç, 'Tətbiq et' 3. Nəticə modellərini filtrsiz siyahıdakı iPhone 15/16/17/18 modelləri ilə müqayisə et | F23: Xüsusiyyəti olan bütün məhsullar nəticədədir (Dynamic Island iPhone 15-dən bəri əsas modellərin hamısında var) və ya natamam data üçün filtr göstərilmir | G23: Bütün xüsusiyyət dəyərlərinin sayğacı 8-dir (10.10 müşahidəsi); 213 məhsuldan yalnız 8-i bu filtrlə tapılır | H23: Medium | I23: P3 | K23: Rejected (icrada təsdiqlənmədi) | L23: Ekran görüntüsü | M23: TC_FLT_EDGE_011
A24: BUG-020 | B24: 'Əlavə xüsusiyyətlər' filtr dəyərləri AZ versiyada ingiliscədir | C24: Kateqoriya — filtr / Lokalizasiya | D24: Production · Chrome (son) · Windows/macOS desktop · inkognito · AZ dili | E24: 1. https://ispace.az/category/iphone aç 2. 'Əlavə xüsusiyyətlər' qrupunu oxu | F24: Dəyərlər azərbaycancadır (brend terminləri istisna) | G24: 'ProMotion technology with adaptive refresh rates up to 120Hz', '1600 nits peak brightness (HDR)', '3000 nits peak brightness (outdoor)', 'Always On display' (10.10 müşahidəsi) | H24: Low | I24: P4 | J24: 1/1 | K24: New | L24: Ekran görüntüsü | M24: TC_FLT_UI_012
A25: BUG-021 | B25: 'Video izləmə müddəti' filtrinin dəyəri məhsulun PDP göstəricisi ilə uyğun deyil | C25: Kateqoriya — filtr / Data | D25: Production · Chrome (son) · Windows/macOS desktop · inkognito · AZ dili | E25: 1. https://ispace.az/category/iphone aç 2. 'Video izləmə müddəti' → '36 Hours' seç, 'Tətbiq et' 3. Nəticələrdən 'iPhone 18 Pro, 512 GB, Burgundy' PDP-sini aç 4. 'Texniki göstəricilər' → video izləmə müddətinə bax | F25: Filtrdə seçilmiş dəyər (36 saat) məhsulun PDP-dəki göstəricisi ilə eynidir | G25: PDP-də video izləmə müddəti 34 saata qədər göstərilir, filtr isə məhsulu 36 saatlıq kimi qaytarır — filtr datası ilə məhsul datası ziddiyyətlidir (10.10 icrası) | H25: Medium | I25: P3 | J25: 1/1 | K25: New | L25: Ekran görüntüsü (filtr + PDP) | M25: TC_FLT_EDGE_007
A26: BUG-022 | B26: Dil dəyişəndə (AZ → EN) tətbiq olunmuş filtrlər silinir | C26: Kateqoriya — filtr / Lokalizasiya | D26: Production · Chrome (son) · Windows/macOS desktop · inkognito · AZ dili | E26: 1. https://ispace.az/category/iphone aç 2. '512 GB' və 'Mövcuddur' seç, 'Tətbiq et' 3. Dili 'English' et | F26: EN versiyada eyni filtrlər seçili qalır, nəticə sayı eynidir | G26: EN-ə keçəndə filtrlər sıfırlanır, bütün məhsullar göstərilir — istifadəçi seçimlərini yenidən etməli olur (10.10 icrası) | H26: Medium | I26: P3 | J26: 1/1 | K26: New | L26: Ekran görüntüsü (əvvəl/sonra URL) | M26: TC_FLT_EDGE_020
A27: BUG-023 | B27: AZ versiyada bəzi iPhone modellərinin məhsul səhifəsində 'Ətraflı' bölməsi ingiliscədir (məs. iPhone 17e) | C27: PDP / Lokalizasiya | D27: Production · Chrome (son) · Windows/macOS desktop · inkognito · AZ dili | E27: 1. https://ispace.az/category/iphone aç (dil: Azərbaycan) 2. iPhone 17e məhsul səhifəsini aç 3. 'Ətraflı' bölməsini aç və mətnin dilinə bax 4. iPhone 17 məhsul səhifəsində eyni bölmə ilə müqayisə et | F27: Bütün modellərin 'Ətraflı' bölməsi azərbaycancadır | G27: AZ versiyada 'Ətraflı' bölməsi bəzi modellərdə azərbaycanca, bəzilərində ingiliscədir (məs. iPhone 17e — tam ingiliscə); eyni kateqoriyada dil qarışıqdır (10.10 icrası) | H27: Low | I27: P3 | J27: 1/1 | K27: New | L27: Ekran görüntüsü | M27: TC_LOC_UI_004
A28: BUG-024 | B28: Səbət və mini-səbətdə '−15% VİSA' endirimi şərtsiz qiymət kimi göstərilir | C28: Səbət / Qiymət | D28: Production · Chrome (son) · Windows/macOS desktop · inkognito · AZ dili | E28: 1. Listing-də AirPods 4 kartına bax: 349 ₼ xətli, 289 ₼, '−15% VİSA' nişanı 2. Səbətə əlavə et 3. Mini-səbətdə və /cart səhifəsində qiymətə bax | F28: Səbətdə ya listing qiyməti (289 ₼) göstərilir, ya da 246 ₼ yanında 'Apple Pay + Visa ilə ödənişdə' şərti yazılır | G28: Səbətdə 246 ₼ (= 289 × 0,85) şərtsiz göstərilir, xətli qiymət kimi 349 ₼ verilir; eyni sətirdə 'ya Ayda 16 ₼' isə 289 ₼-a görədir; 'Tam ödəmək 3 835 ₼' Visa endirimini nəzərdə tutur, amma bu yazılmır (10.10 ekran görüntüləri) | H28: Medium | I28: P2 | J28: 2/2 (ekran görüntüləri) | K28: New | L28: Ekran görüntüləri 10.10: listing, mini-səbət, səbət; səbətdən açılan 'Taksitlə alış' pəncərəsində eyni AirPods 289 ₼, Ödəmək 3 878 ₼ (səbətdə 246 ₼ və 3 835 ₼) | M28: TC_FIN_POS_016, TC_CART_EDGE_022
A29: BUG-025 | B29: Windows/Chrome-da checkout-da Apple Pay default ödəniş üsulu kimi seçilir | C29: Checkout | D29: Production · Chrome (son) · Windows/macOS desktop · inkognito · AZ dili | E29: 1. Windows-da Chrome ilə səbətdə məhsul olan halda /checkout aç 2. 'Ödəniş' bölməsinə bax | F29: Apple Pay yalnız dəstəklənən mühitdə göstərilir və ya default seçilmir | G29: 'Apple Pay vasitəsilə Visa ilə ödənişdə –15%' default seçilib (10.10 ekran görüntüsü, Windows + Chrome) | H29: Medium | I29: P3 | J29: 1/1 (ekran görüntüsü) | K29: New | L29: Ekran görüntüsü 10.10 | M29: Kəşf (checkout səhifəsinin müşahidəsi, submit-siz)
A30: BUG-026 | B30: Mini-səbətdə məhsulun variantı (yaddaş, rəng) göstərilmir | C30: Səbət — mini-səbət | D30: Production · Chrome (son) · Windows/macOS desktop · inkognito · AZ dili | E30: 1. Səbətə iPhone 18 Pro 256 GB Qara əlavə et 2. Açılan mini-səbətə bax | F30: Sətirdə tam ad və variant ('iPhone 18 Pro, 256 GB, Qara') göstərilir | G30: Yalnız 'iPhone 18 Pro' yazılır; eyni modelin iki variantı mini-səbətdə yalnız qiymətlə fərqlənir (10.10 ekran görüntüsü) | H30: Low | I30: P3 | J30: 1/1 (ekran görüntüsü) | K30: Rejected (təkrar yoxlamada təkrarlanmadı) | L30: Ekran görüntüsü 10.10 (mini-səbət) | M30: TC_CART_EDGE_021
A31: BUG-027 | B31: 'Ön sifariş' məhsulu stokdakı məhsulla eyni səbətə xəbərdarlıqsız əlavə olunur | C31: Səbət | D31: Production · Chrome (son) · Windows/macOS desktop · inkognito · AZ dili | E31: 1. 'Ön sifariş' düyməli məhsulu səbətə əlavə et 2. Stokda olan adi məhsul əlavə et 3. Səbətdə sətirlərə və checkout düyməsinə bax | F31: Ön sifariş sətri ayrıca işarələnir (təxmini tarix/şərt) və ya qarışıq səbət barədə xəbərdarlıq göstərilir | G31: Hər iki məhsul səbətdə adi məhsul kimi görünür, ön sifariş barədə heç bir qeyd/mesaj yoxdur (10.10 icrası). Müştəri hər ikisinin eyni vaxtda çatdırılacağını düşünə bilər | H31: Low | I31: P3 | J31: 1/1 | K31: New | L31: Ekran görüntüsü (əlavə edilməlidir) | M31: TC_CART_EDGE_027
A32: BUG-028 | B32: Checkout-da çatdırılma qiyməti '3 AZN-dən' yazılır, 'Çatdırılma və ödəniş' səhifəsində isə 4–50 ₼ | C32: Checkout / Çatdırılma | D32: Production · Chrome (son) · Windows/macOS desktop · inkognito · AZ dili | E32: 1. https://ispace.az/payment-delivery aç, Bakı kuryer tarifini oxu 2. Səbətə yalnız AirPods 4 əlavə et 3. https://ispace.az/cart → 'Sifarişi rəsmiləşdirmək' 4. 'Kuryer ilə çatdırılma', Şəhər 'Bakı' seç 5. Mesajdakı minimum qiyməti 1-ci addımdakı tariflə müqayisə et 6. Sifarişi GÖNDƏRMƏ | F32: Hər iki yerdə eyni tarif məlumatı (minimum qiymət) göstərilir | G32: Checkout: 'Sifarişin məbləği 300 AZN-ə qədər olduqda, çatdırılma qiyməti 3 AZN-dən başlayır'; /payment-delivery: Bakı üzrə 4–50 ₼ (10.10 icrası) | H32: Low | I32: P3 | J32: 1/1 | K32: New | L32: Ekran görüntüsü (checkout mesajı + payment-delivery) | M32: TC_CHK_POS_004
A33: BUG-029 | B33: Taksit pəncərəsində müddət düyməsindəki aylıq məbləğ seçilmiş tərəfdaşa görə yenilənmir | C33: Taksit proqramları | D33: Production · Chrome (son) · Windows/macOS desktop · inkognito · AZ dili | E33: 1. iPhone 18 Pro, 256 GB, Qara PDP-sini aç (3 589 ₼) 2. 'Bütün proqramlara baxın' bas 3. 'Taksit kartları'nda '18 ay' seç — düymədə 199 ₼ 4. 'Leobank taksit kartı ilə ödəniş' seç 5. '18 ay' düyməsindəki məbləğə yenidən bax | F33: Düymədəki məbləğ seçilmiş tərəfdaşa görə yenilənir (217 ₼) və ya minimum məbləğ olduğu yazılır ('199 ₼-dan') | G33: Leobank seçili ikən düymədə '18 ay · 199 ₼' qalır, Leobank sətrində isə '217 ₼ × 18 ödəniş'. Düymədə nə tərəfdaş adı, nə də '-dan' qeydi var — müştəri seçdiyi kartla aylıq 199 ₼ ödəyəcəyini düşünə bilər (fərq 18 ₼/ay, 18 ayda 323 ₼) | H33: Medium | I33: P3 | J33: 1/1 | K33: New | L33: Ekran görüntüləri (UCard seçili və Leobank seçili) | M33: TC_FIN_EDGE_007
A34: BUG-030 | B34: Checkout-da 300 ₼-dan az səbətdə kuryer seçildikdə xülasədə 'Çatdırılma: Ödənişsiz' göstərilir, çatdırılma haqqı məbləğə əlavə olunmur | C34: Checkout / Çatdırılma | D34: Production · Chrome (son) · Windows/macOS desktop · inkognito · AZ dili | E34: 1. Səbətə yalnız AirPods 4 əlavə et (cəmi < 300 ₼) 2. https://ispace.az/cart → 'Sifarişi rəsmiləşdirmək' bas 3. 'Kuryer ilə çatdırılma' və Şəhər 'Bakı' seç 4. Bölmənin altındakı mesajı oxu 5. Sağdakı xülasədə 'Çatdırılma' sətrinə və 'Ödəmək'ə bax 6. Sifarişi GÖNDƏRMƏ | F34: Mesajda göstərilən çatdırılma haqqı xülasənin 'Çatdırılma' sətrində göstərilir və 'Ödəmək'ə əlavə olunur | G34: Mesaj: 'Sifarişin məbləği 300 AZN-ə qədər olduqda, çatdırılma qiyməti 3 AZN-dən başlayır'; xülasə isə 'Çatdırılma: Ödənişsiz' göstərir və 'Ödəmək' dəyişmir (10.10 icrası). Müştəri pulsuz çatdırılma gözləyir — ya şirkət haqqı itirir, ya da müştəriyə sonradan gözlənilməz ödəniş çıxır | H34: High | I34: P2 | J34: 1/1 | K34: New | L34: Ekran görüntüsü (kuryer mesajı + xülasə) | M34: TC_CHK_POS_003
A35: BUG-031 | B35: Checkout-da Bakıdan kənar şəhər seçildikdə çatdırılma mesajı dəyişmir — rayon çatdırılma şərtləri göstərilmir | C35: Checkout / Çatdırılma | D35: Production · Chrome (son) · Windows/macOS desktop · inkognito · AZ dili | E35: 1. Səbətə yalnız AirPods 4 əlavə et (cəmi < 300 ₼) 2. https://ispace.az/cart → 'Sifarişi rəsmiləşdirmək' bas 3. 'Kuryer ilə çatdırılma' seç 4. Şəhər siyahısından 'Sumqayıt' seç və mesajı oxu 5. Şəhəri 'Bakı' et və mesajı yenidən oxu 6. Sifarişi GÖNDƏRMƏ | F35: Sumqayıt seçildikdə rayon çatdırılma şərtləri ('Çatdırılma və ödəniş' səhifəsinə görə: rayon tarifi, 2–3 iş günü, tam ön ödəniş) göstərilir; Bakı seçildikdə mesaj Bakı şərtlərinə qayıdır | G35: Hər iki şəhərdə eyni mesaj qalır: 'Sifarişin məbləği 300 AZN-ə qədər olduqda, çatdırılma qiyməti 3 AZN-dən başlayır (yerindən asılı olaraq)'. Rayon müştərisi tam ön ödəniş tələbi və rayon tarifi haqqında məlumat almır (11.10 icrası) | H35: Medium | I35: P3 | J35: 1/1 | K35: New | L35: Ekran görüntüsü (Sumqayıt və Bakı seçimi) | M35: TC_CHK_POS_007
A36: BUG-032 | B36: Qoruma proqramının qiyməti məhsul səhifəsində və səbətdə fərqlidir (539 ₼ → 538 ₼) | C36: Səbət / Məhsul səhifəsi (PDP) | D36: Production · Chrome (son) · Windows/macOS desktop · inkognito · AZ dili | E36: 1. 'Mövcuddur' filtrli iPhone siyahısından ilk məhsulu aç (16.10: iPhone 18 Pro, 256 GB, Qara — 3 589 ₼) 2. 'Məhsulunuzu qoruyun' bölməsində '+1 il zədələrə qarşı qorunma' qiymətini qeyd et və seç 3. 'Səbətə' → 'Səbətimə baxın' 4. Səbətdə proqramın qiymətini və 'Cəmi'ni müqayisə et | F36: Proqramın qiyməti bütün ekranlarda eynidir; Cəmi = məhsul + PDP-də göstərilən proqram qiyməti (3 589 + 539 = 4 128 ₼) | G36: PDP-də proqram 539 ₼, səbətdə 538 ₼; 'Cəmi' 4 127 ₼ (3 589 + 538). Ehtimal: 15% × 3 589 = 538,35 ₼ — ekranlar fərqli yuvarlaqlaşdırır. Fərq 1 ₼-dır, amma müştəriyə göstərilən və hesablanan məbləğ uyğun gəlmir | H36: Medium | I36: P3 | J36: 1/1 (Gauge avtomat icrası) | K36: New | L36: Gauge HTML report, 16.10.2026 — TC_CART_POS_009 ekran görüntüsü (səbət: Cəmi 4 127 ₼) | M36: TC_CART_POS_009, TC_PDP_POS_008

Sheet Test Summary Report
A1: Test Summary Report — iSpace.az (Web, manual + avtomat)
A4: 1. Ümumi məlumat
A5: Test obyekti | B5: iSpace.az — Kateqoriya və filtrlər (PLP), Məhsul səhifəsi (PDP), Taksit proqramları, Səbət, Checkout (göndərmədən), Axtarış, Lokalizasiya, Xidmət səhifələri (Trade In, Çatdırılma və ödəniş)
A6: Mühit | B6: Production · Google Chrome (son versiya) · inkognito · desktop 1920×1080 · AZ dili · login olmadan
A7: Növ | B7: Manual funksional, neqativ, sərhəd (BVA), edge case, UI və lokalizasiya testləri; scope Test Plan sheet-indədir; regression dəsti Gauge ilə avtomatlaşdırılıb (bölmə 7)
A8: 2. İcra nəticələri
A9: Göstərici | B9: Dəyər
A10: Planlaşdırılmış test case | B10: =COUNTA('Web Test Cases'!$A$5:$A$130) -> 126
A11: İcra olunub | B11: =COUNTA('Web Test Cases'!$A$5:$A$130)-COUNTIF('Web Test Cases'!$L$5:$L$130,"Not Run") -> 126
A12: Pass | B12: =COUNTIF('Web Test Cases'!$L$5:$L$130,"Pass") -> 107
A13: Fail | B13: =COUNTIF('Web Test Cases'!$L$5:$L$130,"Fail") -> 19
A14: Blocked | B14: =COUNTIF('Web Test Cases'!$L$5:$L$130,"Blocked") -> 0
A15: Pass rate (icra olunanlardan) | B15: =IF(B11=0,0,B12/B11) -> 0.84920635
A16: İcra əhatəsi | B16: =IF(B10=0,0,B11/B10) -> 1
A18: Modul | B18: Case | C18: Pass | D18: Fail | E18: Blocked | F18: Pass rate
A19: Kateqoriya (PLP) | B19: =COUNTIF('Web Test Cases'!$C$5:$C$130,A19) -> 46 | C19: =COUNTIFS('Web Test Cases'!$C$5:$C$130,A19,'Web Test Cases'!$L$5:$L$130,"Pass") -> 42 | D19: =COUNTIFS('Web Test Cases'!$C$5:$C$130,A19,'Web Test Cases'!$L$5:$L$130,"Fail") -> 4 | E19: =COUNTIFS('Web Test Cases'!$C$5:$C$130,A19,'Web Test Cases'!$L$5:$L$130,"Blocked") -> 0 | F19: =IF((C19+D19+E19)=0,0,C19/(C19+D19+E19)) -> 0.91304348
A20: Məhsul səhifəsi (PDP) | B20: =COUNTIF('Web Test Cases'!$C$5:$C$130,A20) -> 12 | C20: =COUNTIFS('Web Test Cases'!$C$5:$C$130,A20,'Web Test Cases'!$L$5:$L$130,"Pass") -> 12 | D20: =COUNTIFS('Web Test Cases'!$C$5:$C$130,A20,'Web Test Cases'!$L$5:$L$130,"Fail") -> 0 | E20: =COUNTIFS('Web Test Cases'!$C$5:$C$130,A20,'Web Test Cases'!$L$5:$L$130,"Blocked") -> 0 | F20: =IF((C20+D20+E20)=0,0,C20/(C20+D20+E20)) -> 1
A21: Taksit proqramları | B21: =COUNTIF('Web Test Cases'!$C$5:$C$130,A21) -> 16 | C21: =COUNTIFS('Web Test Cases'!$C$5:$C$130,A21,'Web Test Cases'!$L$5:$L$130,"Pass") -> 10 | D21: =COUNTIFS('Web Test Cases'!$C$5:$C$130,A21,'Web Test Cases'!$L$5:$L$130,"Fail") -> 6 | E21: =COUNTIFS('Web Test Cases'!$C$5:$C$130,A21,'Web Test Cases'!$L$5:$L$130,"Blocked") -> 0 | F21: =IF((C21+D21+E21)=0,0,C21/(C21+D21+E21)) -> 0.625
A22: Səbət | B22: =COUNTIF('Web Test Cases'!$C$5:$C$130,A22) -> 30 | C22: =COUNTIFS('Web Test Cases'!$C$5:$C$130,A22,'Web Test Cases'!$L$5:$L$130,"Pass") -> 27 | D22: =COUNTIFS('Web Test Cases'!$C$5:$C$130,A22,'Web Test Cases'!$L$5:$L$130,"Fail") -> 3 | E22: =COUNTIFS('Web Test Cases'!$C$5:$C$130,A22,'Web Test Cases'!$L$5:$L$130,"Blocked") -> 0 | F22: =IF((C22+D22+E22)=0,0,C22/(C22+D22+E22)) -> 0.9
A23: Checkout | B23: =COUNTIF('Web Test Cases'!$C$5:$C$130,A23) -> 7 | C23: =COUNTIFS('Web Test Cases'!$C$5:$C$130,A23,'Web Test Cases'!$L$5:$L$130,"Pass") -> 4 | D23: =COUNTIFS('Web Test Cases'!$C$5:$C$130,A23,'Web Test Cases'!$L$5:$L$130,"Fail") -> 3 | E23: =COUNTIFS('Web Test Cases'!$C$5:$C$130,A23,'Web Test Cases'!$L$5:$L$130,"Blocked") -> 0 | F23: =IF((C23+D23+E23)=0,0,C23/(C23+D23+E23)) -> 0.57142857
A24: Axtarış | B24: =COUNTIF('Web Test Cases'!$C$5:$C$130,A24) -> 7 | C24: =COUNTIFS('Web Test Cases'!$C$5:$C$130,A24,'Web Test Cases'!$L$5:$L$130,"Pass") -> 7 | D24: =COUNTIFS('Web Test Cases'!$C$5:$C$130,A24,'Web Test Cases'!$L$5:$L$130,"Fail") -> 0 | E24: =COUNTIFS('Web Test Cases'!$C$5:$C$130,A24,'Web Test Cases'!$L$5:$L$130,"Blocked") -> 0 | F24: =IF((C24+D24+E24)=0,0,C24/(C24+D24+E24)) -> 1
A25: Lokalizasiya | B25: =COUNTIF('Web Test Cases'!$C$5:$C$130,A25) -> 5 | C25: =COUNTIFS('Web Test Cases'!$C$5:$C$130,A25,'Web Test Cases'!$L$5:$L$130,"Pass") -> 2 | D25: =COUNTIFS('Web Test Cases'!$C$5:$C$130,A25,'Web Test Cases'!$L$5:$L$130,"Fail") -> 3 | E25: =COUNTIFS('Web Test Cases'!$C$5:$C$130,A25,'Web Test Cases'!$L$5:$L$130,"Blocked") -> 0 | F25: =IF((C25+D25+E25)=0,0,C25/(C25+D25+E25)) -> 0.4
A26: Xidmət səhifələri | B26: =COUNTIF('Web Test Cases'!$C$5:$C$130,A26) -> 3 | C26: =COUNTIFS('Web Test Cases'!$C$5:$C$130,A26,'Web Test Cases'!$L$5:$L$130,"Pass") -> 3 | D26: =COUNTIFS('Web Test Cases'!$C$5:$C$130,A26,'Web Test Cases'!$L$5:$L$130,"Fail") -> 0 | E26: =COUNTIFS('Web Test Cases'!$C$5:$C$130,A26,'Web Test Cases'!$L$5:$L$130,"Blocked") -> 0 | F26: =IF((C26+D26+E26)=0,0,C26/(C26+D26+E26)) -> 1
A28: 3. Defektlər (təsdiqlənmiş, status = New)
A29: Severity | B29: Say
A30: Critical | B30: =COUNTIFS('Bug Reports'!$H$5:$H$39,"Critical",'Bug Reports'!$K$5:$K$39,"New") -> 0
A31: High | B31: =COUNTIFS('Bug Reports'!$H$5:$H$39,"High",'Bug Reports'!$K$5:$K$39,"New") -> 1
A32: Medium | B32: =COUNTIFS('Bug Reports'!$H$5:$H$39,"Medium",'Bug Reports'!$K$5:$K$39,"New") -> 9
A33: Low | B33: =COUNTIFS('Bug Reports'!$H$5:$H$39,"Low",'Bug Reports'!$K$5:$K$39,"New") -> 7
A34: Təkrar yoxlanılmalı | B34: =COUNTIF('Bug Reports'!$K$5:$K$39,"Təkrar yoxlanılmalı")+COUNTIF('Bug Reports'!$K$5:$K$39,"Məlumat lazımdır") -> 0
A35: Bağlanıb (Rejected / Duplicate) | B35: =COUNTIF('Bug Reports'!$K$5:$K$39,"Rejected*")+COUNTIF('Bug Reports'!$K$5:$K$39,"Duplicate*") -> 15
A37: 4. Əsas tapıntılar
A38: • Əsas alış axını (kateqoriya → məhsul → səbət) işləyir: səbətə əlavə, miqdar, silmə və cəm hesablaması Pass oldu; Critical severity-li defekt tapılmadı.
A39: • Ən riskli sahə — qiymət, endirim və taksit məlumatının ekranlar arasında ardıcıllığı: eyni məhsul və eyni səbət üçün fərqli ekranlarda fərqli məbləğlər göstərilir (məs. BUG-032: qoruma proqramı PDP-də 539 ₼, səbətdə 538 ₼).
A40: • BUG-030 (High): checkout-da 300 ₼-dan az səbətdə kuryer haqqı mesajda yazılır, xülasədə isə 'Çatdırılma: Ödənişsiz' qalır və 'Ödəmək' dəyişmir.
A41: • BUG-024: səbətdə '−15% VİSA' endirimi şərtsiz qiymət kimi göstərilir (AirPods 289 → 246 ₼), taksit pəncərəsində isə 289 ₼ — eyni səbətin iki cəmi (3 835 və 3 878 ₼).
A42: • BUG-017: taksit pəncərəsində 'aylıq × ödəniş sayı' heç bir müddətdə ümumi məbləğə bərabər deyil (iPhone 18 Pro: 199 × 18 = 3 582 ≠ 3 589 ₼; Beosound A9: 667 × 9 = 6 003 ≠ 5 999 ₼). BUG-016: 9 ₼-lıq keysdə '1 ₼ × 18' = 18 ₼.
A43: • BUG-029: müddət düyməsindəki aylıq məbləğ seçilmiş tərəfdaşa görə yenilənmir — Leobank seçili ikən düymədə UCard-ın 199 ₼-ı qalır (Leobank: 217 ₼).
A44: • Səbət və checkout: BUG-027 (ön sifariş məhsulu xəbərdarlıqsız eyni səbətə düşür), BUG-028 (checkout-dakı çatdırılma qiyməti 'Çatdırılma və ödəniş' səhifəsi ilə uyğun deyil), BUG-031 (Bakıdan kənar şəhər seçildikdə rayon çatdırılma şərtləri göstərilmir).
A45: • Filtr və lokalizasiya: BUG-021 (filtr dəyəri PDP göstəricisi ilə uyğun deyil), BUG-022 (dil dəyişəndə filtrlər silinir), BUG-011, BUG-020, BUG-023 (tərcümə olunmamış mətnlər).
A47: 5. Müşahidələr və təkmilləşdirmə təklifləri (bug deyil)
A48: ID | B48: Müşahidə | F48: Mənbə
A49: OBS-01 | B49: Qiymət filtrində min > max olduqda ümumi 'Məhsul tapılmadı' göstərilir; səbəbi izah edən mesaj və ya dəyərlərin avtomatik yer dəyişməsi daha yaxşı olardı. | F49: TC_PLP_NEG_017
A50: OBS-02 | B50: Şəkil böyüdüləndə ayrıca şəkil yox, bütün səhifə böyüyür; lightbox/zoom tövsiyə olunur. | F50: Kəşf (EXP-04)
A51: OBS-03 | B51: 'airp' qismən sorğusunda AirPods ilə yanaşı adında 'Air' olan digər məhsullar da göstərilir — relevantlıq sıralaması yaxşılaşdırıla bilər. | F51: TC_SRCH_POS_003
A52: OBS-04 | B52: Düzgün söz + xüsusi simvol sorğusu ('iphone "17" & %') nəticə vermir; simvolların təmizlənməsi tövsiyə olunur. | F52: TC_SRCH_NEG_007
A53: OBS-05 | B53: Stokda olmayan məhsullarda 'Ön sifariş' və 'Mənə xəbər ver' düymələrinin seçilmə məntiqi açıq deyil. | F53: TC_PDP_UI_012
A54: OBS-06 | B54: Səbətdə '+' düyməsi kliklərə gecikmə ilə reaksiya verir; ardıcıl kliklərdə istifadəçi nəticəni gec görür. | F54: TC_CART_EDGE_014
A55: OBS-07 | B55: 'Məhsul tipi' filtrinin yalnız bir dəyəri var və nəticəni dəyişmir — istifadəçiyə fayda verməyən qrupun gizlədilməsi tövsiyə olunur. | F55: Kəşf (EXP-02)
A56: 6. Açıq məsələlər və risklər
A57: • BUG-003 (səbət sayğacı '4') təmiz sessiyada təkrar yoxlandı (TC_CART_EDGE_025, TC_CART_EDGE_028 — Pass): səbəb əvvəlki case-lərdən qalan səbət idi → Rejected. Nəticə: hər səbət case-i yeni inkognito sessiyada başlayır.
A58: • 10.10 təkrar yoxlamasında BUG-002 (qoruma proqramının ləğvi), BUG-007 ('1 kliklə al' validasiyası), BUG-018 (endirimli məhsulun taksiti) və BUG-026 (mini-səbətdə variant) təkrarlanmadı → Rejected. Açıq təkrar yoxlama qalmayıb.
A59: • İcradan əvvəlki müşahidələrdən icrada təsdiqlənməyənlər (BUG-001, BUG-008, BUG-009, BUG-010, BUG-012, BUG-013, BUG-014, BUG-015, BUG-019) Rejected edildi; BUG-004 BUG-003-nın dublikatıdır. Naviqasiya modulu scope-dan çıxarıldı.
A60: • Checkout: prodda real sifariş riski səbəbindən yalnız göndərmədən yoxlanıla bilən case-lər icra olundu (telefon və e-poçt validasiyası, çatdırılma haqqı); sifariş göndərilmədi. Tapıntılar: BUG-025, BUG-028, BUG-030. İcra edilməmiş 17 case (taksit və səbət) və digər checkout case-ləri dəstdən çıxarılıb.
A61: • Prod mühitində test: stok və qiymətlər dəyişkəndir, ona görə avtomat testlər konkret dəyərə deyil, uyğunluq qaydalarına (BR — RTM-də) əsaslanır.
A62: 7. Avtomatlaşdırmaya təsiri
A63: • Regression dəsti 40 case-dir; manual icrada 37-i Pass. 16.10.2026 tarixinə 38-i (95%) Gauge ilə avtomatlaşdırılıb: 35-i Pass, 3-ü bilinən bug səbəbindən gözlənildiyi kimi FAIL olur və 'known-bug' tag-ı ilə ayrılır (TC_FIN_POS_003 / BUG-017, TC_FIN_BVA_006 / BUG-016, TC_CART_POS_009 / BUG-032). TC_CART_POS_012 və TC_FIN_POS_016 prod-da real sifariş/maliyyə axınına girdiyi üçün manual regression kimi qalır. Regression-dan kənar 13 case də avtomatlaşdırılıb — ümumilikdə 126 case-dən 51-i (40%) avtomatdır.
A64: • Fail olan regression case-lərin hamısı pul məbləği ilə bağlıdır (taksit və səbət) — avtomat testlərdə bu sahə dəqiq hesablama assertion-ları ilə yoxlanılır (qiymət × miqdar, sətirlərin cəmi, aylıq × ödəniş sayı). Avtomat icra yeni bug tapdı: BUG-032 (qoruma proqramının qiyməti PDP-də 539 ₼, səbətdə 538 ₼).
A65: • Fail olan manual case-lər (lokalizasiya, checkout) regression-a daxil deyil; onların bug-ları düzəldiləndə təkrar yoxlama manual aparılır.
A66: • Səbət avtomat testləri hər ssenaridə təmiz brauzer sessiyası ilə işləyir. 15.10: iSpace məhsul səhifəsində A/B test (GrowthBook 'pdp_v2') başlatdı və səbət səhifəsinin HTML-ini dəyişdi — testlərin bir hissəsi düşdü. Düzəliş: A/B variantı cookie ilə sabitləndi (gb-exp = pdp_v2:0), səbət locator-ları yeniləndi, səbət/PDP testləri konkret məhsul URL-i əvəzinə 'Mövcuddur' siyahısından ilk məhsulla işləyir (stokdan asılı deyil). 16.10: A/B variantı bəzən yenə dəyişdiyi üçün 'görünənə qədər A/B testini köhnə dizayna qaytar' addımı əlavə olundu (cookie yenidən qoyulur, ən çox 3 cəhd); konkret məhsula bağlı TC_PDP_POS_004 stokdakı variantın icra zamanı seçilməsinə keçirildi. Son icra 16.10.2026: 48 Pass + 3 known-bug gözlənilən FAIL.
A68: 8. Nəticə
A69: Saytın əsas alış axını (kataloq → məhsul → səbət) işləyir və Critical severity-li defekt tapılmadı. Ən zəif sahə qiymət, endirim, taksit və çatdırılma məbləğlərinin ekranlar arasında ardıcıllığıdır (BUG-016, BUG-017, BUG-024, BUG-029, BUG-030, BUG-032) — bunlar müştərinin ödəyəcəyi məbləğ barədə yanlış təsəvvür yaradır. Release öncəsi düzəldilməsi tövsiyə olunanlar: BUG-030 (High), BUG-024, BUG-017 və BUG-016 (P2), sonra BUG-029, BUG-021, BUG-022.
